Workbook

Sheet Registo de operações
M2: Fundos iniciais | Q2: Mov. Add. Fundos | R2: Profit | S2: Current Funds | U2: Risk | V2: Total | Y2: Average | AC2: Comissões | AD2: Swaps | AE2: Capital liquido Gerado | AF2: Efective % (W. Add. Funds) | AG2: RRR Liquido Realizado
E3: Nº Op | F3: % Win | G3: Win | H3: Lose | I3: In | V3: Win | W3: Loss | X3: Total | Y3: Win | Z3: Loss | AA3: Total
E4: =COUNTA(U11:U211) -> 77 | F4: =G4/100%/(E4-I4) -> 0.38961039 | G4: =COUNTIF(M11:M211,"W") -> 30 | H4: =COUNTIF(M11:M211,"L") -> 47 | I4: =E4-G4-H4 -> 0 | M4: 5000 | Q4: 0 | R4: =SUM((X5)+(AD4)+(AC4)) -> 2430.7179 | S4: =SUM((M4)+(Q4)+(R4)) -> 7430.7179 | U4: 0.01 | V4: =Pontuação!B2 -> 0.86933381 | W4: =Pontuação!C2 -> -0.47 | X4: =SUM(Tabela2[[Ganhos %]:[Perdas %]]) -> 0.39933381 | Y4: =Pontuação!B3 -> 0.028977794 | Z4: =Pontuação!C3 -> -0.01 | AA4: =AVERAGE(Tabela2[[Ganhos %]:[Perdas %]]) -> 0.0051861534 | AC4: =SUM(AE11:AE211) -> 2.32 | AD4: =SUM(AF11:AF211) -> 86.37 | AE4: =SUM((V5)+(W5)+(AC4)+(AD4)) -> 2430.7179 | AF4: =SUM((AE4*100)/(M4+Q4))/100 -> 0.48614358 | AG4: =SUM(AK11:AK211) -> 0.41111098
V5: =Pontuação!D2 -> 5633.3383 | W5: =Pontuação!E2 -> -3291.3104 | X5: =SUM(Tabela2[[Ganhos €]:[Perdas €]]) -> 2342.0279 | Y5: =Pontuação!D3 -> 187.77794 | Z5: =Pontuação!E3 -> -70.02788 | AA5: =AVERAGE(Tabela2[[Ganhos €]:[Perdas €]]) -> 30.415947
B7: TIPO | C7: Nº T | D7: Nº S | E7: Dia da semana | F7: DATA | G7: Hora | H7: Grupo | I7: Par/Produto | J7: Estratégia | K7: Marco Temporal | L7: Tipo de entrada | M7: W L | N7: E | O7: G | P7: S | Q7: Starting Position | V7: Stop Loss | Y7: Take Profit | AC7: Close Position | AL7: Balanço de conta depois do trade
Q8: Account Funds (antes do trade) | R8: € Risk | S8: % Risk | T8: Lot | U8: Position entry | V8: Max Loss | W8: Pips | X8: € Loss | Y8: Take Profit | Z8: Pips | AA8: € Gain | AB8: RRR | AC8: Day Close | AD8: Closing price | AE8: Comissão | AF8: Swap | AG8: Lucro | AH8: Lucro liquido | AI8: Pips Close | AJ8: RRR Realizado | AK8: RRR Liquido | BH8: Currency | BI8: Grup | BJ8: Avaliação das Entradas:
A9: , | AR9: Sentido | AS9: Day W | AT9: Hora | AU9: Estrategia | AV9: Time Frame | AW9: W L | AX9: O C | AY9: News | AZ9: Candle | BA9: Grup | BB9: Emotional state
AR10: Short | AS10: 2ª F | AT10: Manhã | AU10: Retest | AV10: 1D | AW10: W | AX10: O | AY10: Yes | AZ10: Open | BA10: Majors | BB10: Impatience | BC10: x | BD10: 0 | BE10: 0 | BF10: -1 | BG10: x | BH10: EURUSD | BI10: =$BA$10 -> Majors
B11: Backtesting | C11: =C10+1 -> 1 | D11: 5 | E11: 2ª F | F11: 30 de Janeiro | G11: Tarde | I11: AUDNZD | J11: Breakout | K11: 3m | L11: short | M11: L | Q11: 5000 | R11: =IF(Q11="","",S11*Q11/100%) -> 50 | S11: 0.01 | T11: 0.01 | U11: 1.09209 | V11: 1.09317 | W11: =IF(V11="","",IF(L11="Long",U11-V11,V11-U11)) -> 0.00108 | X11: =IF(W11="","",R11) -> 50 | Y11: 1.0895 | Z11: =IF(Y11="","",IF(L11="Long",Y11-U11,U11-Y11)) -> 0.00259 | AA11: =IF(AB11="","",AB11*X11/1) -> 119.90741 | AB11: =IF(Z11="","",Z11*1/W11) -> 2.3981481 | AC11: 30 de Janeiro | AD11: 1.09317 | AE11: 0 | AF11: 0 | AG11: =-X11 -> -50 | AH11: =IF(AG11="","",AG11+AF11+AE11) -> -50 | AI11: =IF(AD11="","",IF(L11="Long",AD11-U11,U11-AD11)) -> -0.00108 | AJ11: =IF(AI11="","",AG11*S11/X11) -> -0.01 | AK11: =IF(AI11="","",(AG11+AF11+AE11)*S11/X11) -> -0.01 | AL11: =Q11+AG11 -> 4950 | AR11: Long | AS11: 3ª F | AT11: Tarde | AU11: Breakout | AV11: 12h | AW11: L | AX11: C | AY11: No | AZ11: Close | BA11: Minors | BB11: Fear | BD11: 0.1 | BE11: 0.1 | BF11: 0 | BH11: AUDUSD | BI11: =$BA$10 -> Majors | BL11: A | BM11: Boa entrada - Com estratégia - No timming Correto - Boa probabilidade
B12: Backtesting | C12: =C11+1 -> 2 | D12: 5 | E12: 2ª F | F12: 30 de Janeiro | G12: Tarde | I12: GBPUSD | J12: Breakout | K12: 1m | L12: long | M12: L | Q12: =AL11 -> 4950 | R12: =IF(Q12="","",S12*Q12/100%) -> 49.5 | S12: 0.01 | T12: 0.01 | U12: 1.24002 | V12: 1.23976 | W12: =IF(V12="","",IF(L12="Long",U12-V12,V12-U12)) -> 0.00026 | X12: =IF(W12="","",R12) -> 49.5 | Y12: 1.2408 | Z12: =IF(Y12="","",IF(L12="Long",Y12-U12,U12-Y12)) -> 0.00078 | AA12: =IF(AB12="","",AB12*X12/1) -> 148.5 | AB12: =IF(Z12="","",Z12*1/W12) -> 3 | AC12: 30 de Janeiro | AD12: 1.23976 | AE12: 0 | AF12: 0 | AG12: =-X12 -> -49.5 | AH12: =IF(AG12="","",AG12+AF12+AE12) -> -49.5 | AI12: =IF(AD12="","",IF(L12="Long",AD12-U12,U12-AD12)) -> -0.00026 | AJ12: =IF(AI12="","",AG12*S12/X12) -> -0.01 | AK12: =IF(AI12="","",(AG12+AF12+AE12)*S12/X12) -> -0.01 | AL12: =Q12+AG12 -> 4900.5 | AS12: 4ª F | AT12: Noite | AU12: Bandeira | AV12: 8h | AY12: n/a | AZ12: Next | BA12: Exotics | BB12: Greed | BD12: 0.2 | BE12: 0.2 | BF12: 1 | BH12: GBPCHF | BI12: =$BA$10 -> Majors | BL12: B | BM12: Boa entrada - Com alguma estratégia - Alguma Probabilidade
B13: Backtesting | C13: =C12+1 -> 3 | D13: 5 | E13: 2ª F | F13: 30 de Janeiro | G13: Tarde | I13: CADJPY | J13: Breakout | K13: 1m | L13: long | M13: W | Q13: =AL12 -> 4900.5 | R13: =IF(Q13="","",S13*Q13/100%) -> 49.005 | S13: 0.01 | T13: 0.02 | U13: 97.502 | V13: 97.445 | W13: =IF(V13="","",IF(L13="Long",U13-V13,V13-U13)) -> 0.057 | X13: =IF(W13="","",R13) -> 49.005 | Y13: 97.675 | Z13: =IF(Y13="","",IF(L13="Long",Y13-U13,U13-Y13)) -> 0.173 | AA13: =IF(AB13="","",AB13*X13/1) -> 148.73447 | AB13: =IF(Z13="","",Z13*1/W13) -> 3.0350877 | AC13: 30 de Janeiro | AD13: 97.675 | AE13: 0 | AF13: 0 | AG13: =+AA13 -> 148.73447 | AH13: =IF(AG13="","",AG13+AF13+AE13) -> 148.73447 | AI13: =IF(AD13="","",IF(L13="Long",AD13-U13,U13-AD13)) -> 0.173 | AJ13: =IF(AI13="","",AG13*S13/X13) -> 0.030350877 | AK13: =IF(AI13="","",(AG13+AF13+AE13)*S13/X13) -> 0.030350877 | AL13: =Q13+AG13 -> 5049.2345 | AS13: 5ª F | AU13: Continuation | AV13: 4h | AZ13: n/a | BA13: Indices | BB13: Hope | BD13: 0.3 | BE13: 0.3 | BF13: 2 | BH13: GBPUSD | BI13: =$BA$10 -> Majors | BL13: C | BM13: Razoavél - Com alguma estratégia - Mas impulsiva
B14: Testing em tempo real | C14: =C13+1 -> 4 | D14: 5 | E14: 3ª F | F14: 31 de janeiro | G14: Manhã | I14: GBPUSD | J14: Breakout | K14: 3m | L14: short | M14: W | Q14: =AL13 -> 5049.2345 | R14: =IF(Q14="","",S14*Q14/100%) -> 50.492345 | S14: 0.01 | T14: 0.5 | U14: 1.23495 | V14: 1.23657 | W14: =IF(V14="","",IF(L14="Long",U14-V14,V14-U14)) -> 0.00162 | X14: =IF(W14="","",R14) -> 50.492345 | Y14: 1.23006 | Z14: =IF(Y14="","",IF(L14="Long",Y14-U14,U14-Y14)) -> 0.00489 | AA14: =IF(AB14="","",AB14*X14/1) -> 152.41208 | AB14: =IF(Z14="","",Z14*1/W14) -> 3.0185185 | AC14: 31 de janeiro | AD14: 1.23006 | AE14: 0 | AF14: 0 | AG14: =+AA14 -> 152.41208 | AH14: =IF(AG14="","",AG14+AF14+AE14) -> 152.41208 | AI14: =IF(AD14="","",IF(L14="Long",AD14-U14,U14-AD14)) -> 0.00489 | AJ14: =IF(AI14="","",AG14*S14/X14) -> 0.030185185 | AK14: =IF(AI14="","",(AG14+AF14+AE14)*S14/X14) -> 0.030185185 | AL14: =Q14+AG14 -> 5201.6466 | AS14: 6ª F | AV14: 2h | BA14: Commod | BB14: Confidence | BD14: 0.4 | BE14: 0.4 | BF14: 3 | BH14: USDCAD | BI14: =$BA$10 -> Majors | BL14: D | BM14: Má entrada - Sem estratégia e impulsiva
B15: Testing em tempo real | C15: =C14+1 -> 5 | D15: 5 | E15: 5ª F | F15: 2 de Fevereiro | G15: Manhã | J15: Breakout | K15: 15m | L15: short | M15: W | Q15: =AL14 -> 5201.6466 | R15: =IF(Q15="","",S15*Q15/100%) -> 52.016466 | S15: 0.01 | T15: 0.01 | U15: 83.291 | V15: 83.559 | W15: =IF(V15="","",IF(L15="Long",U15-V15,V15-U15)) -> 0.268 | X15: =IF(W15="","",R15) -> 52.016466 | Y15: 82.488 | Z15: =IF(Y15="","",IF(L15="Long",Y15-U15,U15-Y15)) -> 0.803 | AA15: =IF(AB15="","",AB15*X15/1) -> 155.85531 | AB15: =IF(Z15="","",Z15*1/W15) -> 2.9962687 | AC15: 2 de Fevereiro | AD15: 82.488 | AE15: 0 | AF15: 0 | AG15: =+AA15 -> 155.85531 | AH15: =IF(AG15="","",AG15+AF15+AE15) -> 155.85531 | AI15: =IF(AD15="","",IF(L15="Long",AD15-U15,U15-AD15)) -> 0.803 | AJ15: =IF(AI15="","",AG15*S15/X15) -> 0.029962687 | AK15: =IF(AI15="","",(AG15+AF15+AE15)*S15/X15) -> 0.029962687 | AL15: =Q15+AG15 -> 5357.5019 | AV15: 1h | BB15: Uncertainty | BD15: 0.5 | BE15: 0.5 | BF15: 4 | BH15: USDCHF | BI15: =$BA$10 -> Majors
B16: Backtesting | C16: =C15+1 -> 6 | D16: 5 | E16: 6ª F | F16: 3 de Fevereiro | G16: Manhã | I16: EURUSD | J16: Breakout | K16: 1m | L16: long | M16: L | Q16: =AL15 -> 5357.5019 | R16: =IF(Q16="","",S16*Q16/100%) -> 53.575019 | S16: 0.01 | T16: 0.03 | U16: 1.08959 | V16: 1.08936 | W16: =IF(V16="","",IF(L16="Long",U16-V16,V16-U16)) -> 0.00023 | X16: =IF(W16="","",R16) -> 53.575019 | Y16: 1.09028 | Z16: =IF(Y16="","",IF(L16="Long",Y16-U16,U16-Y16)) -> 0.00069 | AA16: =IF(AB16="","",AB16*X16/1) -> 160.72506 | AB16: =IF(Z16="","",Z16*1/W16) -> 3 | AC16: 3 de Fevereiro | AD16: 1.08936 | AE16: 0 | AF16: 0 | AG16: =-X16 -> -53.575019 | AH16: =IF(AG16="","",AG16+AF16+AE16) -> -53.575019 | AI16: =IF(AD16="","",IF(L16="Long",AD16-U16,U16-AD16)) -> -0.00023 | AJ16: =IF(AI16="","",AG16*S16/X16) -> -0.01 | AK16: =IF(AI16="","",(AG16+AF16+AE16)*S16/X16) -> -0.01 | AL16: =Q16+AG16 -> 5303.9268 | AV16: 30m | BB16: Serene | BD16: 0.6 | BE16: 0.6 | BF16: 5 | BH16: USDJPY | BI16: =$BA$10 -> Majors | BJ16: Avaliação da Gestão
B17: Backtesting | C17: =C16+1 -> 7 | D17: 5 | E17: 6ª F | F17: 3 de Fevereiro | G17: Tarde | I17: AUDCHF | J17: Breakout | K17: 5m | L17: short | M17: W | Q17: =AL16 -> 5303.9268 | R17: =IF(Q17="","",S17*Q17/100%) -> 53.039268 | S17: 0.01 | T17: 0.01 | U17: 0.64558 | V17: 0.64653 | W17: =IF(V17="","",IF(L17="Long",U17-V17,V17-U17)) -> 0.00095 | X17: =IF(W17="","",R17) -> 53.039268 | Y17: 0.6427 | Z17: =IF(Y17="","",IF(L17="Long",Y17-U17,U17-Y17)) -> 0.00288 | AA17: =IF(AB17="","",AB17*X17/1) -> 160.79273 | AB17: =IF(Z17="","",Z17*1/W17) -> 3.0315789 | AC17: 3 de Fevereiro | AD17: 0.6427 | AE17: 0 | AF17: 0 | AG17: =+AA17 -> 160.79273 | AH17: =IF(AG17="","",AG17+AF17+AE17) -> 160.79273 | AI17: =IF(AD17="","",IF(L17="Long",AD17-U17,U17-AD17)) -> 0.00288 | AJ17: =IF(AI17="","",AG17*S17/X17) -> 0.030315789 | AK17: =IF(AI17="","",(AG17+AF17+AE17)*S17/X17) -> 0.030315789 | AL17: =Q17+AG17 -> 5464.7196 | AV17: 15m | BD17: 0.7 | BE17: 0.7 | BF17: 6 | BH17: AUDCAD | BI17: =$BA$11 -> Minors | BL17: A | BM17: Trailing Stop com a sequência de máximos e minimos - Confortável com a posição - Posição encaminhada
B18: Backtesting | C18: =C17+1 -> 8 | D18: 5 | E18: 6ª F | F18: 3 de Fevereiro | G18: Tarde | J18: Breakout | K18: 3m | L18: short | M18: L | Q18: =AL17 -> 5464.7196 | R18: =IF(Q18="","",S18*Q18/100%) -> 54.647196 | S18: 0.01 | T18: 0.05 | U18: 0.68277 | V18: 0.68325 | W18: =IF(V18="","",IF(L18="Long",U18-V18,V18-U18)) -> 0.00048 | X18: =IF(W18="","",R18) -> 54.647196 | Y18: 0.68161 | Z18: =IF(Y18="","",IF(L18="Long",Y18-U18,U18-Y18)) -> 0.00116 | AA18: =IF(AB18="","",AB18*X18/1) -> 132.06406 | AB18: =IF(Z18="","",Z18*1/W18) -> 2.4166667 | AC18: 3 de Fevereiro | AD18: 0.68325 | AE18: 0 | AF18: 0 | AG18: =-X18 -> -54.647196 | AH18: =IF(AG18="","",AG18+AF18+AE18) -> -54.647196 | AI18: =IF(AD18="","",IF(L18="Long",AD18-U18,U18-AD18)) -> -0.00048 | AJ18: =IF(AI18="","",AG18*S18/X18) -> -0.01 | AK18: =IF(AI18="","",(AG18+AF18+AE18)*S18/X18) -> -0.01 | AL18: =Q18+AG18 -> 5410.0724 | AV18: 5m | BD18: 0.8 | BE18: 0.8 | BF18: 7 | BH18: AUDCHF | BI18: =$BA$11 -> Minors | BL18: B | BM18: Trailing Stop com a sequência de máximos e minimos - Preocupação com a posição - Posição a perder estrutura
B19: Backtesting | C19: =C18+1 -> 9 | D19: 5 | E19: 6ª F | F19: 3 de Fevereiro | G19: Tarde | I19: EURAUD | J19: Breakout | K19: 3m | L19: long | M19: W | Q19: =AL18 -> 5410.0724 | R19: =IF(Q19="","",S19*Q19/100%) -> 54.100724 | S19: 0.01 | T19: 0.03 | U19: 1.54298 | V19: 1.54138 | W19: =IF(V19="","",IF(L19="Long",U19-V19,V19-U19)) -> 0.0016 | X19: =IF(W19="","",R19) -> 54.100724 | Y19: 1.54783 | Z19: =IF(Y19="","",IF(L19="Long",Y19-U19,U19-Y19)) -> 0.00485 | AA19: =IF(AB19="","",AB19*X19/1) -> 163.99282 | AB19: =IF(Z19="","",Z19*1/W19) -> 3.03125 | AC19: 3 de Fevereiro | AD19: 1.54783 | AE19: 0 | AF19: 0 | AG19: =+AA19 -> 163.99282 | AH19: =IF(AG19="","",AG19+AF19+AE19) -> 163.99282 | AI19: =IF(AD19="","",IF(L19="Long",AD19-U19,U19-AD19)) -> 0.00485 | AJ19: =IF(AI19="","",AG19*S19/X19) -> 0.0303125 | AK19: =IF(AI19="","",(AG19+AF19+AE19)*S19/X19) -> 0.0303125 | AL19: =Q19+AG19 -> 5574.0652 | AV19: 3m | BD19: 0.9 | BE19: 0.9 | BF19: 8 | BH19: AUDJPY | BI19: =$BA$11 -> Minors | BL19: C | BM19: Alteração do stop sem estratégia de máximos e minimos - Preocupação com a posição
B20: Testing em tempo real | C20: =C19+1 -> 10 | D20: 6 | E20: 2ª F | F20: 6 de Fevereiro | G20: Manhã | I20: AUDUSD | J20: Breakout | K20: 5m | L20: short | M20: W | Q20: =AL19 -> 5574.0652 | R20: =IF(Q20="","",S20*Q20/100%) -> 55.740652 | S20: 0.01 | T20: 0.05 | U20: 0.69251 | V20: 0.69434 | W20: =IF(V20="","",IF(L20="Long",U20-V20,V20-U20)) -> 0.00183 | X20: =IF(W20="","",R20) -> 55.740652 | Y20: 0.68799 | Z20: =IF(Y20="","",IF(L20="Long",Y20-U20,U20-Y20)) -> 0.00452 | AA20: =IF(AB20="","",AB20*X20/1) -> 137.67636 | AB20: =IF(Z20="","",Z20*1/W20) -> 2.4699454 | AC20: 6 de Fevereiro | AD20: 0.68799 | AE20: 0 | AF20: 0 | AG20: =+AA20 -> 137.67636 | AH20: =IF(AG20="","",AG20+AF20+AE20) -> 137.67636 | AI20: =IF(AD20="","",IF(L20="Long",AD20-U20,U20-AD20)) -> 0.00452 | AJ20: =IF(AI20="","",AG20*S20/X20) -> 0.024699454 | AK20: =IF(AI20="","",(AG20+AF20+AE20)*S20/X20) -> 0.024699454 | AL20: =Q20+AG20 -> 5711.7416 | AV20: 1S | BD20: 1 | BE20: 1 | BH20: AUDNZD | BI20: =$BA$11 -> Minors | BL20: D | BM20: Sem Gestão - Não Fechei após a 1ª/2ª vela negativa
B21: Backtesting | C21: =C20+1 -> 11 | D21: 6 | E21: 4ª F | F21: 8 de Fevereiro | G21: Noite | I21: USDSGD | J21: Breakout | K21: 5m | L21: long | M21: L | Q21: =AL20 -> 5711.7416 | R21: =IF(Q21="","",S21*Q21/100%) -> 57.117416 | S21: 0.01 | T21: 0.01 | U21: 1.32401 | V21: 1.32323 | W21: =IF(V21="","",IF(L21="Long",U21-V21,V21-U21)) -> 0.00078 | X21: =IF(W21="","",R21) -> 57.117416 | Y21: 1.32635 | Z21: =IF(Y21="","",IF(L21="Long",Y21-U21,U21-Y21)) -> 0.00234 | AA21: =IF(AB21="","",AB21*X21/1) -> 171.35225 | AB21: =IF(Z21="","",Z21*1/W21) -> 3 | AC21: 8 de Fevereiro | AD21: 1.32323 | AE21: 0 | AF21: 0 | AG21: =-X21 -> -57.117416 | AH21: =IF(AG21="","",AG21+AF21+AE21) -> -57.117416 | AI21: =IF(AD21="","",IF(L21="Long",AD21-U21,U21-AD21)) -> -0.00078 | AJ21: =IF(AI21="","",AG21*S21/X21) -> -0.01 | AK21: =IF(AI21="","",(AG21+AF21+AE21)*S21/X21) -> -0.01 | AL21: =Q21+AG21 -> 5654.6241 | AV21: 6h | BH21: CADCHF | BI21: =$BA$11 -> Minors
B22: Backtesting | C22: =C21+1 -> 12 | D22: 6 | E22: 4ª F | F22: 8 de Fevereiro | G22: Noite | I22: USDJPY | J22: Breakout | K22: 5m | L22: long | M22: L | Q22: =AL21 -> 5654.6241 | R22: =IF(Q22="","",S22*Q22/100%) -> 56.546241 | S22: 0.01 | T22: 0.22 | U22: 131.99 | V22: 131.596 | W22: =IF(V22="","",IF(L22="Long",U22-V22,V22-U22)) -> 0.394 | X22: =IF(W22="","",R22) -> 56.546241 | Y22: 133.5 | Z22: =IF(Y22="","",IF(L22="Long",Y22-U22,U22-Y22)) -> 1.51 | AA22: =IF(AB22="","",AB22*X22/1) -> 216.71275 | AB22: =IF(Z22="","",Z22*1/W22) -> 3.8324873 | AC22: 8 de Fevereiro | AD22: 131.596 | AE22: 0 | AF22: 0 | AG22: =-X22 -> -56.546241 | AH22: =IF(AG22="","",AG22+AF22+AE22) -> -56.546241 | AI22: =IF(AD22="","",IF(L22="Long",AD22-U22,U22-AD22)) -> -0.394 | AJ22: =IF(AI22="","",AG22*S22/X22) -> -0.01 | AK22: =IF(AI22="","",(AG22+AF22+AE22)*S22/X22) -> -0.01 | AL22: =Q22+AG22 -> 5598.0779 | AV22: 15s | BH22: CADJPY | BI22: =$BA$11 -> Minors | BJ22: Avaliação da Saída
B23: Backtesting | C23: =C22+1 -> 13 | D23: 7 | E23: 4ª F | F23: 15 de Fevereiro | G23: Manhã | J23: Breakout | K23: 1m | L23: short | M23: W | Q23: =AL22 -> 5598.0779 | R23: =IF(Q23="","",S23*Q23/100%) -> 55.980779 | S23: 0.01 | T23: 0.02 | U23: 0.69301 | V23: 0.69346 | W23: =IF(V23="","",IF(L23="Long",U23-V23,V23-U23)) -> 0.00045 | X23: =IF(W23="","",R23) -> 55.980779 | Y23: 0.69166 | Z23: =IF(Y23="","",IF(L23="Long",Y23-U23,U23-Y23)) -> 0.00135 | AA23: =IF(AB23="","",AB23*X23/1) -> 167.94234 | AB23: =IF(Z23="","",Z23*1/W23) -> 3 | AC23: 15 de Fevereiro | AD23: 0.69166 | AE23: 0 | AF23: 0 | AG23: =+AA23 -> 167.94234 | AH23: =IF(AG23="","",AG23+AF23+AE23) -> 167.94234 | AI23: =IF(AD23="","",IF(L23="Long",AD23-U23,U23-AD23)) -> 0.00135 | AJ23: =IF(AI23="","",AG23*S23/X23) -> 0.03 | AK23: =IF(AI23="","",(AG23+AF23+AE23)*S23/X23) -> 0.03 | AL23: =Q23+AG23 -> 5766.0202 | AV23: 1m | BH23: CHFJPY | BI23: =$BA$11 -> Minors | BL23: A | BM23: Take Profit no ponto definido inicialmente - saida automática
B24: Testing em tempo real | C24: =C23+1 -> 14 | D24: 7 | E24: 5ª F | F24: 16 de Fevereiro | G24: Manhã | I24: USDCAD | J24: Breakout | K24: 5m | L24: short | M24: W | Q24: =AL23 -> 5766.0202 | R24: =IF(Q24="","",S24*Q24/100%) -> 57.660202 | S24: 0.01 | T24: 0.07 | U24: 1.33704 | V24: 1.33808 | W24: =IF(V24="","",IF(L24="Long",U24-V24,V24-U24)) -> 0.00104 | X24: =IF(W24="","",R24) -> 57.660202 | Y24: 1.33359 | Z24: =IF(Y24="","",IF(L24="Long",Y24-U24,U24-Y24)) -> 0.00345 | AA24: =IF(AB24="","",AB24*X24/1) -> 191.27663 | AB24: =IF(Z24="","",Z24*1/W24) -> 3.3173077 | AC24: 16 de Fevereiro | AD24: 1.33359 | AE24: 0 | AF24: 0 | AG24: =+AA24 -> 191.27663 | AH24: =IF(AG24="","",AG24+AF24+AE24) -> 191.27663 | AI24: =IF(AD24="","",IF(L24="Long",AD24-U24,U24-AD24)) -> 0.00345 | AJ24: =IF(AI24="","",AG24*S24/X24) -> 0.033173077 | AK24: =IF(AI24="","",(AG24+AF24+AE24)*S24/X24) -> 0.033173077 | AL24: =Q24+AG24 -> 5957.2969 | BH24: EURAUD | BI24: =$BA$11 -> Minors | BL24: B | BM24: Stop-Win em trailing Sop com estratégia
B25: Backtesting | C25: =C24+1 -> 15 | D25: 7 | E25: 5ª F | F25: 16 de Fevereiro | G25: Manhã | I25: GBPJPY | J25: Breakout | K25: 1m | L25: long | M25: L | Q25: =AL24 -> 5957.2969 | R25: =IF(Q25="","",S25*Q25/100%) -> 59.572969 | S25: 0.01 | T25: 0.02 | U25: 159.393 | V25: 159.297 | W25: =IF(V25="","",IF(L25="Long",U25-V25,V25-U25)) -> 0.096 | X25: =IF(W25="","",R25) -> 59.572969 | Y25: 159.682 | Z25: =IF(Y25="","",IF(L25="Long",Y25-U25,U25-Y25)) -> 0.289 | AA25: =IF(AB25="","",AB25*X25/1) -> 179.33946 | AB25: =IF(Z25="","",Z25*1/W25) -> 3.0104167 | AC25: 16 de Fevereiro | AD25: 159.297 | AE25: 0 | AF25: 0 | AG25: =-X25 -> -59.572969 | AH25: =IF(AG25="","",AG25+AF25+AE25) -> -59.572969 | AI25: =IF(AD25="","",IF(L25="Long",AD25-U25,U25-AD25)) -> -0.096 | AJ25: =IF(AI25="","",AG25*S25/X25) -> -0.01 | AK25: =IF(AI25="","",(AG25+AF25+AE25)*S25/X25) -> -0.01 | AL25: =Q25+AG25 -> 5897.7239 | BH25: EURCAD | BI25: =$BA$11 -> Minors | BL25: C | BM25: Stop-Loss Parcial devido a falha na posição - Reversão da posição a negativo - Stop de Segurança
B26: Backtesting | C26: =C25+1 -> 16 | D26: 7 | E26: 5ª F | F26: 16 de Fevereiro | G26: Manhã | I26: GBPUSD | J26: Breakout | K26: 1m | L26: long | M26: W | Q26: =AL25 -> 5897.7239 | R26: =IF(Q26="","",S26*Q26/100%) -> 58.977239 | S26: 0.01 | T26: 0.25 | U26: 1.21938 | V26: 1.21872 | W26: =IF(V26="","",IF(L26="Long",U26-V26,V26-U26)) -> 0.00066 | X26: =IF(W26="","",R26) -> 58.977239 | Y26: 1.22136 | Z26: =IF(Y26="","",IF(L26="Long",Y26-U26,U26-Y26)) -> 0.00198 | AA26: =IF(AB26="","",AB26*X26/1) -> 176.93172 | AB26: =IF(Z26="","",Z26*1/W26) -> 3 | AC26: 16 de Fevereiro | AD26: 1.22 | AE26: 0 | AF26: 0 | AG26: =+AA26 -> 176.93172 | AH26: =IF(AG26="","",AG26+AF26+AE26) -> 176.93172 | AI26: =IF(AD26="","",IF(L26="Long",AD26-U26,U26-AD26)) -> 0.00062 | AJ26: =IF(AI26="","",AG26*S26/X26) -> 0.03 | AK26: =IF(AI26="","",(AG26+AF26+AE26)*S26/X26) -> 0.03 | AL26: =Q26+AG26 -> 6074.6556 | BH26: EURCHF | BI26: =$BA$11 -> Minors | BL26: D | BM26: Stop-Loss Total - Má gestão de saída da posição
B27: Backtesting | C27: =C26+1 -> 17 | D27: 7 | E27: 5ª F | F27: 16 de Fevereiro | G27: Manhã | I27: EURJPY | J27: Breakout | K27: 5m | L27: long | M27: W | Q27: =AL26 -> 6074.6556 | R27: =IF(Q27="","",S27*Q27/100%) -> 60.746556 | S27: 0.01 | T27: 0.01 | U27: 141.852 | V27: 141.551 | W27: =IF(V27="","",IF(L27="Long",U27-V27,V27-U27)) -> 0.301 | X27: =IF(W27="","",R27) -> 60.746556 | Y27: 142.755 | Z27: =IF(Y27="","",IF(L27="Long",Y27-U27,U27-Y27)) -> 0.903 | AA27: =IF(AB27="","",AB27*X27/1) -> 182.23967 | AB27: =IF(Z27="","",Z27*1/W27) -> 3 | AC27: 16 de Fevereiro | AD27: 142.755 | AE27: 0 | AF27: 0 | AG27: =+AA27 -> 182.23967 | AH27: =IF(AG27="","",AG27+AF27+AE27) -> 182.23967 | AI27: =IF(AD27="","",IF(L27="Long",AD27-U27,U27-AD27)) -> 0.903 | AJ27: =IF(AI27="","",AG27*S27/X27) -> 0.03 | AK27: =IF(AI27="","",(AG27+AF27+AE27)*S27/X27) -> 0.03 | AL27: =Q27+AG27 -> 6256.8953 | BH27: EURGBP | BI27: =$BA$11 -> Minors | BL27: E | BM27: Fecho Manual - Desconforto com a posição/ 1ª Vela negativa / Reversão
B28: Backtesting | C28: =C27+1 -> 18 | D28: 7 | E28: 5ª F | F28: 16 de Fevereiro | G28: Tarde | I28: CADJPY | J28: Breakout | K28: 5m | L28: long | M28: W | Q28: =AL27 -> 6256.8953 | R28: =IF(Q28="","",S28*Q28/100%) -> 62.568953 | S28: 0.01 | T28: 0.01 | U28: 99.574 | V28: 99.486 | W28: =IF(V28="","",IF(L28="Long",U28-V28,V28-U28)) -> 0.088 | X28: =IF(W28="","",R28) -> 62.568953 | Y28: 99.838 | Z28: =IF(Y28="","",IF(L28="Long",Y28-U28,U28-Y28)) -> 0.264 | AA28: =IF(AB28="","",AB28*X28/1) -> 187.70686 | AB28: =IF(Z28="","",Z28*1/W28) -> 3 | AC28: 16 de Fevereiro | AD28: 99.838 | AE28: 0 | AF28: 0 | AG28: =+AA28 -> 187.70686 | AH28: =IF(AG28="","",AG28+AF28+AE28) -> 187.70686 | AI28: =IF(AD28="","",IF(L28="Long",AD28-U28,U28-AD28)) -> 0.264 | AJ28: =IF(AI28="","",AG28*S28/X28) -> 0.03 | AK28: =IF(AI28="","",(AG28+AF28+AE28)*S28/X28) -> 0.03 | AL28: =Q28+AG28 -> 6444.6021 | BH28: EURJPY | BI28: =$BA$11 -> Minors
B29: Backtesting | C29: =C28+1 -> 19 | D29: 7 | E29: 5ª F | F29: 16 de Fevereiro | G29: Tarde | I29: AUDCAD | J29: Breakout | K29: 1m | L29: short | M29: W | Q29: =AL28 -> 6444.6021 | R29: =IF(Q29="","",S29*Q29/100%) -> 64.446021 | S29: 0.01 | T29: 1 | U29: 0.92624 | V29: 0.92675 | W29: =IF(V29="","",IF(L29="Long",U29-V29,V29-U29)) -> 0.00051 | X29: =IF(W29="","",R29) -> 64.446021 | Y29: 0.92471 | Z29: =IF(Y29="","",IF(L29="Long",Y29-U29,U29-Y29)) -> 0.00153 | AA29: =IF(AB29="","",AB29*X29/1) -> 193.33806 | AB29: =IF(Z29="","",Z29*1/W29) -> 3 | AC29: 16 de Fevereiro | AD29: 0.92471 | AE29: 0 | AF29: 0 | AG29: =+AA29 -> 193.33806 | AH29: =IF(AG29="","",AG29+AF29+AE29) -> 193.33806 | AI29: =IF(AD29="","",IF(L29="Long",AD29-U29,U29-AD29)) -> 0.00153 | AJ29: =IF(AI29="","",AG29*S29/X29) -> 0.03 | AK29: =IF(AI29="","",(AG29+AF29+AE29)*S29/X29) -> 0.03 | AL29: =Q29+AG29 -> 6637.9402 | BH29: EURNZD | BI29: =$BA$11 -> Minors
B30: Backtesting | C30: =C29+1 -> 20 | D30: 7 | E30: 5ª F | F30: 16 de Fevereiro | G30: Noite | I30: GBPJPY | J30: Breakout | K30: 1m | L30: long | M30: L | Q30: =AL29 -> 6637.9402 | R30: =IF(Q30="","",S30*Q30/100%) -> 66.379402 | S30: 0.01 | T30: 0.01 | U30: 161.744 | V30: 161.625 | W30: =IF(V30="","",IF(L30="Long",U30-V30,V30-U30)) -> 0.119 | X30: =IF(W30="","",R30) -> 66.379402 | Y30: 162.106 | Z30: =IF(Y30="","",IF(L30="Long",Y30-U30,U30-Y30)) -> 0.362 | AA30: =IF(AB30="","",AB30*X30/1) -> 201.92726 | AB30: =IF(Z30="","",Z30*1/W30) -> 3.0420168 | AC30: 16 de Fevereiro | AD30: 161.625 | AE30: 0 | AF30: 0 | AG30: =-X30 -> -66.379402 | AH30: =IF(AG30="","",AG30+AF30+AE30) -> -66.379402 | AI30: =IF(AD30="","",IF(L30="Long",AD30-U30,U30-AD30)) -> -0.119 | AJ30: =IF(AI30="","",AG30*S30/X30) -> -0.01 | AK30: =IF(AI30="","",(AG30+AF30+AE30)*S30/X30) -> -0.01 | AL30: =Q30+AG30 -> 6571.5608 | BH30: GBPAUD | BI30: =$BA$11 -> Minors
B31: Backtesting | C31: =C30+1 -> 21 | D31: 7 | E31: 6ª F | F31: 17 de Fevereiro | G31: Manhã | I31: CADJPY | J31: Breakout | K31: 1m | L31: long | M31: L | Q31: =AL30 -> 6571.5608 | R31: =IF(Q31="","",S31*Q31/100%) -> 65.715608 | S31: 0.01 | T31: 0.01 | U31: 100.064 | V31: 100.005 | W31: =IF(V31="","",IF(L31="Long",U31-V31,V31-U31)) -> 0.059 | X31: =IF(W31="","",R31) -> 65.715608 | Y31: 100.236 | Z31: =IF(Y31="","",IF(L31="Long",Y31-U31,U31-Y31)) -> 0.172 | AA31: =IF(AB31="","",AB31*X31/1) -> 191.5777 | AB31: =IF(Z31="","",Z31*1/W31) -> 2.9152542 | AC31: 17 de Fevereiro | AD31: 100.005 | AE31: 0 | AF31: 0 | AG31: =-X31 -> -65.715608 | AH31: =IF(AG31="","",AG31+AF31+AE31) -> -65.715608 | AI31: =IF(AD31="","",IF(L31="Long",AD31-U31,U31-AD31)) -> -0.059 | AJ31: =IF(AI31="","",AG31*S31/X31) -> -0.01 | AK31: =IF(AI31="","",(AG31+AF31+AE31)*S31/X31) -> -0.01 | AL31: =Q31+AG31 -> 6505.8452 | BH31: GBPCAD | BI31: =$BA$11 -> Minors
B32: Backtesting | C32: =C31+1 -> 22 | D32: 7 | E32: 6ª F | F32: 17 de Fevereiro | G32: Manhã | I32: AUDJPY | J32: Breakout | K32: 3m | L32: long | M32: L | Q32: =AL31 -> 6505.8452 | R32: =IF(Q32="","",S32*Q32/100%) -> 65.058452 | S32: 0.01 | T32: 0.11 | U32: 92.601 | V32: 92.482 | W32: =IF(V32="","",IF(L32="Long",U32-V32,V32-U32)) -> 0.119 | X32: =IF(W32="","",R32) -> 65.058452 | Y32: 92.959 | Z32: =IF(Y32="","",IF(L32="Long",Y32-U32,U32-Y32)) -> 0.358 | AA32: =IF(AB32="","",AB32*X32/1) -> 195.72207 | AB32: =IF(Z32="","",Z32*1/W32) -> 3.0084034 | AC32: 17 de Fevereiro | AD32: 92.482 | AE32: 0 | AF32: 0 | AG32: =-X32 -> -65.058452 | AH32: =IF(AG32="","",AG32+AF32+AE32) -> -65.058452 | AI32: =IF(AD32="","",IF(L32="Long",AD32-U32,U32-AD32)) -> -0.119 | AJ32: =IF(AI32="","",AG32*S32/X32) -> -0.01 | AK32: =IF(AI32="","",(AG32+AF32+AE32)*S32/X32) -> -0.01 | AL32: =Q32+AG32 -> 6440.7867 | BH32: GBPCHF | BI32: =$BA$11 -> Minors
B33: Backtesting | C33: =C32+1 -> 23 | D33: 13 | E33: 6ª F | F33: 31 de Março | G33: Manhã | I33: NZDUSD | J33: Breakout | K33: 3m | L33: long | M33: L | Q33: =AL32 -> 6440.7867 | R33: =IF(Q33="","",S33*Q33/100%) -> 64.407867 | S33: 0.01 | T33: 0.05 | U33: 0.62869 | V33: 0.62816 | W33: =IF(V33="","",IF(L33="Long",U33-V33,V33-U33)) -> 0.00053 | X33: =IF(W33="","",R33) -> 64.407867 | Y33: 0.63023 | Z33: =IF(Y33="","",IF(L33="Long",Y33-U33,U33-Y33)) -> 0.00154 | AA33: =IF(AB33="","",AB33*X33/1) -> 187.14739 | AB33: =IF(Z33="","",Z33*1/W33) -> 2.9056604 | AC33: 31 de Março | AD33: 0.62816 | AE33: 0 | AF33: 0 | AG33: =-X33 -> -64.407867 | AH33: =IF(AG33="","",AG33+AF33+AE33) -> -64.407867 | AI33: =IF(AD33="","",IF(L33="Long",AD33-U33,U33-AD33)) -> -0.00053 | AJ33: =IF(AI33="","",AG33*S33/X33) -> -0.01 | AK33: =IF(AI33="","",(AG33+AF33+AE33)*S33/X33) -> -0.01 | AL33: =Q33+AG33 -> 6376.3789 | BH33: GBPJPY | BI33: =$BA$11 -> Minors
B34: Testing em tempo real | C34: 24 | D34: 15 | E34: 3ª F | F34: 11 de Abril | G34: Tarde | H34: Majors | I34: USDJPY | J34: Breakout | K34: 1m | L34: long | M34: W | Q34: =AL33 -> 6376.3789 | R34: =IF(Q34="","",S34*Q34/100%) -> 63.763789 | S34: 0.01 | T34: 0.01 | U34: 133.211 | V34: 133.107 | W34: =IF(V34="","",IF(L34="Long",U34-V34,V34-U34)) -> 0.104 | X34: =IF(W34="","",R34) -> 63.763789 | Y34: 133.523 | Z34: =IF(Y34="","",IF(L34="Long",Y34-U34,U34-Y34)) -> 0.312 | AA34: =IF(AB34="","",AB34*X34/1) -> 191.29137 | AB34: =IF(Z34="","",Z34*1/W34) -> 3 | AC34: 11 de Abril | AD34: 133.523 | AE34: 0 | AF34: 0 | AG34: =+AA34 -> 191.29137 | AH34: =IF(AG34="","",AG34+AF34+AE34) -> 191.29137 | AI34: =IF(AD34="","",IF(L34="Long",AD34-U34,U34-AD34)) -> 0.312 | AJ34: =IF(AI34="","",AG34*S34/X34) -> 0.03 | AK34: =IF(AI34="","",(AG34+AF34+AE34)*S34/X34) -> 0.03 | AL34: =Q34+AG34 -> 6567.6702 | BH34: GBPNZD | BI34: =$BA$11 -> Minors
B35: Testing em tempo real | C35: 25 | D35: 15 | E35: 4ª F | F35: 12 de Abril | G35: Tarde | H35: Majors | I35: EURUSD | J35: Breakout | K35: 3m | L35: long | M35: L | Q35: =AL34 -> 6567.6702 | R35: =IF(Q35="","",S35*Q35/100%) -> 65.676702 | S35: 0.01 | T35: 0.01 | U35: 1.09274 | V35: 1.09201 | W35: =IF(V35="","",IF(L35="Long",U35-V35,V35-U35)) -> 0.00073 | X35: =IF(W35="","",R35) -> 65.676702 | Y35: 1.09493 | Z35: =IF(Y35="","",IF(L35="Long",Y35-U35,U35-Y35)) -> 0.00219 | AA35: =IF(AB35="","",AB35*X35/1) -> 197.03011 | AB35: =IF(Z35="","",Z35*1/W35) -> 3 | AC35: 12 de Abril | AD35: 1.09201 | AE35: 0 | AF35: 0 | AG35: =-X35 -> -65.676702 | AH35: =IF(AG35="","",AG35+AF35+AE35) -> -65.676702 | AI35: =IF(AD35="","",IF(L35="Long",AD35-U35,U35-AD35)) -> -0.00073 | AJ35: =IF(AI35="","",AG35*S35/X35) -> -0.01 | AK35: =IF(AI35="","",(AG35+AF35+AE35)*S35/X35) -> -0.01 | AL35: =Q35+AG35 -> 6501.9935 | BH35: NZDCAD | BI35: =$BA$11 -> Minors
B36: Testing em tempo real | C36: 26 | D36: 15 | E36: 4ª F | F36: 12 de Abril | G36: Tarde | H36: Majors | I36: GBPUSD | J36: Breakout | K36: 1m | L36: long | M36: W | Q36: =AL35 -> 6501.9935 | R36: =IF(Q36="","",S36*Q36/100%) -> 65.019935 | S36: 0.01 | T36: 0.01 | U36: 1.24715 | V36: 1.24616 | W36: =IF(V36="","",IF(L36="Long",U36-V36,V36-U36)) -> 0.00099 | X36: =IF(W36="","",R36) -> 65.019935 | Y36: 1.25012 | Z36: =IF(Y36="","",IF(L36="Long",Y36-U36,U36-Y36)) -> 0.00297 | AA36: =IF(AB36="","",AB36*X36/1) -> 195.05981 | AB36: =IF(Z36="","",Z36*1/W36) -> 3 | AC36: 12 de Abril | AD36: 1.25012 | AE36: 0 | AF36: 0 | AG36: =+AA36 -> 195.05981 | AH36: =IF(AG36="","",AG36+AF36+AE36) -> 195.05981 | AI36: =IF(AD36="","",IF(L36="Long",AD36-U36,U36-AD36)) -> 0.00297 | AJ36: =IF(AI36="","",AG36*S36/X36) -> 0.03 | AK36: =IF(AI36="","",(AG36+AF36+AE36)*S36/X36) -> 0.03 | AL36: =Q36+AG36 -> 6697.0533 | BH36: NZDCHF | BI36: =$BA$11 -> Minors
B37: Testing em tempo real | C37: 27 | D37: 15 | E37: 5ª F | F37: 13 de Abril | G37: Manhã | H37: Majors | I37: GBPUSD | J37: Breakout | K37: 1m | L37: long | M37: W | Q37: =AL36 -> 6697.0533 | R37: =IF(Q37="","",S37*Q37/100%) -> 66.970533 | S37: 0.01 | T37: 0.09 | U37: 1.25031 | V37: 1.24949 | W37: =IF(V37="","",IF(L37="Long",U37-V37,V37-U37)) -> 0.00082 | X37: =IF(W37="","",R37) -> 66.970533 | Y37: 1.25277 | Z37: =IF(Y37="","",IF(L37="Long",Y37-U37,U37-Y37)) -> 0.00246 | AA37: =IF(AB37="","",AB37*X37/1) -> 200.9116 | AB37: =IF(Z37="","",Z37*1/W37) -> 3 | AC37: 13 de Abril | AD37: 1.25277 | AE37: 0 | AF37: 0 | AG37: =+AA37 -> 200.9116 | AH37: =IF(AG37="","",AG37+AF37+AE37) -> 200.9116 | AI37: =IF(AD37="","",IF(L37="Long",AD37-U37,U37-AD37)) -> 0.00246 | AJ37: =IF(AI37="","",AG37*S37/X37) -> 0.03 | AK37: =IF(AI37="","",(AG37+AF37+AE37)*S37/X37) -> 0.03 | AL37: =Q37+AG37 -> 6897.9649 | BH37: NZDJPY | BI37: =$BA$11 -> Minors
B38: Testing em tempo real | C38: 28 | D38: 16 | E38: 3ª F | F38: 18 de Abril | G38: Manhã | H38: Majors | I38: GBPUSD | J38: Breakout | K38: 15s | L38: long | M38: L | Q38: =AL37 -> 6897.9649 | R38: =IF(Q38="","",S38*Q38/100%) -> 68.979649 | S38: 0.01 | T38: 0.01 | U38: 1.24214 | V38: 1.24161 | W38: =IF(V38="","",IF(L38="Long",U38-V38,V38-U38)) -> 0.00053 | X38: =IF(W38="","",R38) -> 68.979649 | Y38: 1.24373 | Z38: =IF(Y38="","",IF(L38="Long",Y38-U38,U38-Y38)) -> 0.00159 | AA38: =IF(AB38="","",AB38*X38/1) -> 206.93895 | AB38: =IF(Z38="","",Z38*1/W38) -> 3 | AC38: 18 de Abril | AD38: 1.24161 | AE38: 0 | AF38: 0 | AG38: =-X38 -> -68.979649 | AH38: =IF(AG38="","",AG38+AF38+AE38) -> -68.979649 | AI38: =IF(AD38="","",IF(L38="Long",AD38-U38,U38-AD38)) -> -0.00053 | AJ38: =IF(AI38="","",AG38*S38/X38) -> -0.01 | AK38: =IF(AI38="","",(AG38+AF38+AE38)*S38/X38) -> -0.01 | AL38: =Q38+AG38 -> 6828.9853 | BH38: NZDUSD | BI38: =$BA$11 -> Minors
B39: Backtesting | C39: 29 | D39: 17 | E39: 6ª F | F39: 28 de Abril | G39: Noite | H39: Majors | I39: AUDUSD | J39: Breakout | K39: 15s | L39: short | M39: W | Q39: =AL38 -> 6828.9853 | R39: =IF(Q39="","",S39*Q39/100%) -> 68.289853 | S39: 0.01 | T39: 0.02 | U39: 0.66089 | V39: 0.66135 | W39: =IF(V39="","",IF(L39="Long",U39-V39,V39-U39)) -> 0.00046 | X39: =IF(W39="","",R39) -> 68.289853 | Y39: 0.65951 | Z39: =IF(Y39="","",IF(L39="Long",Y39-U39,U39-Y39)) -> 0.00138 | AA39: =IF(AB39="","",AB39*X39/1) -> 204.86956 | AB39: =IF(Z39="","",Z39*1/W39) -> 3 | AC39: 28 de Abril | AD39: 0.65951 | AE39: 0 | AF39: 0 | AG39: =+AA39 -> 204.86956 | AH39: =IF(AG39="","",AG39+AF39+AE39) -> 204.86956 | AI39: =IF(AD39="","",IF(L39="Long",AD39-U39,U39-AD39)) -> 0.00138 | AJ39: =IF(AI39="","",AG39*S39/X39) -> 0.03 | AK39: =IF(AI39="","",(AG39+AF39+AE39)*S39/X39) -> 0.03 | AL39: =Q39+AG39 -> 7033.8549 | BH39: USDSGD | BI39: =$BA$11 -> Minors
B40: Testing em tempo real | C40: 30 | D40: 18 | E40: 4ª F | F40: 3 de Mario | G40: Manhã | H40: Majors | I40: USDCAD | J40: Breakout | K40: 1m | L40: long | M40: L | Q40: =AL39 -> 7033.8549 | R40: =IF(Q40="","",S40*Q40/100%) -> 70.338549 | S40: 0.01 | T40: 0.07 | U40: 1.36226 | V40: 1.3619 | W40: =IF(V40="","",IF(L40="Long",U40-V40,V40-U40)) -> 0.00036 | X40: =IF(W40="","",R40) -> 70.338549 | Y40: 1.36334 | Z40: =IF(Y40="","",IF(L40="Long",Y40-U40,U40-Y40)) -> 0.00108 | AA40: =IF(AB40="","",AB40*X40/1) -> 211.01565 | AB40: =IF(Z40="","",Z40*1/W40) -> 3 | AC40: 3 de Mario | AD40: 1.3619 | AE40: 0 | AF40: 0 | AG40: =-X40 -> -70.338549 | AH40: =IF(AG40="","",AG40+AF40+AE40) -> -70.338549 | AI40: =IF(AD40="","",IF(L40="Long",AD40-U40,U40-AD40)) -> -0.00036 | AJ40: =IF(AI40="","",AG40*S40/X40) -> -0.01 | AK40: =IF(AI40="","",(AG40+AF40+AE40)*S40/X40) -> -0.01 | AL40: =Q40+AG40 -> 6963.5163 | BH40: AUDSGD | BI40: =$BA$12 -> Exotics
B41: Testing em tempo real | C41: 31 | D41: 18 | E41: 4ª F | F41: 3 de Maio | G41: Tarde | H41: Majors | I41: GBPCAD | J41: Breakout | K41: 15s | L41: long | M41: L | Q41: =AL40 -> 6963.5163 | R41: =IF(Q41="","",S41*Q41/100%) -> 69.635163 | S41: 0.01 | T41: 0.01 | U41: 1.70853 | V41: 1.70802 | W41: =IF(V41="","",IF(L41="Long",U41-V41,V41-U41)) -> 0.00051 | X41: =IF(W41="","",R41) -> 69.635163 | Y41: 1.71006 | Z41: =IF(Y41="","",IF(L41="Long",Y41-U41,U41-Y41)) -> 0.00153 | AA41: =IF(AB41="","",AB41*X41/1) -> 208.90549 | AB41: =IF(Z41="","",Z41*1/W41) -> 3 | AC41: 3 de Maio | AD41: 1.70802 | AE41: 0 | AF41: 0 | AG41: =-X41 -> -69.635163 | AH41: =IF(AG41="","",AG41+AF41+AE41) -> -69.635163 | AI41: =IF(AD41="","",IF(L41="Long",AD41-U41,U41-AD41)) -> -0.00051 | AJ41: =IF(AI41="","",AG41*S41/X41) -> -0.01 | AK41: =IF(AI41="","",(AG41+AF41+AE41)*S41/X41) -> -0.01 | AL41: =Q41+AG41 -> 6893.8811 | BH41: CHFSGD | BI41: =$BA$12 -> Exotics
B42: Testing em tempo real | C42: 32 | D42: 18 | E42: 5ª F | F42: 4 de Maio | G42: Manhã | H42: Majors | I42: EURUSD | J42: Breakout | K42: 15s | L42: short | M42: W | Q42: =AL41 -> 6893.8811 | R42: =IF(Q42="","",S42*Q42/100%) -> 68.938811 | S42: 0.01 | T42: 0.04 | U42: 1.10536 | V42: 1.10584 | W42: =IF(V42="","",IF(L42="Long",U42-V42,V42-U42)) -> 0.00048 | X42: =IF(W42="","",R42) -> 68.938811 | Y42: 1.10387 | Z42: =IF(Y42="","",IF(L42="Long",Y42-U42,U42-Y42)) -> 0.00149 | AA42: =IF(AB42="","",AB42*X42/1) -> 213.99756 | AB42: =IF(Z42="","",Z42*1/W42) -> 3.1041667 | AC42: 4 de Maio | AD42: 1.10387 | AE42: 0 | AF42: 0 | AG42: =+AA42 -> 213.99756 | AH42: =IF(AG42="","",AG42+AF42+AE42) -> 213.99756 | AI42: =IF(AD42="","",IF(L42="Long",AD42-U42,U42-AD42)) -> 0.00149 | AJ42: =IF(AI42="","",AG42*S42/X42) -> 0.031041667 | AK42: =IF(AI42="","",(AG42+AF42+AE42)*S42/X42) -> 0.031041667 | AL42: =Q42+AG42 -> 7107.8787 | BH42: EURDKK | BI42: =$BA$12 -> Exotics
B43: Testing em tempo real | C43: 33 | D43: 18 | E43: 6ª F | F43: 5 de Maio | G43: Manhã | H43: Majors | I43: USDCAD | J43: Breakout | K43: 15s | L43: short | M43: W | Q43: =AL42 -> 7107.8787 | R43: =IF(Q43="","",S43*Q43/100%) -> 71.078787 | S43: 0.01 | T43: 0.08 | U43: 1.34944 | V43: 1.34974 | W43: =IF(V43="","",IF(L43="Long",U43-V43,V43-U43)) -> 0.0003 | X43: =IF(W43="","",R43) -> 71.078787 | Y43: 1.34854 | Z43: =IF(Y43="","",IF(L43="Long",Y43-U43,U43-Y43)) -> 0.0009 | AA43: =IF(AB43="","",AB43*X43/1) -> 213.23636 | AB43: =IF(Z43="","",Z43*1/W43) -> 3 | AC43: 5 de Maio | AD43: 1.34854 | AE43: 0 | AF43: 0 | AG43: =+AA43 -> 213.23636 | AH43: =IF(AG43="","",AG43+AF43+AE43) -> 213.23636 | AI43: =IF(AD43="","",IF(L43="Long",AD43-U43,U43-AD43)) -> 0.0009 | AJ43: =IF(AI43="","",AG43*S43/X43) -> 0.03 | AK43: =IF(AI43="","",(AG43+AF43+AE43)*S43/X43) -> 0.03 | AL43: =Q43+AG43 -> 7321.1151 | BH43: EURHKD | BI43: =$BA$12 -> Exotics
B44: Testing em tempo real | C44: 34 | D44: 19 | E44: 2ª F | F44: 8 de Maio | G44: Manhã | H44: Majors | I44: USDJPY | J44: Breakout | K44: 15s | L44: Long | M44: L | Q44: =AL43 -> 7321.1151 | R44: =IF(Q44="","",S44*Q44/100%) -> 73.211151 | S44: 0.01 | T44: 0.06 | U44: 135.021 | V44: 134.997 | W44: =IF(V44="","",IF(L44="Long",U44-V44,V44-U44)) -> 0.024 | X44: =IF(W44="","",R44) -> 73.211151 | Y44: 135.093 | Z44: =IF(Y44="","",IF(L44="Long",Y44-U44,U44-Y44)) -> 0.072 | AA44: =IF(AB44="","",AB44*X44/1) -> 219.63345 | AB44: =IF(Z44="","",Z44*1/W44) -> 3 | AC44: 8 de Maio | AD44: 134.997 | AE44: 0 | AF44: 0 | AG44: =-X44 -> -73.211151 | AH44: =IF(AG44="","",AG44+AF44+AE44) -> -73.211151 | AI44: =IF(AD44="","",IF(L44="Long",AD44-U44,U44-AD44)) -> -0.024 | AJ44: =IF(AI44="","",AG44*S44/X44) -> -0.01 | AK44: =IF(AI44="","",(AG44+AF44+AE44)*S44/X44) -> -0.01 | AL44: =Q44+AG44 -> 7247.9039 | BH44: EURNOK | BI44: =$BA$12 -> Exotics
B45: Testing em tempo real | C45: 35 | D45: 19 | E45: 3ª F | F45: 9 de Maio | G45: Tarde | H45: Minors | I45: GBPCAD | J45: Breakout | K45: 15s | L45: Long | M45: L | Q45: =AL44 -> 7247.9039 | R45: =IF(Q45="","",S45*Q45/100%) -> 72.479039 | S45: 0.01 | U45: 1.6907 | V45: 1.69019 | W45: =IF(V45="","",IF(L45="Long",U45-V45,V45-U45)) -> 0.00051 | X45: =IF(W45="","",R45) -> 72.479039 | Y45: 1.69223 | Z45: =IF(Y45="","",IF(L45="Long",Y45-U45,U45-Y45)) -> 0.00153 | AA45: =IF(AB45="","",AB45*X45/1) -> 217.43712 | AB45: =IF(Z45="","",Z45*1/W45) -> 3 | AC45: 9 de Maio | AD45: 1.69019 | AE45: 0 | AF45: 0 | AG45: =-X45 -> -72.479039 | AH45: =IF(AG45="","",AG45+AF45+AE45) -> -72.479039 | AI45: =IF(AD45="","",IF(L45="Long",AD45-U45,U45-AD45)) -> -0.00051 | AJ45: =IF(AI45="","",AG45*S45/X45) -> -0.01 | AK45: =IF(AI45="","",(AG45+AF45+AE45)*S45/X45) -> -0.01 | AL45: =Q45+AG45 -> 7175.4249 | BH45: EURPLN | BI45: =$BA$12 -> Exotics
B46: 2º MT Ic Market demo | C46: 36 | D46: 19 | E46: 5ª F | F46: 11 de Maio | G46: Manhã | H46: Majors | I46: USDCHF | J46: Breakout | K46: 15s | L46: Long | M46: L | Q46: =AL45 -> 7175.4249 | R46: =IF(Q46="","",S46*Q46/100%) -> 71.754249 | S46: 0.01 | U46: 0.89532 | V46: 0.89288 | W46: =IF(V46="","",IF(L46="Long",U46-V46,V46-U46)) -> 0.00244 | X46: =IF(W46="","",R46) -> 71.754249 | Y46: 0.89532 | Z46: =IF(Y46="","",IF(L46="Long",Y46-U46,U46-Y46)) -> 0 | AA46: =IF(AB46="","",AB46*X46/1) -> 0 | AB46: =IF(Z46="","",Z46*1/W46) -> 0 | AC46: 11 de Maio | AD46: 0.89288 | AE46: -8.38 | AF46: 0 | AG46: =-X46 -> -71.754249 | AH46: =IF(AG46="","",AG46+AF46+AE46) -> -80.134249 | AI46: =IF(AD46="","",IF(L46="Long",AD46-U46,U46-AD46)) -> -0.00244 | AJ46: =IF(AI46="","",AG46*S46/X46) -> -0.01 | AK46: =IF(AI46="","",(AG46+AF46+AE46)*S46/X46) -> -0.011167875 | AL46: =Q46+AG46 -> 7103.6706 | BH46: EURSEK | BI46: =$BA$12 -> Exotics
B47: Testing em tempo real | C47: 37 | D47: 19 | E47: 5ª F | F47: 11 de Maio | G47: Manhã | H47: Majors | I47: EURUSD | J47: Breakout | K47: 15s | L47: Short | M47: L | Q47: =AL46 -> 7103.6706 | R47: =IF(Q47="","",S47*Q47/100%) -> 71.036706 | S47: 0.01 | U47: 1.09262 | V47: 1.09309 | W47: =IF(V47="","",IF(L47="Long",U47-V47,V47-U47)) -> 0.00047 | X47: =IF(W47="","",R47) -> 71.036706 | Y47: 1.09121 | Z47: =IF(Y47="","",IF(L47="Long",Y47-U47,U47-Y47)) -> 0.00141 | AA47: =IF(AB47="","",AB47*X47/1) -> 213.11012 | AB47: =IF(Z47="","",Z47*1/W47) -> 3 | AC47: 11 de Maio | AD47: 1.09309 | AE47: 0 | AF47: 0 | AG47: =-X47 -> -71.036706 | AH47: =IF(AG47="","",AG47+AF47+AE47) -> -71.036706 | AI47: =IF(AD47="","",IF(L47="Long",AD47-U47,U47-AD47)) -> -0.00047 | AJ47: =IF(AI47="","",AG47*S47/X47) -> -0.01 | AK47: =IF(AI47="","",(AG47+AF47+AE47)*S47/X47) -> -0.01 | AL47: =Q47+AG47 -> 7032.6339 | BH47: EURSGD | BI47: =$BA$12 -> Exotics
B48: Testing em tempo real | C48: 38 | D48: 19 | E48: 6ª F | F48: 12 de Maio | G48: Tarde | H48: Minors | I48: AUDCAD | J48: Breakout | K48: 1m | L48: Short | M48: W | Q48: =AL47 -> 7032.6339 | R48: =IF(Q48="","",S48*Q48/100%) -> 70.326339 | S48: 0.01 | U48: 0.90187 | V48: 0.90236 | W48: =IF(V48="","",IF(L48="Long",U48-V48,V48-U48)) -> 0.00049 | X48: =IF(W48="","",R48) -> 70.326339 | Y48: 0.9004 | Z48: =IF(Y48="","",IF(L48="Long",Y48-U48,U48-Y48)) -> 0.00147 | AA48: =IF(AB48="","",AB48*X48/1) -> 210.97902 | AB48: =IF(Z48="","",Z48*1/W48) -> 3 | AC48: 12 de Maio | AD48: 0.9004 | AE48: 0 | AF48: 0 | AG48: =+AA48 -> 210.97902 | AH48: =IF(AG48="","",AG48+AF48+AE48) -> 210.97902 | AI48: =IF(AD48="","",IF(L48="Long",AD48-U48,U48-AD48)) -> 0.00147 | AJ48: =IF(AI48="","",AG48*S48/X48) -> 0.03 | AK48: =IF(AI48="","",(AG48+AF48+AE48)*S48/X48) -> 0.03 | AL48: =Q48+AG48 -> 7243.6129 | BH48: EURTRY | BI48: =$BA$12 -> Exotics
B49: 2º MT Ic Market demo | C49: 39 | D49: 20 | E49: 4ª F | F49: 17 de Maio | G49: Manhã | H49: Majors | I49: GBPUSD | J49: Breakout | K49: 1m | L49: short | M49: L | Q49: =AL48 -> 7243.6129 | R49: =IF(Q49="","",S49*Q49/100%) -> 72.436129 | S49: 0.01 | U49: 1.24517 | V49: 1.24628 | W49: =IF(V49="","",IF(L49="Long",U49-V49,V49-U49)) -> 0.00111 | X49: =IF(W49="","",R49) -> 72.436129 | Y49: 1.24184 | Z49: =IF(Y49="","",IF(L49="Long",Y49-U49,U49-Y49)) -> 0.00333 | AA49: =IF(AB49="","",AB49*X49/1) -> 217.30839 | AB49: =IF(Z49="","",Z49*1/W49) -> 3 | AC49: 17 de Maio | AD49: 1.24628 | AE49: 0 | AF49: 0 | AG49: =-X49 -> -72.436129 | AH49: =IF(AG49="","",AG49+AF49+AE49) -> -72.436129 | AI49: =IF(AD49="","",IF(L49="Long",AD49-U49,U49-AD49)) -> -0.00111 | AJ49: =IF(AI49="","",AG49*S49/X49) -> -0.01 | AK49: =IF(AI49="","",(AG49+AF49+AE49)*S49/X49) -> -0.01 | AL49: =Q49+AG49 -> 7171.1768 | BH49: EURZAR | BI49: =$BA$12 -> Exotics
B50: 2º MT Ic Market demo | C50: 40 | D50: 20 | E50: 5ª F | F50: 18 de Maio | G50: Manhã | H50: Minors | I50: GBPCAD | J50: Breakout | K50: 15s | L50: short | M50: W | Q50: =AL49 -> 7171.1768 | R50: =IF(Q50="","",S50*Q50/100%) -> 71.711768 | S50: 0.01 | U50: 1.6794 | V50: 1.67991 | W50: =IF(V50="","",IF(L50="Long",U50-V50,V50-U50)) -> 0.00051 | X50: =IF(W50="","",R50) -> 71.711768 | Y50: 1.67787 | Z50: =IF(Y50="","",IF(L50="Long",Y50-U50,U50-Y50)) -> 0.00153 | AA50: =IF(AB50="","",AB50*X50/1) -> 215.1353 | AB50: =IF(Z50="","",Z50*1/W50) -> 3 | AC50: 18 de Maio | AD50: 1.67787 | AE50: 0 | AF50: 0 | AG50: =+AA50 -> 215.1353 | AH50: =IF(AG50="","",AG50+AF50+AE50) -> 215.1353 | AI50: =IF(AD50="","",IF(L50="Long",AD50-U50,U50-AD50)) -> 0.00153 | AJ50: =IF(AI50="","",AG50*S50/X50) -> 0.03 | AK50: =IF(AI50="","",(AG50+AF50+AE50)*S50/X50) -> 0.03 | AL50: =Q50+AG50 -> 7386.3121 | BH50: GBPDKK | BI50: =$BA$12 -> Exotics
B51: 2º MT Ic Market demo | C51: 41 | D51: 20 | E51: 5ª F | F51: 18 de Maio | G51: Manhã | H51: Majors | I51: GBPUSD | J51: Breakout | K51: 1m | L51: short | M51: L | Q51: =AL50 -> 7386.3121 | R51: =IF(Q51="","",S51*Q51/100%) -> 73.863121 | S51: 0.01 | U51: 1.24344 | V51: 1.2442 | W51: =IF(V51="","",IF(L51="Long",U51-V51,V51-U51)) -> 0.00076 | X51: =IF(W51="","",R51) -> 73.863121 | Y51: 1.24116 | Z51: =IF(Y51="","",IF(L51="Long",Y51-U51,U51-Y51)) -> 0.00228 | AA51: =IF(AB51="","",AB51*X51/1) -> 221.58936 | AB51: =IF(Z51="","",Z51*1/W51) -> 3 | AC51: 18 de Maio | AD51: 1.2442 | AE51: 0 | AF51: 0 | AG51: =-X51 -> -73.863121 | AH51: =IF(AG51="","",AG51+AF51+AE51) -> -73.863121 | AI51: =IF(AD51="","",IF(L51="Long",AD51-U51,U51-AD51)) -> -0.00076 | AJ51: =IF(AI51="","",AG51*S51/X51) -> -0.01 | AK51: =IF(AI51="","",(AG51+AF51+AE51)*S51/X51) -> -0.01 | AL51: =Q51+AG51 -> 7312.449 | BH51: GBPNOK | BI51: =$BA$12 -> Exotics
B52: 2º MT Ic Market demo | C52: 42 | D52: 20 | E52: 6ª F | F52: 19 de Maio | G52: Manhã | H52: Minors | I52: GBPAUD | J52: Breakout | K52: 15s | L52: short | M52: L | Q52: =AL51 -> 7312.449 | R52: =IF(Q52="","",S52*Q52/100%) -> 73.12449 | S52: 0.01 | U52: 1.86499 | V52: 1.866 | W52: =IF(V52="","",IF(L52="Long",U52-V52,V52-U52)) -> 0.00101 | X52: =IF(W52="","",R52) -> 73.12449 | Y52: 1.86196 | Z52: =IF(Y52="","",IF(L52="Long",Y52-U52,U52-Y52)) -> 0.00303 | AA52: =IF(AB52="","",AB52*X52/1) -> 219.37347 | AB52: =IF(Z52="","",Z52*1/W52) -> 3 | AC52: 19 de Maio | AD52: 1.866 | AE52: 0 | AF52: 0 | AG52: =-X52 -> -73.12449 | AH52: =IF(AG52="","",AG52+AF52+AE52) -> -73.12449 | AI52: =IF(AD52="","",IF(L52="Long",AD52-U52,U52-AD52)) -> -0.00101 | AJ52: =IF(AI52="","",AG52*S52/X52) -> -0.01 | AK52: =IF(AI52="","",(AG52+AF52+AE52)*S52/X52) -> -0.01 | AL52: =Q52+AG52 -> 7239.3245 | BH52: GBPSEK | BI52: =$BA$12 -> Exotics
B53: 2º MT Ic Market demo | C53: 43 | D53: 21 | E53: 4ª F | F53: 24 de Maio | G53: Manhã | H53: Majors | I53: EURUSD | J53: Breakout | K53: 15s | L53: short | M53: L | Q53: =AL52 -> 7239.3245 | R53: =IF(Q53="","",S53*Q53/100%) -> 72.393245 | S53: 0.01 | U53: 1.07762 | V53: 1.07813 | W53: =IF(V53="","",IF(L53="Long",U53-V53,V53-U53)) -> 0.00051 | X53: =IF(W53="","",R53) -> 72.393245 | Y53: 1.07609 | Z53: =IF(Y53="","",IF(L53="Long",Y53-U53,U53-Y53)) -> 0.00153 | AA53: =IF(AB53="","",AB53*X53/1) -> 217.17974 | AB53: =IF(Z53="","",Z53*1/W53) -> 3 | AC53: 24 de Maio | AD53: 1.07813 | AE53: 0 | AF53: 0 | AG53: =-X53 -> -72.393245 | AH53: =IF(AG53="","",AG53+AF53+AE53) -> -72.393245 | AI53: =IF(AD53="","",IF(L53="Long",AD53-U53,U53-AD53)) -> -0.00051 | AJ53: =IF(AI53="","",AG53*S53/X53) -> -0.01 | AK53: =IF(AI53="","",(AG53+AF53+AE53)*S53/X53) -> -0.01 | AL53: =Q53+AG53 -> 7166.9313 | BH53: GBPSGD | BI53: =$BA$12 -> Exotics
B54: 2º MT Ic Market demo | C54: 44 | D54: 21 | E54: 6ª F | F54: 26 de Maio | G54: Manhã | H54: Majors | I54: USDCAD | J54: Breakout | K54: 15s | L54: short | M54: L | Q54: =AL53 -> 7166.9313 | R54: =IF(Q54="","",S54*Q54/100%) -> 71.669313 | S54: 0.01 | U54: 1.36186 | V54: 1.36224 | W54: =IF(V54="","",IF(L54="Long",U54-V54,V54-U54)) -> 0.00038 | X54: =IF(W54="","",R54) -> 71.669313 | Y54: 1.36072 | Z54: =IF(Y54="","",IF(L54="Long",Y54-U54,U54-Y54)) -> 0.00114 | AA54: =IF(AB54="","",AB54*X54/1) -> 215.00794 | AB54: =IF(Z54="","",Z54*1/W54) -> 3 | AC54: 26 de Maio | AD54: 1.36224 | AE54: 0 | AF54: 0 | AG54: =-X54 -> -71.669313 | AH54: =IF(AG54="","",AG54+AF54+AE54) -> -71.669313 | AI54: =IF(AD54="","",IF(L54="Long",AD54-U54,U54-AD54)) -> -0.00038 | AJ54: =IF(AI54="","",AG54*S54/X54) -> -0.01 | AK54: =IF(AI54="","",(AG54+AF54+AE54)*S54/X54) -> -0.01 | AL54: =Q54+AG54 -> 7095.2619 | BH54: GBPTRY | BI54: =$BA$12 -> Exotics
B55: 2º MT Ic Market demo | C55: 45 | D55: 22 | E55: 3ª F | F55: 30 de Maio | G55: Manhã | H55: Minors | I55: EURGBP | J55: Breakout | K55: 1m | L55: short | M55: W | Q55: =AL54 -> 7095.2619 | R55: =IF(Q55="","",S55*Q55/100%) -> 70.952619 | S55: 0.01 | U55: 0.86637 | V55: 0.86685 | W55: =IF(V55="","",IF(L55="Long",U55-V55,V55-U55)) -> 0.00048 | X55: =IF(W55="","",R55) -> 70.952619 | Y55: 0.86493 | Z55: =IF(Y55="","",IF(L55="Long",Y55-U55,U55-Y55)) -> 0.00144 | AA55: =IF(AB55="","",AB55*X55/1) -> 212.85786 | AB55: =IF(Z55="","",Z55*1/W55) -> 3 | AC55: 30 de Maio | AD55: 0.86493 | AE55: 0 | AF55: 0 | AG55: =+AA55 -> 212.85786 | AH55: =IF(AG55="","",AG55+AF55+AE55) -> 212.85786 | AI55: =IF(AD55="","",IF(L55="Long",AD55-U55,U55-AD55)) -> 0.00144 | AJ55: =IF(AI55="","",AG55*S55/X55) -> 0.03 | AK55: =IF(AI55="","",(AG55+AF55+AE55)*S55/X55) -> 0.03 | AL55: =Q55+AG55 -> 7308.1198 | BH55: NOKJPY | BI55: =$BA$12 -> Exotics
B56: 2º MT Ic Market demo | C56: 46 | D56: 23 | E56: 4ª F | F56: 7 de Junho | G56: Manhã | H56: Minors | I56: EURJPY | J56: Breakout | K56: 1m | L56: short | M56: L | Q56: =AL55 -> 7308.1198 | R56: =IF(Q56="","",S56*Q56/100%) -> 73.081198 | S56: 0.01 | U56: 148.673 | V56: 148.752 | W56: =IF(V56="","",IF(L56="Long",U56-V56,V56-U56)) -> 0.079 | X56: =IF(W56="","",R56) -> 73.081198 | Y56: 148.436 | Z56: =IF(Y56="","",IF(L56="Long",Y56-U56,U56-Y56)) -> 0.237 | AA56: =IF(AB56="","",AB56*X56/1) -> 219.24359 | AB56: =IF(Z56="","",Z56*1/W56) -> 3 | AC56: 7 de Junho | AD56: 148.752 | AE56: 0 | AF56: 0 | AG56: =-X56 -> -73.081198 | AH56: =IF(AG56="","",AG56+AF56+AE56) -> -73.081198 | AI56: =IF(AD56="","",IF(L56="Long",AD56-U56,U56-AD56)) -> -0.079 | AJ56: =IF(AI56="","",AG56*S56/X56) -> -0.01 | AK56: =IF(AI56="","",(AG56+AF56+AE56)*S56/X56) -> -0.01 | AL56: =Q56+AG56 -> 7235.0386 | BH56: NOKSEK | BI56: =$BA$12 -> Exotics
B57: 2º MT Ic Market demo | C57: 47 | D57: 24 | E57: 5ª F | F57: 15 de Junho | G57: Manhã | H57: Minors | I57: GBPAUD | J57: Breakout | K57: 1m | L57: short | M57: L | Q57: =AL56 -> 7235.0386 | R57: =IF(Q57="","",S57*Q57/100%) -> 72.350386 | S57: 0.01 | U57: 1.85398 | V57: 1.85565 | W57: =IF(V57="","",IF(L57="Long",U57-V57,V57-U57)) -> 0.00167 | X57: =IF(W57="","",R57) -> 72.350386 | Y57: 1.84895 | Z57: =IF(Y57="","",IF(L57="Long",Y57-U57,U57-Y57)) -> 0.00503 | AA57: =IF(AB57="","",AB57*X57/1) -> 217.91763 | AB57: =IF(Z57="","",Z57*1/W57) -> 3.011976 | AC57: 15 de Junho | AD57: 1.85565 | AE57: 0 | AF57: 0 | AG57: =-X57 -> -72.350386 | AH57: =IF(AG57="","",AG57+AF57+AE57) -> -72.350386 | AI57: =IF(AD57="","",IF(L57="Long",AD57-U57,U57-AD57)) -> -0.00167 | AJ57: =IF(AI57="","",AG57*S57/X57) -> -0.01 | AK57: =IF(AI57="","",(AG57+AF57+AE57)*S57/X57) -> -0.01 | AL57: =Q57+AG57 -> 7162.6882 | BH57: SEKJPY | BI57: =$BA$12 -> Exotics
B58: 2º MT Ic Market demo | C58: 48 | D58: 24 | E58: 5ª F | F58: 15 de Junho | G58: Manhã | H58: Minors | I58: AUDNZD | J58: Breakout | K58: 1m | L58: long | M58: L | Q58: =AL57 -> 7162.6882 | R58: =IF(Q58="","",S58*Q58/100%) -> 71.626882 | S58: 0.01 | U58: 1.10256 | V58: 1.10189 | W58: =IF(V58="","",IF(L58="Long",U58-V58,V58-U58)) -> 0.00067 | X58: =IF(W58="","",R58) -> 71.626882 | Y58: 1.10457 | Z58: =IF(Y58="","",IF(L58="Long",Y58-U58,U58-Y58)) -> 0.00201 | AA58: =IF(AB58="","",AB58*X58/1) -> 214.88065 | AB58: =IF(Z58="","",Z58*1/W58) -> 3 | AC58: 15 de Junho | AD58: 1.10249 | AE58: 0 | AF58: 0 | AG58: =-X58 -> -71.626882 | AH58: =IF(AG58="","",AG58+AF58+AE58) -> -71.626882 | AI58: =IF(AD58="","",IF(L58="Long",AD58-U58,U58-AD58)) -> -7e-05 | AJ58: =IF(AI58="","",AG58*S58/X58) -> -0.01 | AK58: =IF(AI58="","",(AG58+AF58+AE58)*S58/X58) -> -0.01 | AL58: =Q58+AG58 -> 7091.0613 | BH58: USDCNH | BI58: =$BA$12 -> Exotics
B59: 2º MT Ic Market demo | C59: 49 | D59: 25 | E59: 5ª F | F59: 22 de Junho | G59: Manhã | H59: Majors | I59: EURUSD | J59: Breakout | K59: 1m | L59: long | M59: L | Q59: =AL58 -> 7091.0613 | R59: =IF(Q59="","",S59*Q59/100%) -> 70.910613 | S59: 0.01 | U59: 1.09979 | V59: 1.09919 | W59: =IF(V59="","",IF(L59="Long",U59-V59,V59-U59)) -> 0.0006 | X59: =IF(W59="","",R59) -> 70.910613 | Y59: 1.10159 | Z59: =IF(Y59="","",IF(L59="Long",Y59-U59,U59-Y59)) -> 0.0018 | AA59: =IF(AB59="","",AB59*X59/1) -> 212.73184 | AB59: =IF(Z59="","",Z59*1/W59) -> 3 | AC59: 22 de Junho | AD59: 1.09919 | AE59: 0 | AF59: 0 | AG59: =-X59 -> -70.910613 | AH59: =IF(AG59="","",AG59+AF59+AE59) -> -70.910613 | AI59: =IF(AD59="","",IF(L59="Long",AD59-U59,U59-AD59)) -> -0.0006 | AJ59: =IF(AI59="","",AG59*S59/X59) -> -0.01 | AK59: =IF(AI59="","",(AG59+AF59+AE59)*S59/X59) -> -0.01 | AL59: =Q59+AG59 -> 7020.1507 | BH59: USDCZK | BI59: =$BA$12 -> Exotics
B60: 2º MT Ic Market demo | C60: 50 | D60: 25 | E60: 5ª F | F60: 22 de Junho | G60: Tarde | H60: Minors | I60: GBPCAD | J60: Breakout | K60: 1m | L60: short | M60: L | Q60: =AL59 -> 7020.1507 | R60: =IF(Q60="","",S60*Q60/100%) -> 70.201507 | S60: 0.01 | U60: 1.6769 | V60: 1.67838 | W60: =IF(V60="","",IF(L60="Long",U60-V60,V60-U60)) -> 0.00148 | X60: =IF(W60="","",R60) -> 70.201507 | Y60: 1.67246 | Z60: =IF(Y60="","",IF(L60="Long",Y60-U60,U60-Y60)) -> 0.00444 | AA60: =IF(AB60="","",AB60*X60/1) -> 210.60452 | AB60: =IF(Z60="","",Z60*1/W60) -> 3 | AC60: 22 de Junho | AD60: 1.67838 | AE60: 0 | AF60: 0 | AG60: =-X60 -> -70.201507 | AH60: =IF(AG60="","",AG60+AF60+AE60) -> -70.201507 | AI60: =IF(AD60="","",IF(L60="Long",AD60-U60,U60-AD60)) -> -0.00148 | AJ60: =IF(AI60="","",AG60*S60/X60) -> -0.01 | AK60: =IF(AI60="","",(AG60+AF60+AE60)*S60/X60) -> -0.01 | AL60: =Q60+AG60 -> 6949.9492 | BH60: USDDKK | BI60: =$BA$12 -> Exotics
B61: 2º MT Ic Market demo | C61: 51 | D61: 26 | E61: 2ª F | F61: 26 de Junho | G61: Manhã | H61: Minors | I61: AUDJPY | J61: Breakout | K61: 3m | L61: short | M61: L | Q61: =AL60 -> 6949.9492 | R61: =IF(Q61="","",S61*Q61/100%) -> 69.499492 | S61: 0.01 | U61: 95.466 | V61: 95.609 | W61: =IF(V61="","",IF(L61="Long",U61-V61,V61-U61)) -> 0.143 | X61: =IF(W61="","",R61) -> 69.499492 | Y61: 95.036 | Z61: =IF(Y61="","",IF(L61="Long",Y61-U61,U61-Y61)) -> 0.43 | AA61: =IF(AB61="","",AB61*X61/1) -> 208.98449 | AB61: =IF(Z61="","",Z61*1/W61) -> 3.006993 | AC61: 26 de Junho | AD61: 95.609 | AE61: 0 | AF61: 0 | AG61: =-X61 -> -69.499492 | AH61: =IF(AG61="","",AG61+AF61+AE61) -> -69.499492 | AI61: =IF(AD61="","",IF(L61="Long",AD61-U61,U61-AD61)) -> -0.143 | AJ61: =IF(AI61="","",AG61*S61/X61) -> -0.01 | AK61: =IF(AI61="","",(AG61+AF61+AE61)*S61/X61) -> -0.01 | AL61: =Q61+AG61 -> 6880.4497 | BH61: USDHKD | BI61: =$BA$12 -> Exotics
B62: 3º MT Ic Market demo | C62: 52 | D62: 27 | E62: 4ª F | F62: 5 de Julho | G62: Tarde | H62: Minors | I62: EURGBP | J62: Breakout | K62: 5m | L62: short | M62: W | Q62: =AL61 -> 6880.4497 | R62: =IF(Q62="","",S62*Q62/100%) -> 68.804497 | S62: 0.01 | U62: 0.85649 | V62: 0.85726 | W62: =IF(V62="","",IF(L62="Long",U62-V62,V62-U62)) -> 0.00077 | X62: =IF(W62="","",R62) -> 68.804497 | Y62: 0.85417 | Z62: =IF(Y62="","",IF(L62="Long",Y62-U62,U62-Y62)) -> 0.00232 | AA62: =IF(AB62="","",AB62*X62/1) -> 207.30706 | AB62: =IF(Z62="","",Z62*1/W62) -> 3.012987 | AC62: 5 de Julho | AD62: 0.85454 | AE62: 0 | AF62: 0 | AG62: =+AA62 -> 207.30706 | AH62: =IF(AG62="","",AG62+AF62+AE62) -> 207.30706 | AI62: =IF(AD62="","",IF(L62="Long",AD62-U62,U62-AD62)) -> 0.00195 | AJ62: =IF(AI62="","",AG62*S62/X62) -> 0.03012987 | AK62: =IF(AI62="","",(AG62+AF62+AE62)*S62/X62) -> 0.03012987 | AL62: =Q62+AG62 -> 7087.7568 | BH62: USDHUF | BI62: =$BA$12 -> Exotics
B63: 3º MT Ic Market demo | C63: 53 | D63: 27 | E63: 6ª F | F63: 7 de Julho | G63: Manhã | H63: Minors | I63: EURCHF | J63: Breakout | K63: 1m | L63: short | M63: w | Q63: =AL62 -> 7087.7568 | R63: =IF(Q63="","",S63*Q63/100%) -> 70.877568 | S63: 0.01 | U63: 0.97416 | V63: 0.9745 | W63: =IF(V63="","",IF(L63="Long",U63-V63,V63-U63)) -> 0.00034 | X63: =IF(W63="","",R63) -> 70.877568 | Y63: 0.97321 | Z63: =IF(Y63="","",IF(L63="Long",Y63-U63,U63-Y63)) -> 0.00095 | AA63: =IF(AB63="","",AB63*X63/1) -> 198.04026 | AB63: =IF(Z63="","",Z63*1/W63) -> 2.7941176 | AC63: 7 de Junho | AD63: 0.97411 | AE63: 0 | AF63: 0 | AG63: =+AA63 -> 198.04026 | AH63: =IF(AG63="","",AG63+AF63+AE63) -> 198.04026 | AI63: =IF(AD63="","",IF(L63="Long",AD63-U63,U63-AD63)) -> 5e-05 | AJ63: =IF(AI63="","",AG63*S63/X63) -> 0.027941176 | AK63: =IF(AI63="","",(AG63+AF63+AE63)*S63/X63) -> 0.027941176 | AL63: =Q63+AG63 -> 7285.797 | BH63: USDMXN | BI63: =$BA$12 -> Exotics
B64: 3º MT Ic Market demo | C64: 54 | D64: 28 | E64: 3ª F | F64: 11 de Julho | G64: Manhã | H64: Minors | I64: AUDCHF | J64: Breakout | K64: 1D | L64: short | M64: W | Q64: =AL63 -> 7285.797 | R64: =IF(Q64="","",S64*Q64/100%) -> 72.85797 | S64: 0.01 | U64: 0.59036 | V64: 0.60311 | W64: =IF(V64="","",IF(L64="Long",U64-V64,V64-U64)) -> 0.01275 | X64: =IF(W64="","",R64) -> 72.85797 | Y64: 0.55209 | Z64: =IF(Y64="","",IF(L64="Long",Y64-U64,U64-Y64)) -> 0.03827 | AA64: =IF(AB64="","",AB64*X64/1) -> 218.6882 | AB64: =IF(Z64="","",Z64*1/W64) -> 3.0015686 | AD64: 0.55209 | AE64: 0 | AF64: 0 | AG64: =AA64 -> 218.6882 | AH64: =IF(AG64="","",AG64+AF64+AE64) -> 218.6882 | AI64: =IF(AD64="","",IF(L64="Long",AD64-U64,U64-AD64)) -> 0.03827 | AJ64: =IF(AI64="","",AG64*S64/X64) -> 0.030015686 | AK64: =IF(AI64="","",(AG64+AF64+AE64)*S64/X64) -> 0.030015686 | AL64: =Q64+AG64 -> 7504.4852 | BH64: USDNOK | BI64: =$BA$12 -> Exotics
B65: 3º MT Ic Market demo | C65: 55 | D65: 29 | E65: 4ª F | F65: 19 de Julho | G65: Manhã | H65: Minors | I65: EURCHF | J65: Retest | K65: 1h | L65: short | M65: L | Q65: =AL64 -> 7504.4852 | R65: =IF(Q65="","",S65*Q65/100%) -> 75.044852 | S65: 0.01 | U65: 0.96436 | V65: 0.96745 | W65: =IF(V65="","",IF(L65="Long",U65-V65,V65-U65)) -> 0.00309 | X65: =IF(W65="","",R65) -> 75.044852 | Y65: 0.95518 | Z65: =IF(Y65="","",IF(L65="Long",Y65-U65,U65-Y65)) -> 0.00918 | AA65: =IF(AB65="","",AB65*X65/1) -> 222.94878 | AB65: =IF(Z65="","",Z65*1/W65) -> 2.9708738 | AC65: 20 de Julho | AD65: 0.96745 | AE65: 0 | AF65: 0 | AG65: =-X65 -> -75.044852 | AH65: =IF(AG65="","",AG65+AF65+AE65) -> -75.044852 | AI65: =IF(AD65="","",IF(L65="Long",AD65-U65,U65-AD65)) -> -0.00309 | AJ65: =IF(AI65="","",AG65*S65/X65) -> -0.01 | AK65: =IF(AI65="","",(AG65+AF65+AE65)*S65/X65) -> -0.01 | AL65: =Q65+AG65 -> 7429.4404 | BH65: USDPLN | BI65: =$BA$12 -> Exotics
B66: 3º MT Ic Market demo | C66: 56 | D66: 29 | E66: 5ª F | F66: 20 de Julho | G66: Manhã | H66: Minors | I66: GBPCAD | J66: Breakout | K66: 1m | L66: short | M66: W | Q66: =AL65 -> 7429.4404 | R66: =IF(Q66="","",S66*Q66/100%) -> 74.294404 | S66: 0.01 | U66: 1.69453 | V66: 1.69585 | W66: =IF(V66="","",IF(L66="Long",U66-V66,V66-U66)) -> 0.00132 | X66: =IF(W66="","",R66) -> 74.294404 | Y66: 1.69057 | Z66: =IF(Y66="","",IF(L66="Long",Y66-U66,U66-Y66)) -> 0.00396 | AA66: =IF(AB66="","",AB66*X66/1) -> 222.88321 | AB66: =IF(Z66="","",Z66*1/W66) -> 3 | AC66: 20 de Julho | AD66: 1.69057 | AE66: 0 | AF66: 0 | AG66: =+AA66 -> 222.88321 | AH66: =IF(AG66="","",AG66+AF66+AE66) -> 222.88321 | AI66: =IF(AD66="","",IF(L66="Long",AD66-U66,U66-AD66)) -> 0.00396 | AJ66: =IF(AI66="","",AG66*S66/X66) -> 0.03 | AK66: =IF(AI66="","",(AG66+AF66+AE66)*S66/X66) -> 0.03 | AL66: =Q66+AG66 -> 7652.3236 | BH66: USDRUB | BI66: =$BA$12 -> Exotics
B67: 3º MT Ic Market demo | C67: 57 | D67: 29 | E67: 6ª F | F67: 21 de Julho | G67: Tarde | H67: Majors | I67: NZDUSD | J67: Breakout | K67: 3m | L67: short | M67: w | Q67: =AL66 -> 7652.3236 | R67: =IF(Q67="","",S67*Q67/100%) -> 76.523236 | S67: 0.01 | U67: 0.61928 | V67: 0.61967 | W67: =IF(V67="","",IF(L67="Long",U67-V67,V67-U67)) -> 0.00039 | X67: =IF(W67="","",R67) -> 76.523236 | Y67: 0.61807 | Z67: =IF(Y67="","",IF(L67="Long",Y67-U67,U67-Y67)) -> 0.00121 | AA67: =IF(AB67="","",AB67*X67/1) -> 237.41825 | AB67: =IF(Z67="","",Z67*1/W67) -> 3.1025641 | AC67: 21 de Julho | AD67: 0.61807 | AE67: 0 | AF67: 0 | AG67: =+AA67 -> 237.41825 | AH67: =IF(AG67="","",AG67+AF67+AE67) -> 237.41825 | AI67: =IF(AD67="","",IF(L67="Long",AD67-U67,U67-AD67)) -> 0.00121 | AJ67: =IF(AI67="","",AG67*S67/X67) -> 0.031025641 | AK67: =IF(AI67="","",(AG67+AF67+AE67)*S67/X67) -> 0.031025641 | AL67: =Q67+AG67 -> 7889.7418 | BH67: USDSEK | BI67: =$BA$12 -> Exotics
B68: MFF Challenge | C68: 58 | D68: 31 | E68: 3ª F | F68: 1 de Agosto | G68: Manhã | H68: Minors | I68: EURGBP | J68: Breakout | K68: 1h | L68: short | M68: L | Q68: =AL67 -> 7889.7418 | R68: =IF(Q68="","",S68*Q68/100%) -> 78.897418 | S68: 0.01 | U68: 0.85569 | V68: 0.85793 | W68: =IF(V68="","",IF(L68="Long",U68-V68,V68-U68)) -> 0.00224 | X68: =IF(W68="","",R68) -> 78.897418 | Y68: 0.84897 | Z68: =IF(Y68="","",IF(L68="Long",Y68-U68,U68-Y68)) -> 0.00672 | AA68: =IF(AB68="","",AB68*X68/1) -> 236.69226 | AB68: =IF(Z68="","",Z68*1/W68) -> 3 | AC68: 1 de Agosto | AD68: 0.85793 | AE68: 0 | AF68: 0 | AG68: =-X68 -> -78.897418 | AH68: =IF(AG68="","",AG68+AF68+AE68) -> -78.897418 | AI68: =IF(AD68="","",IF(L68="Long",AD68-U68,U68-AD68)) -> -0.00224 | AJ68: =IF(AI68="","",AG68*S68/X68) -> -0.01 | AK68: =IF(AI68="","",(AG68+AF68+AE68)*S68/X68) -> -0.01 | AL68: =Q68+AG68 -> 7810.8444 | BH68: USDTHB | BI68: =$BA$12 -> Exotics
B69: MFF Challenge | C69: 59 | D69: 31 | E69: 6ª F | F69: 4 de Agosto | G69: Manhã | H69: Majors | I69: GBPUSD | J69: Breakout | K69: 1m | L69: short | M69: L | Q69: =AL68 -> 7810.8444 | R69: =IF(Q69="","",S69*Q69/100%) -> 78.108444 | S69: 0.01 | U69: 1.26991 | V69: 1.27063 | W69: =IF(V69="","",IF(L69="Long",U69-V69,V69-U69)) -> 0.00072 | X69: =IF(W69="","",R69) -> 78.108444 | Y69: 1.26775 | Z69: =IF(Y69="","",IF(L69="Long",Y69-U69,U69-Y69)) -> 0.00216 | AA69: =IF(AB69="","",AB69*X69/1) -> 234.32533 | AB69: =IF(Z69="","",Z69*1/W69) -> 3 | AC69: 4 de Agosto | AD69: 1.27063 | AE69: 0 | AF69: 0 | AG69: =-X69 -> -78.108444 | AH69: =IF(AG69="","",AG69+AF69+AE69) -> -78.108444 | AI69: =IF(AD69="","",IF(L69="Long",AD69-U69,U69-AD69)) -> -0.00072 | AJ69: =IF(AI69="","",AG69*S69/X69) -> -0.01 | AK69: =IF(AI69="","",(AG69+AF69+AE69)*S69/X69) -> -0.01 | AL69: =Q69+AG69 -> 7732.736 | BH69: USDTRY | BI69: =$BA$12 -> Exotics
B70: MFF Challenge | C70: 60 | D70: 32 | E70: 2ª F | F70: 7 de Agosto | G70: Manhã | H70: Exotics | I70: GBPNOK | J70: Retest | K70: 4h | L70: short | M70: L | Q70: =AL69 -> 7732.736 | R70: =IF(Q70="","",S70*Q70/100%) -> 77.32736 | S70: 0.01 | U70: 12.96925 | V70: 13.11245 | W70: =IF(V70="","",IF(L70="Long",U70-V70,V70-U70)) -> 0.1432 | X70: =IF(W70="","",R70) -> 77.32736 | Y70: 12.53943 | Z70: =IF(Y70="","",IF(L70="Long",Y70-U70,U70-Y70)) -> 0.42982 | AA70: =IF(AB70="","",AB70*X70/1) -> 232.10088 | AB70: =IF(Z70="","",Z70*1/W70) -> 3.0015363 | AC70: 8 de Agosto | AD70: 13.11245 | AE70: 0 | AF70: 0 | AG70: =-X70 -> -77.32736 | AH70: =IF(AG70="","",AG70+AF70+AE70) -> -77.32736 | AI70: =IF(AD70="","",IF(L70="Long",AD70-U70,U70-AD70)) -> -0.1432 | AJ70: =IF(AI70="","",AG70*S70/X70) -> -0.01 | AK70: =IF(AI70="","",(AG70+AF70+AE70)*S70/X70) -> -0.01 | AL70: =Q70+AG70 -> 7655.4086 | BH70: USDZAR | BI70: =$BA$12 -> Exotics
B71: MFF Challenge | C71: 61 | D71: 32 | E71: 3ª F | F71: 8 de Agosto | G71: Manhã | H71: Minors | I71: AUDCHF | J71: Breakout | K71: 3m | L71: short | M71: L | Q71: =AL70 -> 7655.4086 | R71: =IF(Q71="","",S71*Q71/100%) -> 76.554086 | S71: 0.01 | U71: 0.56963 | V71: 0.5706 | W71: =IF(V71="","",IF(L71="Long",U71-V71,V71-U71)) -> 0.00097 | X71: =IF(W71="","",R71) -> 76.554086 | Y71: 0.56672 | Z71: =IF(Y71="","",IF(L71="Long",Y71-U71,U71-Y71)) -> 0.00291 | AA71: =IF(AB71="","",AB71*X71/1) -> 229.66226 | AB71: =IF(Z71="","",Z71*1/W71) -> 3 | AC71: 8 de Agosto | AD71: 0.5706 | AE71: 0 | AF71: 0 | AG71: =-X71 -> -76.554086 | AH71: =IF(AG71="","",AG71+AF71+AE71) -> -76.554086 | AI71: =IF(AD71="","",IF(L71="Long",AD71-U71,U71-AD71)) -> -0.00097 | AJ71: =IF(AI71="","",AG71*S71/X71) -> -0.01 | AK71: =IF(AI71="","",(AG71+AF71+AE71)*S71/X71) -> -0.01 | AL71: =Q71+AG71 -> 7578.8545 | BH71: XAGEUR | BI71: =$BA$14 -> Commod
B72: MFF Challenge | C72: 62 | D72: 35 | E72: 2ª F | F72: 28 de Agosto | G72: Tarde | H72: Minors | I72: CADJPY | J72: Breakout | K72: 15s | L72: Long | M72: L | Q72: =AL71 -> 7578.8545 | R72: =IF(Q72="","",S72*Q72/100%) -> 75.788545 | S72: 0.01 | U72: 107.953 | V72: 107.899 | W72: =IF(V72="","",IF(L72="Long",U72-V72,V72-U72)) -> 0.054 | X72: =IF(W72="","",R72) -> 75.788545 | Y72: 108.116 | Z72: =IF(Y72="","",IF(L72="Long",Y72-U72,U72-Y72)) -> 0.163 | AA72: =IF(AB72="","",AB72*X72/1) -> 228.76913 | AB72: =IF(Z72="","",Z72*1/W72) -> 3.0185185 | AC72: 28 de Agosto | AD72: 107.899 | AE72: 0 | AF72: 0 | AG72: =-X72 -> -75.788545 | AH72: =IF(AG72="","",AG72+AF72+AE72) -> -75.788545 | AI72: =IF(AD72="","",IF(L72="Long",AD72-U72,U72-AD72)) -> -0.054 | AJ72: =IF(AI72="","",AG72*S72/X72) -> -0.01 | AK72: =IF(AI72="","",(AG72+AF72+AE72)*S72/X72) -> -0.01 | AL72: =Q72+AG72 -> 7503.066 | BH72: XAGUSD | BI72: =$BA$14 -> Commod
B73: MFF Challenge | C73: 63 | D73: 35 | E73: 4ª F | F73: 30 de Agosto | G73: Manhã | H73: Minors | I73: CADJPY | J73: Breakout | K73: 3m | L73: long | M73: W | Q73: =AL72 -> 7503.066 | R73: =IF(Q73="","",S73*Q73/100%) -> 75.03066 | S73: 0.01 | U73: 107.771 | V73: 107.683 | W73: =IF(V73="","",IF(L73="Long",U73-V73,V73-U73)) -> 0.088 | X73: =IF(W73="","",R73) -> 75.03066 | Y73: 108.035 | Z73: =IF(Y73="","",IF(L73="Long",Y73-U73,U73-Y73)) -> 0.264 | AA73: =IF(AB73="","",AB73*X73/1) -> 225.09198 | AB73: =IF(Z73="","",Z73*1/W73) -> 3 | AC73: 30 de Agosto | AD73: 107.905 | AE73: 0 | AF73: 0 | AG73: =AA73 -> 225.09198 | AH73: =IF(AG73="","",AG73+AF73+AE73) -> 225.09198 | AI73: =IF(AD73="","",IF(L73="Long",AD73-U73,U73-AD73)) -> 0.134 | AJ73: =IF(AI73="","",AG73*S73/X73) -> 0.03 | AK73: =IF(AI73="","",(AG73+AF73+AE73)*S73/X73) -> 0.03 | AL73: =Q73+AG73 -> 7728.158 | BH73: XNGUSD | BI73: =$BA$14 -> Commod
B74: MFF Challenge | C74: 64 | D74: 35 | E74: 4ª F | F74: 30 de Agosto | G74: Manhã | H74: Minors | I74: CADJPY | J74: Breakout | K74: 15s | L74: long | M74: L | Q74: =AL73 -> 7728.158 | R74: =IF(Q74="","",S74*Q74/100%) -> 77.28158 | S74: 0.01 | U74: 107.949 | V74: 107.907 | W74: =IF(V74="","",IF(L74="Long",U74-V74,V74-U74)) -> 0.042 | X74: =IF(W74="","",R74) -> 77.28158 | Y74: 108.075 | Z74: =IF(Y74="","",IF(L74="Long",Y74-U74,U74-Y74)) -> 0.126 | AA74: =IF(AB74="","",AB74*X74/1) -> 231.84474 | AB74: =IF(Z74="","",Z74*1/W74) -> 3 | AC74: 30 de Agosto | AD74: 107.907 | AE74: 0 | AF74: 0 | AG74: =-X74 -> -77.28158 | AH74: =IF(AG74="","",AG74+AF74+AE74) -> -77.28158 | AI74: =IF(AD74="","",IF(L74="Long",AD74-U74,U74-AD74)) -> -0.042 | AJ74: =IF(AI74="","",AG74*S74/X74) -> -0.01 | AK74: =IF(AI74="","",(AG74+AF74+AE74)*S74/X74) -> -0.01 | AL74: =Q74+AG74 -> 7650.8764 | BH74: XTIUSD | BI74: =$BA$14 -> Commod
B75: MFF Challenge | C75: 65 | D75: 35 | E75: 4ª F | F75: 30 de Agosto | G75: Manhã | H75: Minors | I75: CADJPY | J75: Breakout | K75: 3m | L75: long | M75: L | Q75: =AL74 -> 7650.8764 | R75: =IF(Q75="","",S75*Q75/100%) -> 76.508764 | S75: 0.01 | U75: 107.95 | V75: 107.872 | W75: =IF(V75="","",IF(L75="Long",U75-V75,V75-U75)) -> 0.078 | X75: =IF(W75="","",R75) -> 76.508764 | Y75: 108.184 | Z75: =IF(Y75="","",IF(L75="Long",Y75-U75,U75-Y75)) -> 0.234 | AA75: =IF(AB75="","",AB75*X75/1) -> 229.52629 | AB75: =IF(Z75="","",Z75*1/W75) -> 3 | AC75: 30 de Agosto | AD75: 107.872 | AE75: 0 | AF75: 0 | AG75: =-X75 -> -76.508764 | AH75: =IF(AG75="","",AG75+AF75+AE75) -> -76.508764 | AI75: =IF(AD75="","",IF(L75="Long",AD75-U75,U75-AD75)) -> -0.078 | AJ75: =IF(AI75="","",AG75*S75/X75) -> -0.01 | AK75: =IF(AI75="","",(AG75+AF75+AE75)*S75/X75) -> -0.01 | AL75: =Q75+AG75 -> 7574.3676 | BH75: XBRUSD | BI75: =$BA$14 -> Commod
B76: MFF Challenge | C76: 66 | D76: 35 | E76: 5ª F | F76: 31 de Agosto | G76: Manhã | H76: Majors | I76: GBPUSD | J76: Breakout | K76: 15s | L76: short | M76: L | Q76: =AL75 -> 7574.3676 | R76: =IF(Q76="","",S76*Q76/100%) -> 75.743676 | S76: 0.01 | U76: 1.26754 | V76: 1.26811 | W76: =IF(V76="","",IF(L76="Long",U76-V76,V76-U76)) -> 0.00057 | X76: =IF(W76="","",R76) -> 75.743676 | Y76: 1.26583 | Z76: =IF(Y76="","",IF(L76="Long",Y76-U76,U76-Y76)) -> 0.00171 | AA76: =IF(AB76="","",AB76*X76/1) -> 227.23103 | AB76: =IF(Z76="","",Z76*1/W76) -> 3 | AC76: 31 de Agosto | AD76: 1.26811 | AE76: 0 | AF76: 0 | AG76: =-X76 -> -75.743676 | AH76: =IF(AG76="","",AG76+AF76+AE76) -> -75.743676 | AI76: =IF(AD76="","",IF(L76="Long",AD76-U76,U76-AD76)) -> -0.00057 | AJ76: =IF(AI76="","",AG76*S76/X76) -> -0.01 | AK76: =IF(AI76="","",(AG76+AF76+AE76)*S76/X76) -> -0.01 | AL76: =Q76+AG76 -> 7498.624 | BH76: XPTUSD | BI76: =$BA$14 -> Commod
B77: Fusion demo | C77: 67 | D77: 38 | E77: 5ª F | F77: 21 de Setembro | G77: Manhã | H77: Minors | I77: AUDJPY | J77: Breakout | K77: 1D | L77: Long | M77: W | Q77: =AL76 -> 7498.624 | R77: =IF(Q77="","",S77*Q77/100%) -> 74.98624 | S77: 0.01 | U77: 94.934 | V77: 94.337 | W77: =IF(V77="","",IF(L77="Long",U77-V77,V77-U77)) -> 0.597 | X77: =IF(W77="","",R77) -> 74.98624 | Y77: 96.717 | Z77: =IF(Y77="","",IF(L77="Long",Y77-U77,U77-Y77)) -> 1.783 | AA77: =IF(AB77="","",AB77*X77/1) -> 223.95388 | AB77: =IF(Z77="","",Z77*1/W77) -> 2.9865997 | AC77: 29 de Setembro | AD77: 96.717 | AE77: 10.7 | AF77: 86.37 | AG77: =AA77 -> 223.95388 | AH77: =IF(AG77="","",AG77+AF77+AE77) -> 321.02388 | AI77: =IF(AD77="","",IF(L77="Long",AD77-U77,U77-AD77)) -> 1.783 | AJ77: =IF(AI77="","",AG77*S77/X77) -> 0.029865997 | AK77: =IF(AI77="","",(AG77+AF77+AE77)*S77/X77) -> 0.042811038 | AL77: =Q77+AG77 -> 7722.5778 | BH77: XPDUSD | BI77: =$BA$14 -> Commod
B78: Trading view (não consegui encontrar no Fusion o wheat) | C78: 68 | D78: 44 | E78: 3ª F | F78: 31 de Outubro | G78: Noite | H78: Commod | I78: Wheatusd | J78: Breakout | K78: 8h | L78: Short | M78: L | Q78: =AL77 -> 7722.5778 | R78: =IF(Q78="","",S78*Q78/100%) -> 77.225778 | S78: 0.01 | U78: 5.486 | V78: 5.744 | W78: =IF(V78="","",IF(L78="Long",U78-V78,V78-U78)) -> 0.258 | X78: =IF(W78="","",R78) -> 77.225778 | Y78: 4.712 | Z78: =IF(Y78="","",IF(L78="Long",Y78-U78,U78-Y78)) -> 0.774 | AA78: =IF(AB78="","",AB78*X78/1) -> 231.67733 | AB78: =IF(Z78="","",Z78*1/W78) -> 3 | AC78: 8 de Novembro | AD78: 5.744 | AE78: 0 | AF78: 0 | AG78: =-X78 -> -77.225778 | AH78: =IF(AG78="","",AG78+AF78+AE78) -> -77.225778 | AI78: =IF(AD78="","",IF(L78="Long",AD78-U78,U78-AD78)) -> -0.258 | AJ78: =IF(AI78="","",AG78*S78/X78) -> -0.01 | AK78: =IF(AI78="","",(AG78+AF78+AE78)*S78/X78) -> -0.01 | AL78: =Q78+AG78 -> 7645.3521 | BH78: XAUEUR | BI78: =$BA$14 -> Commod
B79: Trading view (não consegui encontrar no Fusion o wheat) | C79: 69 | D79: 44 | E79: 5ª F | F79: 1 de Novembro | G79: Noite | H79: Commod | I79: Wheatusd | J79: Retest | K79: 8h | L79: Short | M79: L | Q79: =AL78 -> 7645.3521 | R79: =IF(Q79="","",S79*Q79/100%) -> 76.453521 | S79: 0.01 | U79: 5.525 | V79: 5.632 | W79: =IF(V79="","",IF(L79="Long",U79-V79,V79-U79)) -> 0.107 | X79: =IF(W79="","",R79) -> 76.453521 | Y79: 5.204 | Z79: =IF(Y79="","",IF(L79="Long",Y79-U79,U79-Y79)) -> 0.321 | AA79: =IF(AB79="","",AB79*X79/1) -> 229.36056 | AB79: =IF(Z79="","",Z79*1/W79) -> 3 | AC79: 3 de Novembro | AD79: 5.632 | AE79: 0 | AF79: 0 | AG79: =-X79 -> -76.453521 | AH79: =IF(AG79="","",AG79+AF79+AE79) -> -76.453521 | AI79: =IF(AD79="","",IF(L79="Long",AD79-U79,U79-AD79)) -> -0.107 | AJ79: =IF(AI79="","",AG79*S79/X79) -> -0.01 | AK79: =IF(AI79="","",(AG79+AF79+AE79)*S79/X79) -> -0.01 | AL79: =Q79+AG79 -> 7568.8985 | BH79: XAUUSD | BI79: =$BA$14 -> Commod
B80: Trading view (não consegui apanhar a tempo que pôr no fusion) | C80: 70 | D80: 45 | E80: 3ª F | F80: 7 de Novembro | G80: Manhã | H80: Minors | I80: EURCAD | J80: Breakout | K80: 2h | L80: Long | M80: W | Q80: =AL79 -> 7568.8985 | R80: =IF(Q80="","",S80*Q80/100%) -> 75.688985 | S80: 0.01 | U80: 1.46952 | V80: 1.46411 | W80: =IF(V80="","",IF(L80="Long",U80-V80,V80-U80)) -> 0.00541 | X80: =IF(W80="","",R80) -> 75.688985 | Y80: 1.48573 | Z80: =IF(Y80="","",IF(L80="Long",Y80-U80,U80-Y80)) -> 0.01621 | AA80: =IF(AB80="","",AB80*X80/1) -> 226.78714 | AB80: =IF(Z80="","",Z80*1/W80) -> 2.9963031 | AC80: 14 de Novembro | AD80: 1.48573 | AE80: 0 | AF80: 0 | AG80: =Y80 -> 1.48573 | AH80: =IF(AG80="","",AG80+AF80+AE80) -> 1.48573 | AI80: =IF(AD80="","",IF(L80="Long",AD80-U80,U80-AD80)) -> 0.01621 | AJ80: =IF(AI80="","",AG80*S80/X80) -> 0.00019629408 | AK80: =IF(AI80="","",(AG80+AF80+AE80)*S80/X80) -> 0.00019629408 | AL80: =Q80+AG80 -> 7570.3843 | BH80: XAUAUD | BI80: =$BA$14 -> Commod
B81: Fusion demo | C81: 71 | D81: 47 | E81: 6ª F | F81: 24 de Novembro | G81: Manhã | H81: Exotics | I81: EURSGD | J81: Breakout | K81: 2h | L81: Long | M81: L | Q81: =AL80 -> 7570.3843 | R81: =IF(Q81="","",S81*Q81/100%) -> 75.703843 | S81: 0.01 | U81: 1.46371 | V81: 1.45979 | W81: =IF(V81="","",IF(L81="Long",U81-V81,V81-U81)) -> 0.00392 | X81: =IF(W81="","",R81) -> 75.703843 | Y81: 1.47547 | Z81: =IF(Y81="","",IF(L81="Long",Y81-U81,U81-Y81)) -> 0.01176 | AA81: =IF(AB81="","",AB81*X81/1) -> 227.11153 | AB81: =IF(Z81="","",Z81*1/W81) -> 3 | AC81: 30 de Novembro | AD81: 1.45979 | AE81: 0 | AF81: 0 | AG81: =-X81 -> -75.703843 | AH81: =IF(AG81="","",AG81+AF81+AE81) -> -75.703843 | AI81: =IF(AD81="","",IF(L81="Long",AD81-U81,U81-AD81)) -> -0.00392 | AJ81: =IF(AI81="","",AG81*S81/X81) -> -0.01 | AK81: =IF(AI81="","",(AG81+AF81+AE81)*S81/X81) -> -0.01 | AL81: =Q81+AG81 -> 7494.6804 | BH81: SUGAR | BI81: =$BA$14 -> Commod
B82: Fusion demo | C82: 72 | D82: 58 | E82: 2ª F | F82: 27 de Novembro | G82: Manhã | H82: Minors | I82: AUDCAD | J82: Retest | K82: 1h | L82: Long | M82: L | Q82: =AL81 -> 7494.6804 | R82: =IF(Q82="","",S82*Q82/100%) -> 74.946804 | S82: 0.01 | U82: 0.8998 | V82: 0.8964 | W82: =IF(V82="","",IF(L82="Long",U82-V82,V82-U82)) -> 0.0034 | X82: =IF(W82="","",R82) -> 74.946804 | Y82: 0.90991 | Z82: =IF(Y82="","",IF(L82="Long",Y82-U82,U82-Y82)) -> 0.01011 | AA82: =IF(AB82="","",AB82*X82/1) -> 222.85653 | AB82: =IF(Z82="","",Z82*1/W82) -> 2.9735294 | AC82: 30 de Novembro | AD82: 0.8964 | AE82: 0 | AF82: 0 | AG82: =-X82 -> -74.946804 | AH82: =IF(AG82="","",AG82+AF82+AE82) -> -74.946804 | AI82: =IF(AD82="","",IF(L82="Long",AD82-U82,U82-AD82)) -> -0.0034 | AJ82: =IF(AI82="","",AG82*S82/X82) -> -0.01 | AK82: =IF(AI82="","",(AG82+AF82+AE82)*S82/X82) -> -0.01 | AL82: =Q82+AG82 -> 7419.7336 | BH82: DE30 | BI82: indices
B83: Fusion demo | C83: 73 | D83: 58 | E83: 2ª F | F83: 27 de Novembro | G83: Tarde | H83: Exotics | I83: EURNOK | J83: Breakout | K83: 1h | L83: Short | M83: L | Q83: =AL82 -> 7419.7336 | R83: =IF(Q83="","",S83*Q83/100%) -> 74.197336 | S83: 0.01 | U83: 11.67358 | V83: 11.75602 | W83: =IF(V83="","",IF(L83="Long",U83-V83,V83-U83)) -> 0.08244 | X83: =IF(W83="","",R83) -> 74.197336 | Y83: 11.48331 | Z83: =IF(Y83="","",IF(L83="Long",Y83-U83,U83-Y83)) -> 0.19027 | AA83: =IF(AB83="","",AB83*X83/1) -> 171.24608 | AB83: =IF(Z83="","",Z83*1/W83) -> 2.3079816 | AC83: 30 de Novembro | AD83: 11.75602 | AE83: 0 | AF83: 0 | AG83: =-X83 -> -74.197336 | AH83: =IF(AG83="","",AG83+AF83+AE83) -> -74.197336 | AI83: =IF(AD83="","",IF(L83="Long",AD83-U83,U83-AD83)) -> -0.08244 | AJ83: =IF(AI83="","",AG83*S83/X83) -> -0.01 | AK83: =IF(AI83="","",(AG83+AF83+AE83)*S83/X83) -> -0.01 | AL83: =Q83+AG83 -> 7345.5363 | BH83: SOYBEANF1 | BI83: Commod
B84: Trading view (não consegui apanhar a tempo que pôr no fusion) | C84: 74 | D84: 47 | E84: 4ª F | F84: 22 de Novembro | G84: Manhã | H84: Commod | I84: XAUUSD | J84: Retest | K84: 4h | L84: Long | M84: W | Q84: =AL83 -> 7345.5363 | R84: =IF(Q84="","",S84*Q84/100%) -> 73.455363 | S84: 0.01 | U84: 1993.676 | V84: 1982.651 | W84: =IF(V84="","",IF(L84="Long",U84-V84,V84-U84)) -> 11.025 | X84: =IF(W84="","",R84) -> 73.455363 | Y84: 2026.881 | Z84: =IF(Y84="","",IF(L84="Long",Y84-U84,U84-Y84)) -> 33.205 | AA84: =IF(AB84="","",AB84*X84/1) -> 221.23223 | AB84: =IF(Z84="","",Z84*1/W84) -> 3.0117914 | AC84: 28 de Novembro | AD84: 2026.881 | AE84: 0 | AF84: 0 | AG84: =AA84 -> 221.23223 | AH84: =IF(AG84="","",AG84+AF84+AE84) -> 221.23223 | AI84: =IF(AD84="","",IF(L84="Long",AD84-U84,U84-AD84)) -> 33.205 | AJ84: =IF(AI84="","",AG84*S84/X84) -> 0.030117914 | AK84: =IF(AI84="","",(AG84+AF84+AE84)*S84/X84) -> 0.030117914 | AL84: =Q84+AG84 -> 7566.7685 | BH84: UK100 | BI84: indices
B85: Fusion demo | C85: 75 | D85: 48 | E85: 3ª F | F85: 28 de Novembro | G85: Tarde | H85: Minors | I85: NZDUSD | J85: Breakout | K85: 4h | L85: Long | M85: L | Q85: =AL84 -> 7566.7685 | R85: =IF(Q85="","",S85*Q85/100%) -> 75.667685 | S85: 0.01 | U85: 0.53974 | V85: 0.53424 | W85: =IF(V85="","",IF(L85="Long",U85-V85,V85-U85)) -> 0.0055 | X85: =IF(W85="","",R85) -> 75.667685 | Y85: 0.54931 | Z85: =IF(Y85="","",IF(L85="Long",Y85-U85,U85-Y85)) -> 0.00957 | AA85: =IF(AB85="","",AB85*X85/1) -> 131.66177 | AB85: =IF(Z85="","",Z85*1/W85) -> 1.74 | AC85: 6 de Dezembro | AD85: 0.53773 | AE85: 0 | AF85: 0 | AG85: =-X85 -> -75.667685 | AH85: =IF(AG85="","",AG85+AF85+AE85) -> -75.667685 | AI85: =IF(AD85="","",IF(L85="Long",AD85-U85,U85-AD85)) -> -0.00201 | AJ85: =IF(AI85="","",AG85*S85/X85) -> -0.01 | AK85: =IF(AI85="","",(AG85+AF85+AE85)*S85/X85) -> -0.01 | AL85: =Q85+AG85 -> 7491.1008 | BH85: BTCUSD | BI85: Crypto
B86: Fusion demo | C86: 76 | D86: 48 | E86: 5ª F | F86: 29 de Novembro | G86: Tarde | H86: Exotics | I86: USDCNH | J86: Retest | K86: 2h | L86: Short | M86: L | Q86: =AL85 -> 7491.1008 | R86: =IF(Q86="","",S86*Q86/100%) -> 74.911008 | S86: 0.01 | U86: 7.14061 | V86: 7.16701 | W86: =IF(V86="","",IF(L86="Long",U86-V86,V86-U86)) -> 0.0264 | X86: =IF(W86="","",R86) -> 74.911008 | Y86: 7.06148 | Z86: =IF(Y86="","",IF(L86="Long",Y86-U86,U86-Y86)) -> 0.07913 | AA86: =IF(AB86="","",AB86*X86/1) -> 224.5344 | AB86: =IF(Z86="","",Z86*1/W86) -> 2.9973485 | AC86: 5 de Dezembro | AD86: 7.16701 | AE86: 0 | AF86: 0 | AG86: =-X86 -> -74.911008 | AH86: =IF(AG86="","",AG86+AF86+AE86) -> -74.911008 | AI86: =IF(AD86="","",IF(L86="Long",AD86-U86,U86-AD86)) -> -0.0264 | AJ86: =IF(AI86="","",AG86*S86/X86) -> -0.01 | AK86: =IF(AI86="","",(AG86+AF86+AE86)*S86/X86) -> -0.01 | AL86: =Q86+AG86 -> 7416.1898 | BH86: JP225 | BI86: Indices
B87: Fusion demo | C87: 77 | D87: 51 | E87: 5ª F | F87: 21 de Dezembro | G87: Manhã | H87: Minors | I87: GBPAUD | J87: Breakout | K87: 30m | L87: Short | M87: L | Q87: =AL86 -> 7416.1898 | R87: =IF(Q87="","",S87*Q87/100%) -> 74.161898 | S87: 0.01 | U87: 1.87128 | V87: 1.87644 | W87: =IF(V87="","",IF(L87="Long",U87-V87,V87-U87)) -> 0.00516 | X87: =IF(W87="","",R87) -> 74.161898 | Y87: 1.85582 | Z87: =IF(Y87="","",IF(L87="Long",Y87-U87,U87-Y87)) -> 0.01546 | AA87: =IF(AB87="","",AB87*X87/1) -> 222.19825 | AB87: =IF(Z87="","",Z87*1/W87) -> 2.996124 | AC87: 21 de Dezembro | AD87: 1.87644 | AE87: 0 | AF87: 0 | AG87: =-X87 -> -74.161898 | AH87: =IF(AG87="","",AG87+AF87+AE87) -> -74.161898 | AI87: =IF(AD87="","",IF(L87="Long",AD87-U87,U87-AD87)) -> -0.00516 | AJ87: =IF(AI87="","",AG87*S87/X87) -> -0.01 | AK87: =IF(AI87="","",(AG87+AF87+AE87)*S87/X87) -> -0.01 | AL87: =Q87+AG87 -> 7342.0279 | BH87: Wheatusd | BI87: Commod
C88: 78 | Q88: =AL87 -> 7342.0279 | R88: =IF(Q88="","",S88*Q88/100%) -> 0 | W88: =IF(V88="","",IF(L88="Long",U88-V88,V88-U88)) | X88: =IF(W88="","",R88) | Z88: =IF(Y88="","",IF(L88="Long",Y88-U88,U88-Y88)) | AA88: =IF(AB88="","",AB88*X88/1) | AB88: =IF(Z88="","",Z88*1/W88) | AH88: =IF(AG88="","",AG88+AF88+AE88) | AI88: =IF(AD88="","",IF(L88="Long",AD88-U88,U88-AD88)) | AJ88: =IF(AI88="","",AG88*S88/X88) | AK88: =IF(AI88="","",(AG88+AF88+AE88)*S88/X88) | AL88: =Q88+AG88 -> 7342.0279
C89: 79 | Q89: =AL88 -> 7342.0279 | R89: =IF(Q89="","",S89*Q89/100%) -> 0 | W89: =IF(V89="","",IF(L89="Long",U89-V89,V89-U89)) | X89: =IF(W89="","",R89) | Z89: =IF(Y89="","",IF(L89="Long",Y89-U89,U89-Y89)) | AA89: =IF(AB89="","",AB89*X89/1) | AB89: =IF(Z89="","",Z89*1/W89) | AH89: =IF(AG89="","",AG89+AF89+AE89) | AI89: =IF(AD89="","",IF(L89="Long",AD89-U89,U89-AD89)) | AJ89: =IF(AI89="","",AG89*S89/X89) | AK89: =IF(AI89="","",(AG89+AF89+AE89)*S89/X89) | AL89: =Q89+AG89 -> 7342.0279
C90: 80 | Q90: =AL89 -> 7342.0279 | R90: =IF(Q90="","",S90*Q90/100%) -> 0 | W90: =IF(V90="","",IF(L90="Long",U90-V90,V90-U90)) | X90: =IF(W90="","",R90) | Z90: =IF(Y90="","",IF(L90="Long",Y90-U90,U90-Y90)) | AA90: =IF(AB90="","",AB90*X90/1) | AB90: =IF(Z90="","",Z90*1/W90) | AH90: =IF(AG90="","",AG90+AF90+AE90) | AI90: =IF(AD90="","",IF(L90="Long",AD90-U90,U90-AD90)) | AJ90: =IF(AI90="","",AG90*S90/X90) | AK90: =IF(AI90="","",(AG90+AF90+AE90)*S90/X90) | AL90: =Q90+AG90 -> 7342.0279
C91: 81 | Q91: =AL90 -> 7342.0279 | R91: =IF(Q91="","",S91*Q91/100%) -> 0 | W91: =IF(V91="","",IF(L91="Long",U91-V91,V91-U91)) | X91: =IF(W91="","",R91) | Z91: =IF(Y91="","",IF(L91="Long",Y91-U91,U91-Y91)) | AA91: =IF(AB91="","",AB91*X91/1) | AB91: =IF(Z91="","",Z91*1/W91) | AH91: =IF(AG91="","",AG91+AF91+AE91) | AI91: =IF(AD91="","",IF(L91="Long",AD91-U91,U91-AD91)) | AJ91: =IF(AI91="","",AG91*S91/X91) | AK91: =IF(AI91="","",(AG91+AF91+AE91)*S91/X91) | AL91: =Q91+AG91 -> 7342.0279
C92: 82 | Q92: =AL91 -> 7342.0279 | R92: =IF(Q92="","",S92*Q92/100%) -> 0 | W92: =IF(V92="","",IF(L92="Long",U92-V92,V92-U92)) | X92: =IF(W92="","",R92) | Z92: =IF(Y92="","",IF(L92="Long",Y92-U92,U92-Y92)) | AA92: =IF(AB92="","",AB92*X92/1) | AB92: =IF(Z92="","",Z92*1/W92) | AH92: =IF(AG92="","",AG92+AF92+AE92) | AI92: =IF(AD92="","",IF(L92="Long",AD92-U92,U92-AD92)) | AJ92: =IF(AI92="","",AG92*S92/X92) | AK92: =IF(AI92="","",(AG92+AF92+AE92)*S92/X92) | AL92: =Q92+AG92 -> 7342.0279
C93: 83 | Q93: =AL92 -> 7342.0279 | R93: =IF(Q93="","",S93*Q93/100%) -> 0 | W93: =IF(V93="","",IF(L93="Long",U93-V93,V93-U93)) | X93: =IF(W93="","",R93) | Z93: =IF(Y93="","",IF(L93="Long",Y93-U93,U93-Y93)) | AA93: =IF(AB93="","",AB93*X93/1) | AB93: =IF(Z93="","",Z93*1/W93) | AH93: =IF(AG93="","",AG93+AF93+AE93) | AI93: =IF(AD93="","",IF(L93="Long",AD93-U93,U93-AD93)) | AJ93: =IF(AI93="","",AG93*S93/X93) | AK93: =IF(AI93="","",(AG93+AF93+AE93)*S93/X93) | AL93: =Q93+AG93 -> 7342.0279
C94: 84 | Q94: =AL93 -> 7342.0279 | R94: =IF(Q94="","",S94*Q94/100%) -> 0 | W94: =IF(V94="","",IF(L94="Long",U94-V94,V94-U94)) | X94: =IF(W94="","",R94) | Z94: =IF(Y94="","",IF(L94="Long",Y94-U94,U94-Y94)) | AA94: =IF(AB94="","",AB94*X94/1) | AB94: =IF(Z94="","",Z94*1/W94) | AH94: =IF(AG94="","",AG94+AF94+AE94) | AI94: =IF(AD94="","",IF(L94="Long",AD94-U94,U94-AD94)) | AJ94: =IF(AI94="","",AG94*S94/X94) | AK94: =IF(AI94="","",(AG94+AF94+AE94)*S94/X94) | AL94: =Q94+AG94 -> 7342.0279
C95: 85 | Q95: =AL94 -> 7342.0279 | R95: =IF(Q95="","",S95*Q95/100%) -> 0 | W95: =IF(V95="","",IF(L95="Long",U95-V95,V95-U95)) | X95: =IF(W95="","",R95) | Z95: =IF(Y95="","",IF(L95="Long",Y95-U95,U95-Y95)) | AA95: =IF(AB95="","",AB95*X95/1) | AB95: =IF(Z95="","",Z95*1/W95) | AH95: =IF(AG95="","",AG95+AF95+AE95) | AI95: =IF(AD95="","",IF(L95="Long",AD95-U95,U95-AD95)) | AJ95: =IF(AI95="","",AG95*S95/X95) | AK95: =IF(AI95="","",(AG95+AF95+AE95)*S95/X95) | AL95: =Q95+AG95 -> 7342.0279
C96: 86 | Q96: =AL95 -> 7342.0279 | R96: =IF(Q96="","",S96*Q96/100%) -> 0 | W96: =IF(V96="","",IF(L96="Long",U96-V96,V96-U96)) | X96: =IF(W96="","",R96) | Z96: =IF(Y96="","",IF(L96="Long",Y96-U96,U96-Y96)) | AA96: =IF(AB96="","",AB96*X96/1) | AB96: =IF(Z96="","",Z96*1/W96) | AH96: =IF(AG96="","",AG96+AF96+AE96) | AI96: =IF(AD96="","",IF(L96="Long",AD96-U96,U96-AD96)) | AJ96: =IF(AI96="","",AG96*S96/X96) | AK96: =IF(AI96="","",(AG96+AF96+AE96)*S96/X96) | AL96: =Q96+AG96 -> 7342.0279
C97: 87 | Q97: =AL96 -> 7342.0279 | R97: =IF(Q97="","",S97*Q97/100%) -> 0 | W97: =IF(V97="","",IF(L97="Long",U97-V97,V97-U97)) | X97: =IF(W97="","",R97) | Z97: =IF(Y97="","",IF(L97="Long",Y97-U97,U97-Y97)) | AA97: =IF(AB97="","",AB97*X97/1) | AB97: =IF(Z97="","",Z97*1/W97) | AH97: =IF(AG97="","",AG97+AF97+AE97) | AI97: =IF(AD97="","",IF(L97="Long",AD97-U97,U97-AD97)) | AJ97: =IF(AI97="","",AG97*S97/X97) | AK97: =IF(AI97="","",(AG97+AF97+AE97)*S97/X97) | AL97: =Q97+AG97 -> 7342.0279
C98: 88 | Q98: =AL97 -> 7342.0279 | R98: =IF(Q98="","",S98*Q98/100%) -> 0 | W98: =IF(V98="","",IF(L98="Long",U98-V98,V98-U98)) | X98: =IF(W98="","",R98) | Z98: =IF(Y98="","",IF(L98="Long",Y98-U98,U98-Y98)) | AA98: =IF(AB98="","",AB98*X98/1) | AB98: =IF(Z98="","",Z98*1/W98) | AH98: =IF(AG98="","",AG98+AF98+AE98) | AI98: =IF(AD98="","",IF(L98="Long",AD98-U98,U98-AD98)) | AJ98: =IF(AI98="","",AG98*S98/X98) | AK98: =IF(AI98="","",(AG98+AF98+AE98)*S98/X98) | AL98: =Q98+AG98 -> 7342.0279
C99: 89 | Q99: =AL98 -> 7342.0279 | R99: =IF(Q99="","",S99*Q99/100%) -> 0 | W99: =IF(V99="","",IF(L99="Long",U99-V99,V99-U99)) | X99: =IF(W99="","",R99) | Z99: =IF(Y99="","",IF(L99="Long",Y99-U99,U99-Y99)) | AA99: =IF(AB99="","",AB99*X99/1) | AB99: =IF(Z99="","",Z99*1/W99) | AH99: =IF(AG99="","",AG99+AF99+AE99) | AI99: =IF(AD99="","",IF(L99="Long",AD99-U99,U99-AD99)) | AJ99: =IF(AI99="","",AG99*S99/X99) | AK99: =IF(AI99="","",(AG99+AF99+AE99)*S99/X99) | AL99: =Q99+AG99 -> 7342.0279
... C110: 100 | Q110: =AL109 -> 7342.0279 | R110: =IF(Q110="","",S110*Q110/100%) -> 0 | W110: =IF(V110="","",IF(L110="Long",U110-V110,V110-U110)) | X110: =IF(W110="","",R110) | Z110: =IF(Y110="","",IF(L110="Long",Y110-U110,U110-Y110)) | AA110: =IF(AB110="","",AB110*X110/1) | AB110: =IF(Z110="","",Z110*1/W110) | AH110: =IF(AG110="","",AG110+AF110+AE110) | AI110: =IF(AD110="","",IF(L110="Long",AD110-U110,U110-AD110)) | AJ110: =IF(AI110="","",AG110*S110/X110) | AK110: =IF(AI110="","",(AG110+AF110+AE110)*S110/X110) | AL110: =Q110+AG110 -> 7342.0279
Q111: =AL110 -> 7342.0279 | R111: =IF(Q111="","",S111*Q111/100%) -> 0 | W111: =IF(V111="","",IF(L111="Long",U111-V111,V111-U111)) | X111: =IF(W111="","",R111) | Z111: =IF(Y111="","",IF(L111="Long",Y111-U111,U111-Y111)) | AA111: =IF(AB111="","",AB111*X111/1) | AB111: =IF(Z111="","",Z111*1/W111) | AH111: =IF(AG111="","",AG111+AF111+AE111) | AI111: =IF(AD111="","",IF(L111="Long",AD111-U111,U111-AD111)) | AJ111: =IF(AI111="","",AG111*S111/X111) | AK111: =IF(AI111="","",(AG111+AF111+AE111)*S111/X111) | AL111: =Q111+AG111 -> 7342.0279
Q112: =AL111 -> 7342.0279 | R112: =IF(Q112="","",S112*Q112/100%) -> 0 | W112: =IF(V112="","",IF(L112="Long",U112-V112,V112-U112)) | X112: =IF(W112="","",R112) | Z112: =IF(Y112="","",IF(L112="Long",Y112-U112,U112-Y112)) | AA112: =IF(AB112="","",AB112*X112/1) | AB112: =IF(Z112="","",Z112*1/W112) | AH112: =IF(AG112="","",AG112+AF112+AE112) | AI112: =IF(AD112="","",IF(L112="Long",AD112-U112,U112-AD112)) | AJ112: =IF(AI112="","",AG112*S112/X112) | AK112: =IF(AI112="","",(AG112+AF112+AE112)*S112/X112) | AL112: =Q112+AG112 -> 7342.0279
...

Sheet Weekly Analysis
A1: Nº da semana: | B1: 1 | C1: 2 | D1: 3 | E1: 4 | F1: 5 | G1: 6 | H1: 7 | I1: 8 | J1: 9 | K1: 10 | L1: 11 | M1: 12 | N1: 13 | O1: 14 | P1: 15 | Q1: 16 | R1: 17 | S1: 18 | T1: 19 | U1: 20 | V1: 21 | W1: 22 | X1: 23 | Y1: 24 | Z1: 25 | AA1: 26 | AB1: 27 | AC1: 28 | AD1: 29 | AE1: 30 | AF1: 31 | AG1: 32 | AH1: 33 | AI1: 34 | AJ1: 35 | AK1: 36 | AL1: 37 | AM1: 38 | AN1: 39 | AO1: 40 | AP1: 41 | AQ1: 42 | AR1: 43 | AS1: 44 | AT1: 45 | AU1: 46 | AV1: 47 | AW1: 48 | AX1: 49 | AY1: 50 | AZ1: 51 | BA1: 52
A2: Total de Operações Abertas: | B2: =COUNTIF('Registo de operações'!$D$11:$D$1001,B1) -> 0 | C2: =COUNTIF('Registo de operações'!$D$11:$D$1001,C1) -> 0 | D2: =COUNTIF('Registo de operações'!$D$11:$D$1001,D1) -> 0 | E2: =COUNTIF('Registo de operações'!$D$11:$D$1001,E1) -> 0 | F2: =COUNTIF('Registo de operações'!$D$11:$D$1001,F1) -> 9 | G2: =COUNTIF('Registo de operações'!$D$11:$D$1001,G1) -> 3 | H2: =COUNTIF('Registo de operações'!$D$11:$D$1001,H1) -> 10 | I2: =COUNTIF('Registo de operações'!$D$11:$D$1001,I1) -> 0 | ... BA2: =COUNTIF('Registo de operações'!$D$11:$D$1001,BA1) -> 0
A3: Total de Operações Vencedoras: | B3: =COUNTIFS('Registo de operações'!$D$11:$D$1001,B1,'Registo de operações'!$M$11:$M$1001,'Registo de operações'!$AW$10) -> 0 | C3: =COUNTIFS('Registo de operações'!$D$11:$D$1001,C1,'Registo de operações'!$M$11:$M$1001,'Registo de operações'!$AW$10) -> 0 | D3: =COUNTIFS('Registo de operações'!$D$11:$D$1001,D1,'Registo de operações'!$M$11:$M$1001,'Registo de operações'!$AW$10) -> 0 | E3: =COUNTIFS('Registo de operações'!$D$11:$D$1001,E1,'Registo de operações'!$M$11:$M$1001,'Registo de operações'!$AW$10) -> 0 | F3: =COUNTIFS('Registo de operações'!$D$11:$D$1001,F1,'Registo de operações'!$M$11:$M$1001,'Registo de operações'!$AW$10) -> 5 | G3: =COUNTIFS('Registo de operações'!$D$11:$D$1001,G1,'Registo de operações'!$M$11:$M$1001,'Registo de operações'!$AW$10) -> 1 | H3: =COUNTIFS('Registo de operações'!$D$11:$D$1001,H1,'Registo de operações'!$M$11:$M$1001,'Registo de operações'!$AW$10) -> 6 | I3: =COUNTIFS('Registo de operações'!$D$11:$D$1001,I1,'Registo de operações'!$M$11:$M$1001,'Registo de operações'!$AW$10) -> 0 | ... BA3: =COUNTIFS('Registo de operações'!$D$11:$D$1001,BA1,'Registo de operações'!$M$11:$M$1001,'Registo de operações'!$AW$10) -> 0
A4: Taxa de Acerto: | B4: =B3/B2 -> #DIV/0! | C4: =C3/C2 -> #DIV/0! | D4: =D3/D2 -> #DIV/0! | E4: =E3/E2 -> #DIV/0! | F4: =F3/F2 -> 0.55555556 | G4: =G3/G2 -> 0.33333333 | H4: =H3/H2 -> 0.6 | I4: =I3/I2 -> #DIV/0! | ... BA4: =BA3/BA2 -> #DIV/0!
A5: % Realizada: | B5: =SUMIFS('Registo de operações'!$AJ$11:$AJ$1001,'Registo de operações'!$D$11:$D$1001,'Weekly Analysis'!B1) -> 0 | C5: =SUMIFS('Registo de operações'!$AJ$11:$AJ$1001,'Registo de operações'!$D$11:$D$1001,'Weekly Analysis'!C1) -> 0 | D5: =SUMIFS('Registo de operações'!$AJ$11:$AJ$1001,'Registo de operações'!$D$11:$D$1001,'Weekly Analysis'!D1) -> 0 | E5: =SUMIFS('Registo de operações'!$AJ$11:$AJ$1001,'Registo de operações'!$D$11:$D$1001,'Weekly Analysis'!E1) -> 0 | F5: =SUMIFS('Registo de operações'!$AJ$11:$AJ$1001,'Registo de operações'!$D$11:$D$1001,'Weekly Analysis'!F1) -> 0.11112704 | G5: =SUMIFS('Registo de operações'!$AJ$11:$AJ$1001,'Registo de operações'!$D$11:$D$1001,'Weekly Analysis'!G1) -> 0.0046994536 | H5: =SUMIFS('Registo de operações'!$AJ$11:$AJ$1001,'Registo de operações'!$D$11:$D$1001,'Weekly Analysis'!H1) -> 0.14317308 | I5: =SUMIFS('Registo de operações'!$AJ$11:$AJ$1001,'Registo de operações'!$D$11:$D$1001,'Weekly Analysis'!I1) -> 0 | ... BA5: =SUMIFS('Registo de operações'!$AJ$11:$AJ$1001,'Registo de operações'!$D$11:$D$1001,'Weekly Analysis'!BA1) -> 0
A6: Capital Realizado: | B6: =SUMIFS('Registo de operações'!$AG$11:$AG$1001,'Registo de operações'!$D$11:$D$1001,'Weekly Analysis'!B1) -> 0 | C6: =SUMIFS('Registo de operações'!$AG$11:$AG$1001,'Registo de operações'!$D$11:$D$1001,'Weekly Analysis'!C1) -> 0 | D6: =SUMIFS('Registo de operações'!$AG$11:$AG$1001,'Registo de operações'!$D$11:$D$1001,'Weekly Analysis'!D1) -> 0 | E6: =SUMIFS('Registo de operações'!$AG$11:$AG$1001,'Registo de operações'!$D$11:$D$1001,'Weekly Analysis'!E1) -> 0 | F6: =SUMIFS('Registo de operações'!$AG$11:$AG$1001,'Registo de operações'!$D$11:$D$1001,'Weekly Analysis'!F1) -> 574.06519 | G6: =SUMIFS('Registo de operações'!$AG$11:$AG$1001,'Registo de operações'!$D$11:$D$1001,'Weekly Analysis'!G1) -> 24.012707 | H6: =SUMIFS('Registo de operações'!$AG$11:$AG$1001,'Registo de operações'!$D$11:$D$1001,'Weekly Analysis'!H1) -> 842.70885 | I6: =SUMIFS('Registo de operações'!$AG$11:$AG$1001,'Registo de operações'!$D$11:$D$1001,'Weekly Analysis'!I1) -> 0 | ... BA6: =SUMIFS('Registo de operações'!$AG$11:$AG$1001,'Registo de operações'!$D$11:$D$1001,'Weekly Analysis'!BA1) -> 0
A7: Objectivo Semanal | B7: 0.04 | C7: 0.04 | D7: 0.04 | E7: 0.04 | F7: 0.04 | G7: 0.04 | H7: 0.04 | I7: 0.04 | J7: 0.04 | K7: 0.04 | L7: 0.04 | M7: 0.04 | N7: 0.04 | O7: 0.06 | P7: 0.06 | Q7: 0.06 | R7: 0.06 | S7: 0.06 | T7: 0.06 | U7: 0.06 | V7: 0.06 | W7: 0.06 | X7: 0.06 | Y7: 0.06 | Z7: 0.06 | AA7: 0.06 | AB7: 0.06 | AC7: 0.06 | AD7: 0.06 | AE7: 0.06 | AF7: 0.06 | AG7: 0.06 | AH7: 0.06 | AI7: 0.06 | AJ7: 0.06 | AK7: 0.06 | AL7: 0.06 | AM7: 0.06 | AN7: 0.06 | AO7: 0.06 | AP7: 0.06 | AQ7: 0.06 | AR7: 0.06 | AS7: 0.06 | AT7: 0.06 | AU7: 0.06 | AV7: 0.06 | AW7: 0.06 | AX7: 0.06 | AY7: 0.06 | AZ7: 0.06 | BA7: 0.06
A9: Nº Total de operações negativas | B9: =COUNTIFS('Registo de operações'!$D$11:$D$1001,B1,'Registo de operações'!$M$11:$M$1001,'Registo de operações'!$AW$11) -> 0 | C9: =COUNTIFS('Registo de operações'!$D$11:$D$1001,C1,'Registo de operações'!$M$11:$M$1001,'Registo de operações'!$AW$11) -> 0 | D9: =COUNTIFS('Registo de operações'!$D$11:$D$1001,D1,'Registo de operações'!$M$11:$M$1001,'Registo de operações'!$AW$11) -> 0 | E9: =COUNTIFS('Registo de operações'!$D$11:$D$1001,E1,'Registo de operações'!$M$11:$M$1001,'Registo de operações'!$AW$11) -> 0 | F9: =COUNTIFS('Registo de operações'!$D$11:$D$1001,F1,'Registo de operações'!$M$11:$M$1001,'Registo de operações'!$AW$11) -> 4 | G9: =COUNTIFS('Registo de operações'!$D$11:$D$1001,G1,'Registo de operações'!$M$11:$M$1001,'Registo de operações'!$AW$11) -> 2 | H9: =COUNTIFS('Registo de operações'!$D$11:$D$1001,H1,'Registo de operações'!$M$11:$M$1001,'Registo de operações'!$AW$11) -> 4 | I9: =COUNTIFS('Registo de operações'!$D$11:$D$1001,I1,'Registo de operações'!$M$11:$M$1001,'Registo de operações'!$AW$11) -> 0 | ... BA9: =COUNTIFS('Registo de operações'!$D$11:$D$1001,BA1,'Registo de operações'!$M$11:$M$1001,'Registo de operações'!$AW$11) -> 0
A10: Volume de drawdown semanal | B10: =SUMIFS('Registo de operações'!$AJ$11:$AJ$1001,'Registo de operações'!$D$11:$D$1001,'Weekly Analysis'!B1,'Registo de operações'!$AJ$11:$AJ$1001,"<0") -> 0 | C10: =SUMIFS('Registo de operações'!$AJ$11:$AJ$1001,'Registo de operações'!$D$11:$D$1001,'Weekly Analysis'!C1,'Registo de operações'!$AJ$11:$AJ$1001,"<0") -> 0 | D10: =SUMIFS('Registo de operações'!$AJ$11:$AJ$1001,'Registo de operações'!$D$11:$D$1001,'Weekly Analysis'!D1,'Registo de operações'!$AJ$11:$AJ$1001,"<0") -> 0 | E10: =SUMIFS('Registo de operações'!$AJ$11:$AJ$1001,'Registo de operações'!$D$11:$D$1001,'Weekly Analysis'!E1,'Registo de operações'!$AJ$11:$AJ$1001,"<0") -> 0 | F10: =SUMIFS('Registo de operações'!$AJ$11:$AJ$1001,'Registo de operações'!$D$11:$D$1001,'Weekly Analysis'!F1,'Registo de operações'!$AJ$11:$AJ$1001,"<0") -> -0.04 | G10: =SUMIFS('Registo de operações'!$AJ$11:$AJ$1001,'Registo de operações'!$D$11:$D$1001,'Weekly Analysis'!G1,'Registo de operações'!$AJ$11:$AJ$1001,"<0") -> -0.02 | H10: =SUMIFS('Registo de operações'!$AJ$11:$AJ$1001,'Registo de operações'!$D$11:$D$1001,'Weekly Analysis'!H1,'Registo de operações'!$AJ$11:$AJ$1001,"<0") -> -0.04 | I10: =SUMIFS('Registo de operações'!$AJ$11:$AJ$1001,'Registo de operações'!$D$11:$D$1001,'Weekly Analysis'!I1,'Registo de operações'!$AJ$11:$AJ$1001,"<0") -> 0 | ... BA10: =SUMIFS('Registo de operações'!$AJ$11:$AJ$1001,'Registo de operações'!$D$11:$D$1001,'Weekly Analysis'!BA1,'Registo de operações'!$AJ$11:$AJ$1001,"<0") -> 0
A11: Média de perda por operação | B11: =AVERAGEIFS('Registo de operações'!$AJ$11:$AJ$1001,'Registo de operações'!$D$11:$D$1001,'Weekly Analysis'!B1,'Registo de operações'!$AJ$11:$AJ$1001,"<0") -> #DIV/0! | C11: =AVERAGEIFS('Registo de operações'!$AJ$11:$AJ$1001,'Registo de operações'!$D$11:$D$1001,'Weekly Analysis'!C1,'Registo de operações'!$AJ$11:$AJ$1001,"<0") -> #DIV/0! | D11: =AVERAGEIFS('Registo de operações'!$AJ$11:$AJ$1001,'Registo de operações'!$D$11:$D$1001,'Weekly Analysis'!D1,'Registo de operações'!$AJ$11:$AJ$1001,"<0") -> #DIV/0! | E11: =AVERAGEIFS('Registo de operações'!$AJ$11:$AJ$1001,'Registo de operações'!$D$11:$D$1001,'Weekly Analysis'!E1,'Registo de operações'!$AJ$11:$AJ$1001,"<0") -> #DIV/0! | F11: =AVERAGEIFS('Registo de operações'!$AJ$11:$AJ$1001,'Registo de operações'!$D$11:$D$1001,'Weekly Analysis'!F1,'Registo de operações'!$AJ$11:$AJ$1001,"<0") -> -0.01 | G11: =AVERAGEIFS('Registo de operações'!$AJ$11:$AJ$1001,'Registo de operações'!$D$11:$D$1001,'Weekly Analysis'!G1,'Registo de operações'!$AJ$11:$AJ$1001,"<0") -> -0.01 | H11: =AVERAGEIFS('Registo de operações'!$AJ$11:$AJ$1001,'Registo de operações'!$D$11:$D$1001,'Weekly Analysis'!H1,'Registo de operações'!$AJ$11:$AJ$1001,"<0") -> -0.01 | I11: =AVERAGEIFS('Registo de operações'!$AJ$11:$AJ$1001,'Registo de operações'!$D$11:$D$1001,'Weekly Analysis'!I1,'Registo de operações'!$AJ$11:$AJ$1001,"<0") -> #DIV/0! | ... BA11: =AVERAGEIFS('Registo de operações'!$AJ$11:$AJ$1001,'Registo de operações'!$D$11:$D$1001,'Weekly Analysis'!BA1,'Registo de operações'!$AJ$11:$AJ$1001,"<0") -> #DIV/0!
A12: Limite de drawdown semanal
A13: Limite de drawdown diário
A14: Média Limite de perda P/ Operação | B14: -0.005 | C14: -0.005 | D14: -0.005 | E14: -0.005 | F14: -0.005 | G14: -0.005 | H14: -0.005 | I14: -0.005 | J14: -0.005 | K14: -0.005 | L14: -0.005 | M14: -0.005 | N14: -0.005 | O14: -0.005 | P14: -0.005 | Q14: -0.005 | R14: -0.005 | S14: -0.005 | T14: -0.005 | U14: -0.005 | V14: -0.005 | W14: -0.005 | X14: -0.005 | Y14: -0.005 | Z14: -0.005 | AA14: -0.005 | AB14: -0.005 | AC14: -0.005 | AD14: -0.005 | AE14: -0.005 | AF14: -0.005 | AG14: -0.005 | AH14: -0.005 | AI14: -0.005 | AJ14: -0.005 | AK14: -0.005 | AL14: -0.005 | AM14: -0.005 | AN14: -0.005 | AO14: -0.005 | AP14: -0.005 | AQ14: -0.005 | AR14: -0.005 | AS14: -0.005 | AT14: -0.005 | AU14: -0.005 | AV14: -0.005 | AW14: -0.005 | AX14: -0.005 | AY14: -0.005 | AZ14: -0.005 | BA14: -0.005
A17: Análise da qualidade de trading
A18: Overtrading
A19: Análise das posições Positivas
A20: Análise das posições Negativas
A22: Avaliação semanal

Sheet Trading Plan
C1: Are you able to sustain 12 losses in a row?
B2: TRADING IS A SURVIVAL GAME. THOSE WHO PROTECT THEIR CAPITAL STAY IN THE GAME TO PLAY ANOTHER DAY.
B4: Todos o dias voam milhoes de euros sem dono - só precisamos de o saber agarra.
B5: O DINHEIRO ESTÁ ATRÁS DO MEDO
A8: Regras dos dias: | B8: Não operar a minutos ou segundos á segunda-feira
B9: Domingo é dia de organizar as operações a horas e dias
A10: Máximo de lucro: | B10: 5% \ semana
A11: Máximo de perdas: | B11: 3% \ semana
A12: Máximo de operações \ dia: | B12: 2 | C12: Na primeira com lucro, não opero para o dia \ Se me sentir confortável máx. 2 operações
C13: Na primeira em perda, dou uma segunda hipotse para o dia
A15: Nº Máximo de operações a Dia/Semana em Simultâneo: | B15: 2
A16: Nº Máximo de operações de 1H-12H em simulâneo: | B16: 2
A17: Nº Máximo de operações a Minutos em Simultâneo: | B17: 2
A18: Nº Máximo de operações Semanais: | B18: 5
A19: Exposição máxima de Conta em simultâneo | B19: =(B14+B15+B16)*B22 -> 0.02
A20: % de Risco Máximo por Operação | B20: 0.01 | C20: Objetivo no FTMO = 0,5% - Neste sentido conseguir agunetar com 20 trades negativos de seguida
A21: Nº Máximo de STOP-LOSS Diários | B21: 2
A22: Objectivo de % média de perda por operação negativa: | B22: 0.005
A24: % Máxima de Drawdown Mensal: | B24: 0.5 | C24: Depende de quanto eu fizer, quero conseguir tirar 1.500 para mim
A26: % Máxima de Drawdown Semanal:
A27: Nº Máximo de dias consecutivos só com Perdas: | B27: 2 \ 3 | C27: ex: 1 operação negativa por dia = 3% máximo da semana
C28: ex: 2 operações negativos num dia, e outra negativa noutro dia = 3% máximo da semana
A30: Valor que tiro como ordenado mensal: | B30: 1.500€
A31: Fundo de energência CGD: | B31: 5.000€
A32: Extra na conta FTMO para buffer: | B32: 0.1
A33: Minimo na conta pessoal IC market real: | B33: 10.000€
J34: Viver uma vida simples, livre do que a sociedade espera de nós. Quero estar rodeada de pessoas que transmitem boa energia, quero ser eu a tranmitir a boa energia. Viver livre de preconceitos, sentir-me amada por mim mesma sem a necessidade de aprovação do meio externo. Quero liberdade financeira, viajar muito por este mundo, ser capaz de me auto-sustentar, ter mais tempo para a minha familia, ter mais tempo para mim, aproveitar a vida rir sentir-me concretizada e fazer o que amo todos os dias - Animais, plantas, comida, natureza, paz | L34: WHAT | M34: GOAL | N34: PLAN
L35: Ordenado (A) + mochila ás costas (B) | M35: Trader profissional. Liberdade de trabalhar todos os dias para mim mesma. Com o meu exforço obtenho os meus resultados. Poder trabalhar de qualquer parte do mundo, viajar de mochila ás costas | N35: 0.6
L36: Fundo (s) | M36: Fundo de emergência; Sobrinhos; Animais; fundo c / Carlos; fundo para viajar de mochila ás costas e se precisar de algo! | N36: 0.2
J37: MY STRONG SIDE | K37: MY LESS STRONG SIDE | L37: Auto-caravana (C) | M37: Ter a minha casa e o meu conforto sobre rodas, sem pressas, Slow life, conhecer novas pessoas, novas habilidades pessoais.
J38: A minha intuição Jeito para pesquisar e me informar nos melhores sitios | K38: A indecisão sem dúvida, e o "medo" de perder o que já criei até este ponto. | L38: Terrano (D) | M38: Desejo um lugar tranquilo e silêncioso com espaço suficiente para ser auto sustêntável, com a praia relativamente perto. Consiga viver com paz e tranquila, na minha liberdade e forma de ser.
J39: VALORES PESSOAIS | K39: TIME | L39: Reforma (E) | N39: Compound 20%
J40: Respeito proprio Paz, calma Clareza Independência Sucesso | K40: 4 \ 5 H por dia Das 9h até as 13h da manhã | L40: Passive Income | M40: Outros planos, outros investimentos e projectos de coisas que me apaixonam.

Sheet Statistics
A3: Nº Entradas/Dia semana | B3: 2ª Feira | C3: 3ª Feira | D3: 4ª Feira | E3: 5ª Feira | F3: 6ª Feira | G3: TOTAL
B4: =COUNTIF('Registo de operações'!$E$11:$E$1001,'Registo de operações'!AS10) -> 10 | C4: =COUNTIF('Registo de operações'!$E$11:$E$211,'Registo de operações'!AS11) -> 11 | D4: =COUNTIF('Registo de operações'!$E$11:$E$211,'Registo de operações'!AS12) -> 16 | E4: =COUNTIF('Registo de operações'!$E$11:$E$211,'Registo de operações'!AS13) -> 24 | F4: =COUNTIF('Registo de operações'!$E$11:$E$211,'Registo de operações'!AS14) -> 16 | G4: =SUM(B4:F4) -> 77
A5: Acerto: | B5: =COUNTIFS('Registo de operações'!$E$11:$E$1001,'Registo de operações'!$AS$10,'Registo de operações'!$M$11:$M$1001,'Registo de operações'!$AW$10) -> 2 | C5: =COUNTIFS('Registo de operações'!$E$11:$E$1001,'Registo de operações'!$AS$11,'Registo de operações'!$M$11:$M$1001,'Registo de operações'!$AW$10) -> 5 | D5: =COUNTIFS('Registo de operações'!$E$11:$E$1001,'Registo de operações'!$AS$12,'Registo de operações'!$M$11:$M$1001,'Registo de operações'!$AW$10) -> 5 | E5: =COUNTIFS('Registo de operações'!$E$11:$E$1001,'Registo de operações'!$AS$13,'Registo de operações'!$M$11:$M$1001,'Registo de operações'!$AW$10) -> 11 | F5: =COUNTIFS('Registo de operações'!$E$11:$E$1001,'Registo de operações'!$AS$14,'Registo de operações'!$M$11:$M$1001,'Registo de operações'!$AW$10) -> 7
A6: Perda: | B6: =COUNTIFS('Registo de operações'!$E$11:$E$1001,'Registo de operações'!$AS$10,'Registo de operações'!$M$11:$M$1001,'Registo de operações'!$AW$11) -> 8 | C6: =COUNTIFS('Registo de operações'!$E$11:$E$1001,'Registo de operações'!$AS$11,'Registo de operações'!$M$11:$M$1001,'Registo de operações'!$AW$11) -> 6 | D6: =COUNTIFS('Registo de operações'!$E$11:$E$1001,'Registo de operações'!$AS$12,'Registo de operações'!$M$11:$M$1001,'Registo de operações'!$AW$11) -> 11 | E6: =COUNTIFS('Registo de operações'!$E$11:$E$1001,'Registo de operações'!$AS$13,'Registo de operações'!$M$11:$M$1001,'Registo de operações'!$AW$11) -> 13 | F6: =COUNTIFS('Registo de operações'!$E$11:$E$1001,'Registo de operações'!$AS$14,'Registo de operações'!$M$11:$M$1001,'Registo de operações'!$AW$11) -> 9
A7: Taxa de Acerto: | B7: =B5/B4 -> 0.2 | C7: =C5/C4 -> 0.45454545 | D7: =D5/D4 -> 0.3125 | E7: =E5/E4 -> 0.45833333 | F7: =F5/F4 -> 0.4375
A9: Marcos Temporais | B9: 3 Minutos | C9: 5 Minutos | D9: 15 Minutos | E9: 30 Minutos | F9: 1 Hora | G9: 2 Horas | H9: 4 Horas | I9: 8 Horas | J9: 1 Dia | K9: 1 Semana | L9: 15S | M9: 1m | N9: TOTAL
B10: =COUNTIF('Registo de operações'!$K$11:$K$211,'Registo de operações'!AV19) -> 12 | C10: =COUNTIF('Registo de operações'!$K$11:$K$211,'Registo de operações'!$AV$18) -> 8 | D10: =COUNTIF('Registo de operações'!$K$11:$K$211,'Registo de operações'!$AV$17) -> 1 | E10: =COUNTIF('Registo de operações'!$K$11:$K$211,'Registo de operações'!$AV$16) -> 1 | F10: =COUNTIF('Registo de operações'!$K$11:$K$211,'Registo de operações'!$AV$15) -> 4 | G10: =COUNTIF('Registo de operações'!$K$11:$K$211,'Registo de operações'!$AV$14) -> 3 | H10: =COUNTIF('Registo de operações'!$K$11:$K$211,'Registo de operações'!$AV$13) -> 3 | I10: =COUNTIF('Registo de operações'!$K$11:$K$211,'Registo de operações'!$AV$12) -> 2 | J10: =COUNTIF('Registo de operações'!$K$11:$K$211,'Registo de operações'!$AV$10) -> 2 | K10: =COUNTIF('Registo de operações'!$K$11:$K$211,'Registo de operações'!$AV$20) -> 0 | L10: =COUNTIF('Registo de operações'!$K$11:$K$211,'Registo de operações'!$AV$22) -> 16 | M10: =COUNTIF('Registo de operações'!$K$11:$K$211,'Registo de operações'!$AV$23) -> 25 | N10: =SUM(B10:M10) -> 77
A11: Acerto: | B11: =COUNTIFS('Registo de operações'!$K$11:$K$1001,'Registo de operações'!$AV$19,'Registo de operações'!$M$11:$M$1001,'Registo de operações'!$AW$10) -> 4 | C11: =COUNTIFS('Registo de operações'!$K$11:$K$1001,'Registo de operações'!$AV$18,'Registo de operações'!$M$11:$M$1001,'Registo de operações'!$AW$10) -> 6 | D11: =COUNTIFS('Registo de operações'!$K$11:$K$1001,'Registo de operações'!$AV$17,'Registo de operações'!$M$11:$M$1001,'Registo de operações'!$AW$10) -> 1 | E11: =COUNTIFS('Registo de operações'!$K$11:$K$1001,'Registo de operações'!$AV$16,'Registo de operações'!$M$11:$M$1001,'Registo de operações'!$AW$10) -> 0 | F11: =COUNTIFS('Registo de operações'!$K$11:$K$1001,'Registo de operações'!$AV$15,'Registo de operações'!$M$11:$M$1001,'Registo de operações'!$AW$10) -> 0 | G11: =COUNTIFS('Registo de operações'!$K$11:$K$1001,'Registo de operações'!$AV$14,'Registo de operações'!$M$11:$M$1001,'Registo de operações'!$AW$10) -> 1 | H11: =COUNTIFS('Registo de operações'!$K$11:$K$1001,'Registo de operações'!$AV$13,'Registo de operações'!$M$11:$M$1001,'Registo de operações'!$AW$10) -> 1 | I11: =COUNTIFS('Registo de operações'!$K$11:$K$1001,'Registo de operações'!$AV$12,'Registo de operações'!$M$11:$M$1001,'Registo de operações'!$AW$10) -> 0 | J11: =COUNTIFS('Registo de operações'!$K$11:$K$1001,'Registo de operações'!$AV$10,'Registo de operações'!$M$11:$M$1001,'Registo de operações'!$AW$10) -> 2 | K11: =COUNTIFS('Registo de operações'!$K$11:$K$1001,'Registo de operações'!$AV$20,'Registo de operações'!$M$11:$M$1001,'Registo de operações'!$AW$10) -> 0 | L11: =COUNTIFS('Registo de operações'!$K$11:$K$1001,'Registo de operações'!$AV$22,'Registo de operações'!$M$11:$M$1001,'Registo de operações'!$AW$10) -> 4 | M11: =COUNTIFS('Registo de operações'!$K$11:$K$1001,'Registo de operações'!$AV$23,'Registo de operações'!$M$11:$M$1001,'Registo de operações'!$AW$10) -> 11
A12: Perda: | B12: =COUNTIFS('Registo de operações'!$K$11:$K$1001,'Registo de operações'!$AV$19,'Registo de operações'!$M$11:$M$1001,'Registo de operações'!$AW$11) -> 8 | C12: =COUNTIFS('Registo de operações'!$K$11:$K$1001,'Registo de operações'!$AV$18,'Registo de operações'!$M$11:$M$1001,'Registo de operações'!$AW$11) -> 2 | D12: =COUNTIFS('Registo de operações'!$K$11:$K$1001,'Registo de operações'!$AV$17,'Registo de operações'!$M$11:$M$1001,'Registo de operações'!$AW$11) -> 0 | E12: =COUNTIFS('Registo de operações'!$K$11:$K$1001,'Registo de operações'!$AV$16,'Registo de operações'!$M$11:$M$1001,'Registo de operações'!$AW$11) -> 1 | F12: =COUNTIFS('Registo de operações'!$K$11:$K$1001,'Registo de operações'!$AV$15,'Registo de operações'!$M$11:$M$1001,'Registo de operações'!$AW$11) -> 4 | G12: =COUNTIFS('Registo de operações'!$K$11:$K$1001,'Registo de operações'!$AV$14,'Registo de operações'!$M$11:$M$1001,'Registo de operações'!$AW$11) -> 2 | H12: =COUNTIFS('Registo de operações'!$K$11:$K$1001,'Registo de operações'!$AV$13,'Registo de operações'!$M$11:$M$1001,'Registo de operações'!$AW$11) -> 2 | I12: =COUNTIFS('Registo de operações'!$K$11:$K$1001,'Registo de operações'!$AV$12,'Registo de operações'!$M$11:$M$1001,'Registo de operações'!$AW$11) -> 2 | J12: =COUNTIFS('Registo de operações'!$K$11:$K$1001,'Registo de operações'!$AV$10,'Registo de operações'!$M$11:$M$1001,'Registo de operações'!$AW$11) -> 0 | K12: =COUNTIFS('Registo de operações'!$K$11:$K$1001,'Registo de operações'!$AV$20,'Registo de operações'!$M$11:$M$1001,'Registo de operações'!$AW$11) -> 0 | L12: =COUNTIFS('Registo de operações'!$K$11:$K$1001,'Registo de operações'!$AV$22,'Registo de operações'!$M$11:$M$1001,'Registo de operações'!$AW$11) -> 12 | M12: =COUNTIFS('Registo de operações'!$K$11:$K$1001,'Registo de operações'!$AV$23,'Registo de operações'!$M$11:$M$1001,'Registo de operações'!$AW$11) -> 14
A13: Taxa de Acerto: | B13: =B11/B10 -> 0.33333333 | C13: =C11/C10 -> 0.75 | D13: =D11/D10 -> 1 | E13: =E11/E10 -> 0 | F13: =F11/F10 -> 0 | G13: =G11/G10 -> 0.33333333 | H13: =H11/H10 -> 0.33333333 | I13: =I11/I10 -> 0 | ... M13: =M11/M10 -> 0.44
A15: Entradas por estratégia | B15: BreakOut | C15: Bandeira | D15: Retest | E15: Total
B16: =COUNTIF('Registo de operações'!$J$11:$J$1001,'Registo de operações'!AU11) -> 71 | C16: =COUNTIF('Registo de operações'!$J$11:$J$1001,'Registo de operações'!AU12) -> 0 | D16: =COUNTIF('Registo de operações'!$J$11:$J$1001,'Registo de operações'!AU10) -> 6 | E16: =SUM(B16:D16) -> 77
A17: Acerto: | B17: =COUNTIFS('Registo de operações'!$J$11:$J$1001,'Registo de operações'!$AU$11,'Registo de operações'!$M$11:$M$1001,'Registo de operações'!AW10) -> 29 | C17: =COUNTIFS('Registo de operações'!$J$11:$J$1001,'Registo de operações'!$AU$12,'Registo de operações'!$M$11:$M$1001,'Registo de operações'!AW10) -> 0 | D17: =COUNTIFS('Registo de operações'!$J$11:$J$1001,'Registo de operações'!$AU$10,'Registo de operações'!$M$11:$M$1001,'Registo de operações'!AW10) -> 1
A18: Perda: | B18: =COUNTIFS('Registo de operações'!$J$11:$J$1001,'Registo de operações'!$AU$11,'Registo de operações'!$M$11:$M$1001,'Registo de operações'!AW11) -> 42 | C18: =COUNTIFS('Registo de operações'!$J$11:$J$1001,'Registo de operações'!$AU$12,'Registo de operações'!$M$11:$M$1001,'Registo de operações'!AW11) -> 0 | D18: =COUNTIFS('Registo de operações'!$J$11:$J$1001,'Registo de operações'!$AU$10,'Registo de operações'!$M$11:$M$1001,'Registo de operações'!AW11) -> 5
A19: Taxa de Acerto estratégia: | B19: =B17/B16 -> 0.4084507 | C19: =C17/C16 -> #DIV/0! | D19: =D17/D16 -> 0.16666667
A21: Pares | B21: AUDCAD | C21: AUDCHF | D21: AUDJPY | E21: AUDNZD | F21: AUDUSD | G21: CADJPY | H21: EURAUD | I21: EURJPY | J21: EURUSD | K21: GBPCAD | L21: GBPJPY | M21: GBPUSD | N21: NZDUSD | O21: USDCAD | P21: USDJPY | Q21: USDSGD | R21: EURGBP
B22: =COUNTIF('Registo de operações'!$I$11:$I$211,'Registo de operações'!$BH$17) -> 3 | C22: =COUNTIF('Registo de operações'!$I$11:$I$211,'Registo de operações'!$BH$18) -> 3 | D22: =COUNTIF('Registo de operações'!$I$11:$I$211,'Registo de operações'!$BH$19) -> 3 | E22: =COUNTIF('Registo de operações'!$I$11:$I$211,'Registo de operações'!$BH$20) -> 2 | F22: =COUNTIF('Registo de operações'!$I$11:$I$211,'Registo de operações'!$BH$11) -> 2 | G22: =COUNTIF('Registo de operações'!$I$11:$I$211,'Registo de operações'!$BH$22) -> 7 | H22: =COUNTIF('Registo de operações'!$I$11:$I$211,'Registo de operações'!$BH$24) -> 1 | I22: =COUNTIF('Registo de operações'!$I$11:$I$211,'Registo de operações'!$BH$28) -> 2 | J22: =COUNTIF('Registo de operações'!$I$11:$I$211,'Registo de operações'!$BH$10) -> 6 | K22: =COUNTIF('Registo de operações'!$I$11:$I$211,'Registo de operações'!$BH$31) -> 5 | L22: =COUNTIF('Registo de operações'!$I$11:$I$211,'Registo de operações'!$BH$33) -> 2 | M22: =COUNTIF('Registo de operações'!$I$11:$I$211,'Registo de operações'!$BH$13) -> 10 | N22: =COUNTIF('Registo de operações'!$I$11:$I$211,'Registo de operações'!$BH$38) -> 3 | O22: =COUNTIF('Registo de operações'!$I$11:$I$211,'Registo de operações'!$BH$14) -> 4 | P22: =COUNTIF('Registo de operações'!$I$11:$I$211,'Registo de operações'!$BH$16) -> 3 | Q22: =COUNTIF('Registo de operações'!$I$11:$I$211,'Registo de operações'!$BH$39) -> 1 | R22: =COUNTIF('Registo de operações'!$I$11:$I$211,'Registo de operações'!$BH$27) -> 3
A23: Acerto: | B23: =COUNTIFS('Registo de operações'!$I$11:$I$1001,'Registo de operações'!$BH$17,'Registo de operações'!$M$11:$M$1001,'Registo de operações'!$AW$10) -> 2 | C23: =COUNTIFS('Registo de operações'!$I$11:$I$1001,'Registo de operações'!$BH$18,'Registo de operações'!$M$11:$M$1001,'Registo de operações'!$AW$10) -> 2 | D23: =COUNTIFS('Registo de operações'!$I$11:$I$1001,'Registo de operações'!$BH$19,'Registo de operações'!$M$11:$M$1001,'Registo de operações'!$AW$10) -> 1 | E23: =COUNTIFS('Registo de operações'!$I$11:$I$1001,'Registo de operações'!$BH$20,'Registo de operações'!$M$11:$M$1001,'Registo de operações'!$AW$10) -> 0 | F23: =COUNTIFS('Registo de operações'!$I$11:$I$1001,'Registo de operações'!$BH$11,'Registo de operações'!$M$11:$M$1001,'Registo de operações'!$AW$10) -> 2 | G23: =COUNTIFS('Registo de operações'!$I$11:$I$1001,'Registo de operações'!$BH$22,'Registo de operações'!$M$11:$M$1001,'Registo de operações'!$AW$10) -> 3 | H23: =COUNTIFS('Registo de operações'!$I$11:$I$1001,'Registo de operações'!$BH$24,'Registo de operações'!$M$11:$M$1001,'Registo de operações'!$AW$10) -> 1 | I23: =COUNTIFS('Registo de operações'!$I$11:$I$1001,'Registo de operações'!$BH$28,'Registo de operações'!$M$11:$M$1001,'Registo de operações'!$AW$10) -> 1 | J23: =COUNTIFS('Registo de operações'!$I$11:$I$1001,'Registo de operações'!$BH$10,'Registo de operações'!$M$11:$M$1001,'Registo de operações'!$AW$10) -> 1 | K23: =COUNTIFS('Registo de operações'!$I$11:$I$1001,'Registo de operações'!$BH$31,'Registo de operações'!$M$11:$M$1001,'Registo de operações'!$AW$10) -> 2 | L23: =COUNTIFS('Registo de operações'!$I$11:$I$1001,'Registo de operações'!$BH$33,'Registo de operações'!$M$11:$M$1001,'Registo de operações'!$AW$10) -> 0 | M23: =COUNTIFS('Registo de operações'!$I$11:$I$1001,'Registo de operações'!$BH$13,'Registo de operações'!$M$11:$M$1001,'Registo de operações'!$AW$10) -> 4 | N23: =COUNTIFS('Registo de operações'!$I$11:$I$1001,'Registo de operações'!$BH$38,'Registo de operações'!$M$11:$M$1001,'Registo de operações'!$AW$10) -> 1 | O23: =COUNTIFS('Registo de operações'!$I$11:$I$1001,'Registo de operações'!$BH$14,'Registo de operações'!$M$11:$M$1001,'Registo de operações'!$AW$10) -> 2 | P23: =COUNTIFS('Registo de operações'!$I$11:$I$1001,'Registo de operações'!$BH$16,'Registo de operações'!$M$11:$M$1001,'Registo de operações'!$AW$10) -> 1 | Q23: =COUNTIFS('Registo de operações'!$I$11:$I$1001,'Registo de operações'!$BH$39,'Registo de operações'!$M$11:$M$1001,'Registo de operações'!$AW$10) -> 0 | R23: =COUNTIFS('Registo de operações'!$I$11:$I$1001,'Registo de operações'!$BH$27,'Registo de operações'!$M$11:$M$1001,'Registo de operações'!$AW$10) -> 2
A24: Perda: | B24: =COUNTIFS('Registo de operações'!$I$11:$I$1001,'Registo de operações'!$BH$17,'Registo de operações'!$M$11:$M$1001,'Registo de operações'!$AW$11) -> 1 | C24: =COUNTIFS('Registo de operações'!$I$11:$I$1001,'Registo de operações'!$BH$18,'Registo de operações'!$M$11:$M$1001,'Registo de operações'!$AW$11) -> 1 | D24: =COUNTIFS('Registo de operações'!$I$11:$I$1001,'Registo de operações'!$BH$19,'Registo de operações'!$M$11:$M$1001,'Registo de operações'!$AW$11) -> 2 | E24: =COUNTIFS('Registo de operações'!$I$11:$I$1001,'Registo de operações'!$BH$20,'Registo de operações'!$M$11:$M$1001,'Registo de operações'!$AW$11) -> 2 | F24: =COUNTIFS('Registo de operações'!$I$11:$I$1001,'Registo de operações'!$BH$11,'Registo de operações'!$M$11:$M$1001,'Registo de operações'!$AW$11) -> 0 | G24: =COUNTIFS('Registo de operações'!$I$11:$I$1001,'Registo de operações'!$BH$22,'Registo de operações'!$M$11:$M$1001,'Registo de operações'!$AW$11) -> 4 | H24: =COUNTIFS('Registo de operações'!$I$11:$I$1001,'Registo de operações'!$BH$24,'Registo de operações'!$M$11:$M$1001,'Registo de operações'!$AW$11) -> 0 | I24: =COUNTIFS('Registo de operações'!$I$11:$I$1001,'Registo de operações'!$BH$28,'Registo de operações'!$M$11:$M$1001,'Registo de operações'!$AW$11) -> 1 | J24: =COUNTIFS('Registo de operações'!$I$11:$I$1001,'Registo de operações'!$BH$10,'Registo de operações'!$M$11:$M$1001,'Registo de operações'!$AW$11) -> 5 | K24: =COUNTIFS('Registo de operações'!$I$11:$I$1001,'Registo de operações'!$BH$31,'Registo de operações'!$M$11:$M$1001,'Registo de operações'!$AW$11) -> 3 | L24: =COUNTIFS('Registo de operações'!$I$11:$I$1001,'Registo de operações'!$BH$33,'Registo de operações'!$M$11:$M$1001,'Registo de operações'!$AW$11) -> 2 | M24: =COUNTIFS('Registo de operações'!$I$11:$I$1001,'Registo de operações'!$BH$13,'Registo de operações'!$M$11:$M$1001,'Registo de operações'!$AW$11) -> 6 | N24: =COUNTIFS('Registo de operações'!$I$11:$I$1001,'Registo de operações'!$BH$38,'Registo de operações'!$M$11:$M$1001,'Registo de operações'!$AW$11) -> 2 | O24: =COUNTIFS('Registo de operações'!$I$11:$I$1001,'Registo de operações'!$BH$14,'Registo de operações'!$M$11:$M$1001,'Registo de operações'!$AW$11) -> 2 | P24: =COUNTIFS('Registo de operações'!$I$11:$I$1001,'Registo de operações'!$BH$16,'Registo de operações'!$M$11:$M$1001,'Registo de operações'!$AW$11) -> 2 | Q24: =COUNTIFS('Registo de operações'!$I$11:$I$1001,'Registo de operações'!$BH$39,'Registo de operações'!$M$11:$M$1001,'Registo de operações'!$AW$11) -> 1 | R24: =COUNTIFS('Registo de operações'!$I$11:$I$1001,'Registo de operações'!$BH$39,'Registo de operações'!$M$11:$M$1001,'Registo de operações'!$AW$11) -> 1
A25: Taxa de Acerto: | B25: =B23/B22 -> 0.66666667 | C25: =C23/C22 -> 0.66666667 | D25: =D23/D22 -> 0.33333333 | E25: =E23/E22 -> 0 | F25: =F23/F22 -> 1 | G25: =G23/G22 -> 0.42857143 | H25: =H23/H22 -> 1 | I25: =I23/I22 -> 0.5 | ... R25: =R23/R22 -> 0.66666667
G27: GBPUSD
G28: CADJPY
G29: AUDCAD
G30: AUDCHF
G31: GBPCAD
G32: EURGBP

Sheet Evolução de Conta

Sheet Pontuação
H1: Majors | I1: Minors | J1: Exotics | K1: Breakout | M1: Retest
B2: =SUM(B5:B204) -> 0.86933381 | C2: =SUM(C5:C204) -> -0.47 | D2: =SUM(D5:D204) -> 5633.3383 | E2: =SUM(E5:E204) -> -3291.3104 | G2: W | H2: =COUNTIFS(#REF!,"Majors",$L$11:$L$210,"W") -> #REF! | I2: =COUNTIFS(#REF!,"Minors",$L$11:$L$210,"W") -> #REF! | J2: =COUNTIFS(#REF!,"Exotics",$L$11:$L$210,"W") -> #REF! | K2: 6 | L2: =K2*100%/#REF! -> #REF! | M2: 11 | N2: =M2*100%/$C$5 -> -1100
B3: =AVERAGE(B5:B204) -> 0.028977794 | C3: =AVERAGE(C5:C204) -> -0.01 | D3: =AVERAGE(D5:D204) -> 187.77794 | E3: =AVERAGE(E5:E204) -> -70.02788 | G3: L | H3: =H4-H2 -> #REF! | I3: =I4-I2 -> #REF! | J3: =J4-J2 -> #REF! | K3: 7 | L3: =K3*100%/#REF! -> #REF! | M3: 14 | N3: =M3*100%/$C$5 -> -1400
A4: Nº T | B4: Ganhos % | C4: Perdas % | D4: Ganhos € | E4: Perdas € | G4: Total | H4: =COUNTIF(#REF!,"MAJORS") -> #REF! | I4: =COUNTIF(#REF!,"minors") -> #REF! | J4: =COUNTIF(#REF!,"Exotics") -> #REF! | K4: =SUM(K2:K3) -> 13 | L4: =SUM(L2:L3) -> #REF! | M4: =SUM(M2:M3) -> 25 | N4: =SUM(N2:N3) -> -2500
A5: ='Registo de operações'!C11 -> 1 | B5: =IF('Registo de operações'!AJ11>0,'Registo de operações'!AJ11,"") | C5: =IF('Registo de operações'!AJ11<0,'Registo de operações'!AJ11,"") -> -0.01 | D5: =IF('Registo de operações'!AG11>0,'Registo de operações'!AG11,"") | E5: =IF('Registo de operações'!AG11<0,'Registo de operações'!AG11,"") -> -50
A6: ='Registo de operações'!C12 -> 2 | B6: =IF('Registo de operações'!AJ12>0,'Registo de operações'!AJ12,"") | C6: =IF('Registo de operações'!AJ12<0,'Registo de operações'!AJ12,"") -> -0.01 | D6: =IF('Registo de operações'!AG12>0,'Registo de operações'!AG12,"") | E6: =IF('Registo de operações'!AG12<0,'Registo de operações'!AG12,"") -> -49.5
A7: ='Registo de operações'!C13 -> 3 | B7: =IF('Registo de operações'!AJ13>0,'Registo de operações'!AJ13,"") -> 0.030350877 | C7: =IF('Registo de operações'!AJ13<0,'Registo de operações'!AJ13,"") | D7: =IF('Registo de operações'!AG13>0,'Registo de operações'!AG13,"") -> 148.73447 | E7: =IF('Registo de operações'!AG13<0,'Registo de operações'!AG13,"")
A8: ='Registo de operações'!C14 -> 4 | B8: =IF('Registo de operações'!AJ14>0,'Registo de operações'!AJ14,"") -> 0.030185185 | C8: =IF('Registo de operações'!AJ14<0,'Registo de operações'!AJ14,"") | D8: =IF('Registo de operações'!AG14>0,'Registo de operações'!AG14,"") -> 152.41208 | E8: =IF('Registo de operações'!AG14<0,'Registo de operações'!AG14,"")
A9: ='Registo de operações'!C15 -> 5 | B9: =IF('Registo de operações'!AJ15>0,'Registo de operações'!AJ15,"") -> 0.029962687 | C9: =IF('Registo de operações'!AJ15<0,'Registo de operações'!AJ15,"") | D9: =IF('Registo de operações'!AG15>0,'Registo de operações'!AG15,"") -> 155.85531 | E9: =IF('Registo de operações'!AG15<0,'Registo de operações'!AG15,"")
A10: ='Registo de operações'!C16 -> 6 | B10: =IF('Registo de operações'!AJ16>0,'Registo de operações'!AJ16,"") | C10: =IF('Registo de operações'!AJ16<0,'Registo de operações'!AJ16,"") -> -0.01 | D10: =IF('Registo de operações'!AG16>0,'Registo de operações'!AG16,"") | E10: =IF('Registo de operações'!AG16<0,'Registo de operações'!AG16,"") -> -53.575019
A11: ='Registo de operações'!C17 -> 7 | B11: =IF('Registo de operações'!AJ17>0,'Registo de operações'!AJ17,"") -> 0.030315789 | C11: =IF('Registo de operações'!AJ17<0,'Registo de operações'!AJ17,"") | D11: =IF('Registo de operações'!AG17>0,'Registo de operações'!AG17,"") -> 160.79273 | E11: =IF('Registo de operações'!AG17<0,'Registo de operações'!AG17,"")
A12: ='Registo de operações'!C18 -> 8 | B12: =IF('Registo de operações'!AJ18>0,'Registo de operações'!AJ18,"") | C12: =IF('Registo de operações'!AJ18<0,'Registo de operações'!AJ18,"") -> -0.01 | D12: =IF('Registo de operações'!AG18>0,'Registo de operações'!AG18,"") | E12: =IF('Registo de operações'!AG18<0,'Registo de operações'!AG18,"") -> -54.647196
A13: ='Registo de operações'!C19 -> 9 | B13: =IF('Registo de operações'!AJ19>0,'Registo de operações'!AJ19,"") -> 0.0303125 | C13: =IF('Registo de operações'!AJ19<0,'Registo de operações'!AJ19,"") | D13: =IF('Registo de operações'!AG19>0,'Registo de operações'!AG19,"") -> 163.99282 | E13: =IF('Registo de operações'!AG19<0,'Registo de operações'!AG19,"")
A14: ='Registo de operações'!C20 -> 10 | B14: =IF('Registo de operações'!AJ20>0,'Registo de operações'!AJ20,"") -> 0.024699454 | C14: =IF('Registo de operações'!AJ20<0,'Registo de operações'!AJ20,"") | D14: =IF('Registo de operações'!AG20>0,'Registo de operações'!AG20,"") -> 137.67636 | E14: =IF('Registo de operações'!AG20<0,'Registo de operações'!AG20,"")
A15: ='Registo de operações'!C21 -> 11 | B15: =IF('Registo de operações'!AJ21>0,'Registo de operações'!AJ21,"") | C15: =IF('Registo de operações'!AJ21<0,'Registo de operações'!AJ21,"") -> -0.01 | D15: =IF('Registo de operações'!AG21>0,'Registo de operações'!AG21,"") | E15: =IF('Registo de operações'!AG21<0,'Registo de operações'!AG21,"") -> -57.117416
A16: ='Registo de operações'!C22 -> 12 | B16: =IF('Registo de operações'!AJ22>0,'Registo de operações'!AJ22,"") | C16: =IF('Registo de operações'!AJ22<0,'Registo de operações'!AJ22,"") -> -0.01 | D16: =IF('Registo de operações'!AG22>0,'Registo de operações'!AG22,"") | E16: =IF('Registo de operações'!AG22<0,'Registo de operações'!AG22,"") -> -56.546241
... A203: ='Registo de operações'!C209 -> 0 | B203: =IF('Registo de operações'!AJ209>0,'Registo de operações'!AJ209,"") | C203: =IF('Registo de operações'!AJ209<0,'Registo de operações'!AJ209,"") | D203: =IF('Registo de operações'!AG209>0,'Registo de operações'!AG209,"") | E203: =IF('Registo de operações'!AG209<0,'Registo de operações'!AG209,"")
A204: ='Registo de operações'!C211 -> 0 | B204: =IF('Registo de operações'!AJ211>0,'Registo de operações'!AJ211,"") | C204: =IF('Registo de operações'!AJ211<0,'Registo de operações'!AJ211,"") | D204: =IF('Registo de operações'!AG211>0,'Registo de operações'!AG211,"") | E204: =IF('Registo de operações'!AG211<0,'Registo de operações'!AG211,"")

Sheet Cálculo stop
C5: Valor Atual de conta | D5: ='Registo de operações'!S4 -> 7430.7179
C6: Gestão de Risco: | D6: 1
C7: Posições em aberto | D7: ='Registo de operações'!I4 -> 0
C8: Valor do Stop: | D8: =(D5*(D6/100)) -> 74.307179
C9: Account equity: | D9: =D5-(D7*D8) -> 7430.7179
C10: Valor do STOP Equity: | D10: =(D9*(D6/100)) -> 74.307179
