Workbook

Sheet Registo de operações
M2: Fundos iniciais | Q2: Mov. Add. Fundos | R2: Profit | S2: Current Funds | U2: Risk | V2: Total | Y2: Average | AC2: Comissões | AD2: Swaps | AE2: Capital liquido Gerado | AF2: Efective % (W. Add. Funds) | AG2: RRR Liquido Realizado
E3: Nº Op | F3: % Win | G3: Win | H3: Lose | I3: NEUTRO | V3: Win | W3: Loss | X3: Total | Y3: Win | Z3: Loss | AA3: Total
E4: =COUNTA(U11:U211) -> 81 | F4: =G4/100%/(E4-I4) -> 0.36486486 | G4: =COUNTIF(M11:M211,"W") -> 27 | H4: =COUNTIF(M11:M211,"L") -> 47 | I4: =E4-G4-H4 -> 7 | M4: 10000 | Q4: 0 | R4: =SUM((X5)+(AD4)+(AC4)) -> -624.36224 | S4: =SUM((M4)+(Q4)+(R4)) -> 9375.6378 | U4: 0.01 | V4: =Pontuação!B2 -> 0.43638742 | W4: =Pontuação!C2 -> -0.43733417 | X4: =SUM(Tabela2[[Ganhos %]:[Perdas %]]) -> -0.00094675072 | Y4: =Pontuação!B3 -> 0.014546247 | Z4: =Pontuação!C3 -> -0.0089251872 | AA4: =AVERAGE(Tabela2[[Ganhos %]:[Perdas %]]) -> -1.1984186e-05 | AC4: =SUM(AE11:AE211) -> -564.39 | AD4: =SUM(AF11:AF211) -> 0.24 | AE4: =SUM((V5)+(W5)+(AC4)+(AD4)) -> -624.36224 | AF4: =SUM((AE4*100)/(M4+Q4))/100 -> -0.062436224 | AG4: =SUM(AK11:AK211) -> -0.058406776
V5: =Pontuação!D2 -> 4242.6641 | W5: =Pontuação!E2 -> -4302.8764 | X5: =SUM(Tabela2[[Ganhos €]:[Perdas €]]) -> -60.212236 | Y5: =Pontuação!D3 -> 141.42214 | Z5: =Pontuação!E3 -> -87.813803 | AA5: =AVERAGE(Tabela2[[Ganhos €]:[Perdas €]]) -> -0.7621802
B7: TIPO | C7: Nº T | D7: Nº S | E7: Dia da semana | F7: DATA | G7: Hora | H7: Grupo | I7: Par/Produto | J7: estratégia | K7: Marco Temporal | L7: Tipo de entrada | M7: W L | N7: E | O7: G | P7: S | Q7: Starting Position | V7: Stop Loss | Y7: Take Profit | AC7: Close Position | AL7: TOTAL depois da operação
Q8: Account Funds | R8: € Risk | S8: % Risk | T8: Lot | U8: Position entry | V8: Max Loss | W8: Pips | X8: € Loss | Y8: Take Profit | Z8: Pips | AA8: € Gain | AB8: RRR | AC8: Day Close | AD8: Closing price | AE8: Comissão | AF8: Swap | AG8: Lucro | AH8: Lucro liquido | AI8: Pips Close | AJ8: RRR Realizado | AK8: RRR Liquido | BH8: Currency | BI8: Grup | BJ8: Avaliação das Entradas:
A9: , | AR9: Sentido | AS9: Day W | AT9: Hora | AU9: Estratégia | AV9: Time Frame | AW9: W L | AX9: O C | AY9: News | AZ9: Candle | BA9: Grup | BB9: Emotional state
AR10: Short | AS10: 2ª F | AT10: Londres | AU10: BSL | AV10: 1D | AW10: W | AX10: O | AY10: Yes | AZ10: Open | BA10: Majors | BB10: Impatience | BC10: x | BD10: 0 | BE10: 0 | BF10: -1 | BG10: x | BH10: EURUSD | BI10: =$BA$10 -> Majors
B11: Fusion demo | C11: 77 | D11: 4 | E11: 2ª F | F11: 22 de Janeiro | G11: Londres | H11: Minors | I11: AUDUSD | J11: ICT | K11: 30m | L11: Short | M11: L | Q11: 10000 | R11: =IF(Q11="","",S11*Q11/100%) -> 100 | S11: 0.01 | U11: 0.65724 | V11: 0.66006 | W11: =IF(V11="","",IF(L11="Long",U11-V11,V11-U11)) -> 0.00282 | X11: =IF(W11="","",R11) -> 100 | Y11: 0.65124 | Z11: =IF(Y11="","",IF(L11="Long",Y11-U11,U11-Y11)) -> 0.006 | AA11: =IF(AB11="","",AB11*X11/1) -> 212.76596 | AB11: =IF(Z11="","",Z11*1/W11) -> 2.1276596 | AC11: 22 de Janeiro | AD11: =V11 -> 0.66006 | AE11: -1.54 | AF11: 0.24 | AG11: =-X11 -> -100 | AH11: =IF(AG11="","",AG11+AF11+AE11) -> -101.3 | AI11: =IF(AD11="","",IF(L11="Long",AD11-U11,U11-AD11)) -> -0.00282 | AJ11: =IF(AI11="","",AG11*S11/X11) -> -0.01 | AK11: =IF(AI11="","",(AG11+AF11+AE11)*S11/X11) -> -0.01013 | AL11: =Q11+AH11 -> 9898.7 | AR11: Long | AS11: 3ª F | AT11: NY | AU11: SSL | AV11: 12h | AW11: L | AX11: C | AY11: No | AZ11: Close | BA11: Minors | BB11: Fear | BD11: 0.1 | BE11: 0.1 | BF11: 0 | BH11: AUDUSD | BI11: =$BA$10 -> Majors | BL11: A | BM11: Boa entrada - Com estratégia - No timming Correto - Boa probabilidade
B12: Fusion demo | C12: 78 | D12: 5 | E12: 5ª F | F12: 1 de Fevereiro | G12: Londres | H12: Majors | I12: EURUSD | J12: ICT | K12: 1m | L12: Short | M12: L | Q12: =AL11 -> 9898.7 | R12: =IF(Q12="","",S12*Q12/100%) -> 98.987 | S12: 0.01 | U12: 1.08129 | V12: 1.0816 | W12: =IF(V12="","",IF(L12="Long",U12-V12,V12-U12)) -> 0.00031 | X12: =IF(W12="","",R12) -> 98.987 | Y12: 1.08033 | Z12: =IF(Y12="","",IF(L12="Long",Y12-U12,U12-Y12)) -> 0.00096 | AA12: =IF(AB12="","",AB12*X12/1) -> 306.54039 | AB12: =IF(Z12="","",Z12*1/W12) -> 3.0967742 | AC12: 2 de Fevereiro | AD12: =V12 -> 1.0816 | AE12: -13.98 | AF12: 0 | AG12: =-X12 -> -98.987 | AH12: =IF(AG12="","",AG12+AF12+AE12) -> -112.967 | AI12: =IF(AD12="","",IF(L12="Long",AD12-U12,U12-AD12)) -> -0.00031 | AJ12: =IF(AI12="","",AG12*S12/X12) -> -0.01 | AK12: =IF(AI12="","",(AG12+AF12+AE12)*S12/X12) -> -0.011412307 | AL12: =Q12+AH12 -> 9785.733 | AS12: 4ª F | AT12: Asia | AU12: FVG | AV12: 8h | AW12: N | AY12: n/a | AZ12: Next | BA12: Exotics | BB12: Greed | BD12: 0.2 | BE12: 0.2 | BF12: 1 | BH12: GBPCHF | BI12: =$BA$10 -> Majors | BL12: B | BM12: Boa entrada - Com alguma estratégia - Alguma Probabilidade
B13: Fusion demo | C13: 79 | D13: 5 | E13: 5ª F | F13: 1 de Fevereiro | G13: Londres | H13: Majors | I13: EURUSD | J13: ICT | K13: 1m | L13: Short | M13: L | Q13: =AL12 -> 9785.733 | R13: =IF(Q13="","",S13*Q13/100%) -> 97.85733 | S13: 0.01 | U13: 1.08154 | V13: 1.08178 | W13: =IF(V13="","",IF(L13="Long",U13-V13,V13-U13)) -> 0.00024 | X13: =IF(W13="","",R13) -> 97.85733 | Y13: 1.08034 | Z13: =IF(Y13="","",IF(L13="Long",Y13-U13,U13-Y13)) -> 0.0012 | AA13: =IF(AB13="","",AB13*X13/1) -> 489.28665 | AB13: =IF(Z13="","",Z13*1/W13) -> 5 | AC13: 2 de Fevereiro | AD13: =V13 -> 1.08178 | AE13: -18.64 | AF13: 0 | AG13: =-X13 -> -97.85733 | AH13: =IF(AG13="","",AG13+AF13+AE13) -> -116.49733 | AI13: =IF(AD13="","",IF(L13="Long",AD13-U13,U13-AD13)) -> -0.00024 | AJ13: =IF(AI13="","",AG13*S13/X13) -> -0.01 | AK13: =IF(AI13="","",(AG13+AF13+AE13)*S13/X13) -> -0.011904814 | AL13: =Q13+AH13 -> 9669.2357 | AS13: 5ª F | AU13: OB | AV13: 4h | AZ13: n/a | BA13: Indices | BB13: Hope | BD13: 0.3 | BE13: 0.3 | BF13: 2 | BH13: GBPUSD | BI13: =$BA$10 -> Majors | BL13: C | BM13: Razoavél - Com alguma estratégia - Mas impulsiva
B14: Fusion demo | C14: 80 | D14: 6 | E14: 4ª F | F14: 7 de Fevereiro | G14: Londres | H14: Majors | I14: EURUSD | J14: ICT | K14: 1m | L14: Short | M14: L | Q14: =AL13 -> 9669.2357 | R14: =IF(Q14="","",S14*Q14/100%) -> 96.692357 | S14: 0.01 | U14: 1.0769 | V14: 1.07709 | W14: =IF(V14="","",IF(L14="Long",U14-V14,V14-U14)) -> 0.00019 | X14: =IF(W14="","",R14) -> 96.692357 | Y14: 1.07633 | Z14: =IF(Y14="","",IF(L14="Long",Y14-U14,U14-Y14)) -> 0.00057 | AA14: =IF(AB14="","",AB14*X14/1) -> 290.07707 | AB14: =IF(Z14="","",Z14*1/W14) -> 3 | AC14: 7 de Janeiro | AD14: =V14 -> 1.07709 | AE14: -22.16 | AF14: 0 | AG14: =-X14 -> -96.692357 | AH14: =IF(AG14="","",AG14+AF14+AE14) -> -118.85236 | AI14: =IF(AD14="","",IF(L14="Long",AD14-U14,U14-AD14)) -> -0.00019 | AJ14: =IF(AI14="","",AG14*S14/X14) -> -0.01 | AK14: =IF(AI14="","",(AG14+AF14+AE14)*S14/X14) -> -0.012291805 | AL14: =Q14+AH14 -> 9550.3833 | AS14: 6ª F | AV14: 2h | BA14: Futures | BB14: Confidence | BD14: 0.4 | BE14: 0.4 | BF14: 3 | BH14: USDCAD | BI14: =$BA$10 -> Majors | BL14: D | BM14: Má entrada - Sem estratégia e impulsiva
B15: FTMO challenge 1 | C15: 81 | D15: 12 | E15: 3ª F | F15: 19 de Março | G15: Londres | H15: Majors | I15: AUDUSD | J15: ICT | K15: 1m | L15: Long | M15: W | Q15: =AL14 -> 9550.3833 | R15: =IF(Q15="","",S15*Q15/100%) -> 95.503833 | S15: 0.01 | U15: 0.65107 | V15: 0.65086 | W15: =IF(V15="","",IF(L15="Long",U15-V15,V15-U15)) -> 0.00021 | X15: =IF(W15="","",R15) -> 95.503833 | Y15: 0.65158 | Z15: =IF(Y15="","",IF(L15="Long",Y15-U15,U15-Y15)) -> 0.00051 | AA15: =IF(AB15="","",AB15*X15/1) -> 231.93788 | AB15: =IF(Z15="","",Z15*1/W15) -> 2.4285714 | AC15: 19 de Março | AD15: =Y15 -> 0.65158 | AE15: -13.61 | AF15: 0 | AG15: =AA15 -> 231.93788 | AH15: =IF(AG15="","",AG15+AF15+AE15) -> 218.32788 | AI15: =IF(AD15="","",IF(L15="Long",AD15-U15,U15-AD15)) -> 0.00051 | AJ15: =IF(AI15="","",AG15*S15/X15) -> 0.024285714 | AK15: =IF(AI15="","",(AG15+AF15+AE15)*S15/X15) -> 0.022860641 | AL15: =Q15+AH15 -> 9768.7112 | AV15: 1h | BB15: Uncertainty | BD15: 0.5 | BE15: 0.5 | BF15: 4 | BH15: USDCHF | BI15: =$BA$10 -> Majors
B16: FTMO challenge 1 | C16: 82 | D16: 12 | E16: 5ª F | F16: 21 de Março | G16: Londres | H16: Majors | I16: EURUSD | J16: ICT | K16: 1m | L16: Short | M16: W | Q16: =AL15 -> 9768.7112 | R16: =IF(Q16="","",S16*Q16/100%) -> 97.687112 | S16: 0.01 | U16: 1.09349 | V16: 1.09389 | W16: =IF(V16="","",IF(L16="Long",U16-V16,V16-U16)) -> 0.0004 | X16: =IF(W16="","",R16) -> 97.687112 | Y16: 1.09233 | Z16: =IF(Y16="","",IF(L16="Long",Y16-U16,U16-Y16)) -> 0.00116 | AA16: =IF(AB16="","",AB16*X16/1) -> 283.29262 | AB16: =IF(Z16="","",Z16*1/W16) -> 2.9 | AC16: 21 de Março | AD16: =Y16 -> 1.09233 | AE16: -7.66 | AF16: 0 | AG16: =AA16 -> 283.29262 | AH16: =IF(AG16="","",AG16+AF16+AE16) -> 275.63262 | AI16: =IF(AD16="","",IF(L16="Long",AD16-U16,U16-AD16)) -> 0.00116 | AJ16: =IF(AI16="","",AG16*S16/X16) -> 0.029 | AK16: =IF(AI16="","",(AG16+AF16+AE16)*S16/X16) -> 0.028215864 | AL16: =Q16+AH16 -> 10044.344 | AV16: 30m | BB16: Serene | BD16: 0.6 | BE16: 0.6 | BF16: 5 | BH16: USDJPY | BI16: =$BA$10 -> Majors | BJ16: Avaliação da Gestão
B17: FTMO challenge 1 | C17: 83 | D17: 13 | E17: 3ª F | F17: 26 de Março | G17: Londres | H17: Majors | I17: EURUSD | J17: ICT | K17: 5m | L17: Short | M17: W | Q17: =AL16 -> 10044.344 | R17: =IF(Q17="","",S17*Q17/100%) -> 100.44344 | S17: 0.01 | U17: 1.08491 | V17: 1.08533 | W17: =IF(V17="","",IF(L17="Long",U17-V17,V17-U17)) -> 0.00042 | X17: =IF(W17="","",R17) -> 100.44344 | Y17: 1.08368 | Z17: =IF(Y17="","",IF(L17="Long",Y17-U17,U17-Y17)) -> 0.00123 | AA17: =IF(AB17="","",AB17*X17/1) -> 294.15578 | AB17: =IF(Z17="","",Z17*1/W17) -> 2.9285714 | AC17: 26 de Março | AD17: 1.08424 | AE17: -7.33 | AF17: 0 | AG17: 163 | AH17: =IF(AG17="","",AG17+AF17+AE17) -> 155.67 | AI17: =IF(AD17="","",IF(L17="Long",AD17-U17,U17-AD17)) -> 0.00067 | AJ17: =IF(AI17="","",AG17*S17/X17) -> 0.016228039 | AK17: =IF(AI17="","",(AG17+AF17+AE17)*S17/X17) -> 0.015498275 | AL17: =Q17+AH17 -> 10200.014 | AV17: 15m | BD17: 0.7 | BE17: 0.7 | BF17: 6 | BH17: AUDCAD | BI17: =$BA$11 -> Minors | BL17: A | BM17: Trailing Stop com a sequência de máximos e minimos - Confortável com a posição - Posição encaminhada
B18: FTMO challenge 1 | C18: 84 | D18: 13 | E18: 5ª F | F18: 28 de Março | G18: Londres | H18: Majors | I18: EURUSD | J18: ICT | K18: 1m | L18: Long | M18: L | Q18: =AL17 -> 10200.014 | R18: =IF(Q18="","",S18*Q18/100%) -> 102.00014 | S18: 0.01 | U18: 1.07935 | V18: 1.07894 | W18: =IF(V18="","",IF(L18="Long",U18-V18,V18-U18)) -> 0.00041 | X18: =IF(W18="","",R18) -> 102.00014 | Y18: 1.08002 | Z18: =IF(Y18="","",IF(L18="Long",Y18-U18,U18-Y18)) -> 0.00067 | AA18: =IF(AB18="","",AB18*X18/1) -> 166.68315 | AB18: =IF(Z18="","",Z18*1/W18) -> 1.6341463 | AC18: 28 de Março | AD18: =V18 -> 1.07894 | AE18: -7.98 | AF18: 0 | AG18: =-X18 -> -102.00014 | AH18: =IF(AG18="","",AG18+AF18+AE18) -> -109.98014 | AI18: =IF(AD18="","",IF(L18="Long",AD18-U18,U18-AD18)) -> -0.00041 | AJ18: =IF(AI18="","",AG18*S18/X18) -> -0.01 | AK18: =IF(AI18="","",(AG18+AF18+AE18)*S18/X18) -> -0.010782352 | AL18: =Q18+AH18 -> 10090.034 | AV18: 5m | BD18: 0.8 | BE18: 0.8 | BF18: 7 | BH18: AUDCHF | BI18: =$BA$11 -> Minors | BL18: B | BM18: Trailing Stop com a sequência de máximos e minimos - Preocupação com a posição - Posição a perder estrutura
B19: FTMO challenge 1 | C19: 85 | D19: 14 | E19: 3ª F | F19: 2 de Arbil | G19: NY | H19: Majors | I19: AUDUSD | J19: ICT | K19: 1m | L19: Short | M19: W | Q19: =AL18 -> 10090.034 | R19: =IF(Q19="","",S19*Q19/100%) -> 100.90034 | S19: 0.01 | U19: 0.65041 | V19: 0.65072 | W19: =IF(V19="","",IF(L19="Long",U19-V19,V19-U19)) -> 0.00031 | X19: =IF(W19="","",R19) -> 100.90034 | Y19: 0.64886 | Z19: =IF(Y19="","",IF(L19="Long",Y19-U19,U19-Y19)) -> 0.00155 | AA19: =IF(AB19="","",AB19*X19/1) -> 504.50168 | AB19: =IF(Z19="","",Z19*1/W19) -> 5 | AC19: 2 de Abril | AD19: 0.65021 | AE19: -10.52 | AF19: 0 | AG19: 70.16 | AH19: =IF(AG19="","",AG19+AF19+AE19) -> 59.64 | AI19: =IF(AD19="","",IF(L19="Long",AD19-U19,U19-AD19)) -> 0.0002 | AJ19: =IF(AI19="","",AG19*S19/X19) -> 0.006953396 | AK19: =IF(AI19="","",(AG19+AF19+AE19)*S19/X19) -> 0.005910783 | AL19: =Q19+AH19 -> 10149.674 | AV19: 3m | BD19: 0.9 | BE19: 0.9 | BF19: 8 | BH19: AUDJPY | BI19: =$BA$11 -> Minors | BL19: C | BM19: Alteração do stop sem estratégia de máximos e minimos - Preocupação com a posição
B20: FTMO challenge 1 | C20: 86 | D20: 14 | E20: 4ª F | F20: 3 de Abril | G20: NY | H20: Majors | I20: EURUSD | J20: ICT | K20: 1m | L20: Short | Q20: =AL19 -> 10149.674 | R20: =IF(Q20="","",S20*Q20/100%) -> 101.49674 | S20: 0.01 | U20: 1.07809 | V20: 1.07851 | W20: =IF(V20="","",IF(L20="Long",U20-V20,V20-U20)) -> 0.00042 | X20: =IF(W20="","",R20) -> 101.49674 | Y20: 1.07706 | Z20: =IF(Y20="","",IF(L20="Long",Y20-U20,U20-Y20)) -> 0.00103 | AA20: =IF(AB20="","",AB20*X20/1) -> 248.90866 | AB20: =IF(Z20="","",Z20*1/W20) -> 2.452381 | AC20: 3 de Abril | AD20: 1.97817 | AE20: -7.56 | AF20: 0 | AG20: -20.18 | AH20: =IF(AG20="","",AG20+AF20+AE20) -> -27.74 | AI20: =IF(AD20="","",IF(L20="Long",AD20-U20,U20-AD20)) -> -0.90008 | AJ20: =IF(AI20="","",AG20*S20/X20) -> -0.0019882413 | AK20: =IF(AI20="","",(AG20+AF20+AE20)*S20/X20) -> -0.0027330928 | AL20: =Q20+AH20 -> 10121.934 | AV20: 1S | BD20: 1 | BE20: 1 | BH20: AUDNZD | BI20: =$BA$11 -> Minors | BL20: D | BM20: Sem Gestão - Não Fechei após a 1ª/2ª vela negativa
B21: FTMO challenge 1 | C21: 87 | D21: 14 | E21: 5ª F | F21: 4 de Abril | G21: NY | H21: Majors | I21: EURUSD | J21: ICT | K21: 1m | L21: Long | Q21: =AL20 -> 10121.934 | R21: =IF(Q21="","",S21*Q21/100%) -> 101.21934 | S21: 0.01 | U21: 1.086689 | V21: 1.08637 | W21: =IF(V21="","",IF(L21="Long",U21-V21,V21-U21)) -> 0.000319 | X21: =IF(W21="","",R21) -> 101.21934 | Y21: 1.08787 | Z21: =IF(Y21="","",IF(L21="Long",Y21-U21,U21-Y21)) -> 0.001181 | AA21: =IF(AB21="","",AB21*X21/1) -> 374.73366 | AB21: =IF(Z21="","",Z21*1/W21) -> 3.7021944 | AC21: 4 de Abril | AD21: =U21 -> 1.086689 | AE21: -6.1 | AF21: 0 | AG21: 0 | AH21: =IF(AG21="","",AG21+AF21+AE21) -> -6.1 | AI21: =IF(AD21="","",IF(L21="Long",AD21-U21,U21-AD21)) -> 0 | AJ21: =IF(AI21="","",AG21*S21/X21) -> 0 | AK21: =IF(AI21="","",(AG21+AF21+AE21)*S21/X21) -> -0.00060265165 | AL21: =Q21+AH21 -> 10115.834 | AV21: 6h | BH21: CADCHF | BI21: =$BA$11 -> Minors
B22: FTMO challenge 1 | C22: 88 | D22: 14 | E22: 6ª F | F22: 5 de Abril | G22: NY | H22: Majors | I22: AUDUSD | J22: ICT | K22: 1m | L22: Long | M22: L | Q22: =AL21 -> 10115.834 | R22: =IF(Q22="","",S22*Q22/100%) -> 101.15834 | S22: 0.01 | U22: 0.65855 | V22: 0.65829 | W22: =IF(V22="","",IF(L22="Long",U22-V22,V22-U22)) -> 0.00026 | X22: =IF(W22="","",R22) -> 101.15834 | Y22: 0.65877 | Z22: =IF(Y22="","",IF(L22="Long",Y22-U22,U22-Y22)) -> 0.00022 | AA22: =IF(AB22="","",AB22*X22/1) -> 85.595516 | AB22: =IF(Z22="","",Z22*1/W22) -> 0.84615385 | AC22: 5 de Abril | AD22: 0.65829 | AE22: -12.18 | AF22: 0 | AG22: -52.79 | AH22: =IF(AG22="","",AG22+AF22+AE22) -> -64.97 | AI22: =IF(AD22="","",IF(L22="Long",AD22-U22,U22-AD22)) -> -0.00026 | AJ22: =IF(AI22="","",AG22*S22/X22) -> -0.0052185516 | AK22: =IF(AI22="","",(AG22+AF22+AE22)*S22/X22) -> -0.0064226046 | AL22: =Q22+AH22 -> 10050.864 | AV22: 15s | BH22: CADJPY | BI22: =$BA$11 -> Minors | BJ22: Avaliação da Saída
B23: FTMO challenge 1 | C23: 89 | D23: 14 | E23: 6ª F | F23: 5 de Abril | G23: NY | H23: Majors | I23: EURUSD | J23: ICT | K23: 1m | L23: Long | M23: L | Q23: =AL22 -> 10050.864 | R23: =IF(Q23="","",S23*Q23/100%) -> 100.50864 | S23: 0.01 | U23: 1.08 | V23: 1.0791 | W23: =IF(V23="","",IF(L23="Long",U23-V23,V23-U23)) -> 0.0009 | X23: =IF(W23="","",R23) -> 100.50864 | Y23: 1.08414 | Z23: =IF(Y23="","",IF(L23="Long",Y23-U23,U23-Y23)) -> 0.00414 | AA23: =IF(AB23="","",AB23*X23/1) -> 462.33973 | AB23: =IF(Z23="","",Z23*1/W23) -> 4.6 | AC23: 5 de Abril | AD23: 1.07995 | AE23: -3.7 | AF23: 0 | AG23: -6.16 | AH23: =IF(AG23="","",AG23+AF23+AE23) -> -9.86 | AI23: =IF(AD23="","",IF(L23="Long",AD23-U23,U23-AD23)) -> -5e-05 | AJ23: =IF(AI23="","",AG23*S23/X23) -> -0.00061288265 | AK23: =IF(AI23="","",(AG23+AF23+AE23)*S23/X23) -> -0.00098101022 | AL23: =Q23+AH23 -> 10041.004 | AV23: 1m | BH23: CHFJPY | BI23: =$BA$11 -> Minors | BL23: A | BM23: Take Profit no ponto definido inicialmente - saida automática
B24: FTMO challenge 1 | C24: 90 | D24: 15 | E24: 3ª F | F24: 9 de Abril | G24: NY | H24: Majors | I24: AUDUSD | J24: ICT | K24: 1m | L24: Short | M24: L | Q24: =AL23 -> 10041.004 | R24: =IF(Q24="","",S24*Q24/100%) -> 100.41004 | S24: 0.01 | U24: 0.66183 | V24: 0.662 | W24: =IF(V24="","",IF(L24="Long",U24-V24,V24-U24)) -> 0.00017 | X24: =IF(W24="","",R24) -> 100.41004 | Y24: 0.66114 | Z24: =IF(Y24="","",IF(L24="Long",Y24-U24,U24-Y24)) -> 0.00069 | AA24: =IF(AB24="","",AB24*X24/1) -> 407.54662 | AB24: =IF(Z24="","",Z24*1/W24) -> 4.0588235 | AC24: 9 de Abril | AD24: =V24 -> 0.662 | AE24: -11.24 | AF24: 0 | AG24: =-X24 -> -100.41004 | AH24: =IF(AG24="","",AG24+AF24+AE24) -> -111.65004 | AI24: =IF(AD24="","",IF(L24="Long",AD24-U24,U24-AD24)) -> -0.00017 | AJ24: =IF(AI24="","",AG24*S24/X24) -> -0.01 | AK24: =IF(AI24="","",(AG24+AF24+AE24)*S24/X24) -> -0.01111941 | AL24: =Q24+AH24 -> 9929.3536 | AV24: 2m | BH24: EURAUD | BI24: =$BA$11 -> Minors | BL24: B | BM24: Stop-Win em trailing Sop com estratégia
B25: FTMO challenge 1 | C25: 91 | D25: 15 | E25: 3ª F | F25: 9 de Abril | G25: NY | H25: Majors | I25: EURUSD | J25: ICT | K25: 1m | L25: long | M25: W | Q25: =AL24 -> 9929.3536 | R25: =IF(Q25="","",S25*Q25/100%) -> 99.293536 | S25: 0.01 | U25: 1.08668 | V25: 1.08594 | W25: =IF(V25="","",IF(L25="Long",U25-V25,V25-U25)) -> 0.00074 | X25: =IF(W25="","",R25) -> 99.293536 | Y25: 1.08901 | Z25: =IF(Y25="","",IF(L25="Long",Y25-U25,U25-Y25)) -> 0.00233 | AA25: =IF(AB25="","",AB25*X25/1) -> 312.64046 | AB25: =IF(Z25="","",Z25*1/W25) -> 3.1486486 | AC25: 9 de Abril | AD25: 1.08594 | AE25: -4.2 | AF25: 0 | AG25: 176.04 | AH25: =IF(AG25="","",AG25+AF25+AE25) -> 171.84 | AI25: =IF(AD25="","",IF(L25="Long",AD25-U25,U25-AD25)) -> -0.00074 | AJ25: =IF(AI25="","",AG25*S25/X25) -> 0.017729251 | AK25: =IF(AI25="","",(AG25+AF25+AE25)*S25/X25) -> 0.017306262 | AL25: =Q25+AH25 -> 10101.194 | AV25: 4m | BH25: EURCAD | BI25: =$BA$11 -> Minors | BL25: C | BM25: Stop-Loss Parcial devido a falha na posição - Reversão da posição a negativo - Stop de Segurança
B26: FTMO challenge 1 | C26: 92 | D26: 15 | E26: 4ª F | F26: 10 de Abril | G26: NY | H26: Majors | I26: EURUSD | J26: ICT | K26: 1m | L26: Short | M26: L | Q26: =AL25 -> 10101.194 | R26: =IF(Q26="","",S26*Q26/100%) -> 101.01194 | S26: 0.01 | U26: 1.08594 | V26: 1.08635 | W26: =IF(V26="","",IF(L26="Long",U26-V26,V26-U26)) -> 0.00041 | X26: =IF(W26="","",R26) -> 101.01194 | Y26: 1.08491 | Z26: =IF(Y26="","",IF(L26="Long",Y26-U26,U26-Y26)) -> 0.00103 | AA26: =IF(AB26="","",AB26*X26/1) -> 253.76169 | AB26: =IF(Z26="","",Z26*1/W26) -> 2.5121951 | AC26: 10 de Abril | AD26: 1.08601 | AE26: -7.74 | AF26: 0 | AG26: -18.05 | AH26: =IF(AG26="","",AG26+AF26+AE26) -> -25.79 | AI26: =IF(AD26="","",IF(L26="Long",AD26-U26,U26-AD26)) -> -7e-05 | AJ26: =IF(AI26="","",AG26*S26/X26) -> -0.0017869175 | AK26: =IF(AI26="","",(AG26+AF26+AE26)*S26/X26) -> -0.0025531636 | AL26: =Q26+AH26 -> 10075.404 | BH26: EURCHF | BI26: =$BA$11 -> Minors | BL26: D | BM26: Stop-Loss Total - Má gestão de saída da posição
B27: FTMO challenge 1 | C27: 93 | D27: 15 | E27: 4ª F | F27: 10 de Abril | G27: NY | H27: Majors | I27: EURUSD | J27: ICT | K27: 1m | L27: Short | M27: L | Q27: =AL26 -> 10075.404 | R27: =IF(Q27="","",S27*Q27/100%) -> 100.75404 | S27: 0.01 | U27: 1.08594 | V27: 1.08633 | W27: =IF(V27="","",IF(L27="Long",U27-V27,V27-U27)) -> 0.00039 | X27: =IF(W27="","",R27) -> 100.75404 | Y27: 1.08491 | Z27: =IF(Y27="","",IF(L27="Long",Y27-U27,U27-Y27)) -> 0.00103 | AA27: =IF(AB27="","",AB27*X27/1) -> 266.09399 | AB27: =IF(Z27="","",Z27*1/W27) -> 2.6410256 | AC27: 10 de Abril | AD27: 1.08619 | AE27: -8.56 | AF27: 0 | AG27: -71.35 | AH27: =IF(AG27="","",AG27+AF27+AE27) -> -79.91 | AI27: =IF(AD27="","",IF(L27="Long",AD27-U27,U27-AD27)) -> -0.00025 | AJ27: =IF(AI27="","",AG27*S27/X27) -> -0.0070816021 | AK27: =IF(AI27="","",(AG27+AF27+AE27)*S27/X27) -> -0.0079311959 | AL27: =Q27+AH27 -> 9995.4936 | BH27: EURGBP | BI27: =$BA$11 -> Minors | BL27: E | BM27: Fecho Manual - Desconforto com a posição/ 1ª Vela negativa / Reversão
B28: FTMO challenge 1 | C28: 94 | D28: 15 | E28: 4ª F | F28: 10 de Abril | G28: NY | H28: Majors | I28: EURUSD | J28: ICT | K28: 1m | L28: Long | M28: L | Q28: =AL27 -> 9995.4936 | R28: =IF(Q28="","",S28*Q28/100%) -> 99.954936 | S28: 0.01 | U28: 1.07546 | V28: 1.07489 | W28: =IF(V28="","",IF(L28="Long",U28-V28,V28-U28)) -> 0.00057 | X28: =IF(W28="","",R28) -> 99.954936 | Y28: 1.07785 | Z28: =IF(Y28="","",IF(L28="Long",Y28-U28,U28-Y28)) -> 0.00239 | AA28: =IF(AB28="","",AB28*X28/1) -> 419.10929 | AB28: =IF(Z28="","",Z28*1/W28) -> 4.1929825 | AC28: 10 de Abril | AD28: 1.07546 | AE28: -5.6 | AF28: 0 | AG28: -60.4 | AH28: =IF(AG28="","",AG28+AF28+AE28) -> -66 | AI28: =IF(AD28="","",IF(L28="Long",AD28-U28,U28-AD28)) -> 0 | AJ28: =IF(AI28="","",AG28*S28/X28) -> -0.0060427231 | AK28: =IF(AI28="","",(AG28+AF28+AE28)*S28/X28) -> -0.0066029755 | AL28: =Q28+AH28 -> 9929.4936 | BH28: EURJPY | BI28: =$BA$11 -> Minors
B29: FTMO challenge 1 | C29: 100 | D29: 19 | E29: 2ª F | F29: 6 de Maio | G29: Londres | H29: Majors | I29: GBPUSD | J29: ICT | K29: 1m | L29: Short | M29: W | Q29: =AL28 -> 9929.4936 | R29: =IF(Q29="","",S29*Q29/100%) -> 99.294936 | S29: 0.01 | U29: 1.25713 | V29: 1.25753 | W29: =IF(V29="","",IF(L29="Long",U29-V29,V29-U29)) -> 0.0004 | X29: =IF(W29="","",R29) -> 99.294936 | Y29: 1.25673 | Z29: =IF(Y29="","",IF(L29="Long",Y29-U29,U29-Y29)) -> 0.0004 | AA29: =IF(AB29="","",AB29*X29/1) -> 99.294936 | AB29: =IF(Z29="","",Z29*1/W29) -> 1 | AC29: 6 de Maio | AD29: =Y29 -> 1.25673 | AE29: -7.08 | AF29: 0 | AG29: =AA29 -> 99.294936 | AH29: =IF(AG29="","",AG29+AF29+AE29) -> 92.214936 | AI29: =IF(AD29="","",IF(L29="Long",AD29-U29,U29-AD29)) -> 0.0004 | AJ29: =IF(AI29="","",AG29*S29/X29) -> 0.01 | AK29: =IF(AI29="","",(AG29+AF29+AE29)*S29/X29) -> 0.0092869727 | AL29: =Q29+AH29 -> 10021.709 | BH29: EURNZD | BI29: =$BA$11 -> Minors
B30: FTMO challenge 1 | C30: 101 | D30: 19 | E30: 3ª F | F30: 7 de Maio | G30: Londres | H30: Majors | I30: GBPUSD | J30: ICT | K30: 1m | L30: Short | M30: W | Q30: =AL29 -> 10021.709 | R30: =IF(Q30="","",S30*Q30/100%) -> 100.21709 | S30: 0.01 | U30: 1.25427 | V30: 1.25477 | W30: =IF(V30="","",IF(L30="Long",U30-V30,V30-U30)) -> 0.0005 | X30: =IF(W30="","",R30) -> 100.21709 | Y30: 1.25376 | Z30: =IF(Y30="","",IF(L30="Long",Y30-U30,U30-Y30)) -> 0.00051 | AA30: =IF(AB30="","",AB30*X30/1) -> 102.22143 | AB30: =IF(Z30="","",Z30*1/W30) -> 1.02 | AC30: 7 de Maio | AD30: =Y30 -> 1.25376 | AE30: -6.54 | AF30: 0 | AG30: =AA30 -> 102.22143 | AH30: =IF(AG30="","",AG30+AF30+AE30) -> 95.681428 | AI30: =IF(AD30="","",IF(L30="Long",AD30-U30,U30-AD30)) -> 0.00051 | AJ30: =IF(AI30="","",AG30*S30/X30) -> 0.0102 | AK30: =IF(AI30="","",(AG30+AF30+AE30)*S30/X30) -> 0.0095474167 | AL30: =Q30+AH30 -> 10117.39 | BH30: GBPAUD | BI30: =$BA$11 -> Minors
B31: FTMO challenge 1 | C31: 102 | D31: 19 | E31: 3ª F | F31: 7 de Maio | G31: NY | H31: Majors | I31: EURUSD | J31: ICT | K31: 1m | L31: Short | M31: L | Q31: =AL30 -> 10117.39 | R31: =IF(Q31="","",S31*Q31/100%) -> 101.1739 | S31: 0.01 | U31: 1.07753 | V31: 1.07789 | W31: =IF(V31="","",IF(L31="Long",U31-V31,V31-U31)) -> 0.00036 | X31: =IF(W31="","",R31) -> 101.1739 | Y31: 1.07717 | Z31: =IF(Y31="","",IF(L31="Long",Y31-U31,U31-Y31)) -> 0.00036 | AA31: =IF(AB31="","",AB31*X31/1) -> 101.1739 | AB31: =IF(Z31="","",Z31*1/W31) -> 1 | AC31: 7 de Maio | AD31: =V31 -> 1.07789 | AE31: -8.82 | AF31: 0 | AG31: =-X31 -> -101.1739 | AH31: =IF(AG31="","",AG31+AF31+AE31) -> -109.9939 | AI31: =IF(AD31="","",IF(L31="Long",AD31-U31,U31-AD31)) -> -0.00036 | AJ31: =IF(AI31="","",AG31*S31/X31) -> -0.01 | AK31: =IF(AI31="","",(AG31+AF31+AE31)*S31/X31) -> -0.010871766 | AL31: =Q31+AH31 -> 10007.396 | BH31: GBPCAD | BI31: =$BA$11 -> Minors
B32: FTMO challenge 1 | C32: 103 | D32: 19 | E32: 4ª F | F32: 8 de Maio | G32: NY | H32: Majors | I32: GBPUSD | J32: ICT | K32: 1m | L32: Long | M32: L | Q32: =AL31 -> 10007.396 | R32: =IF(Q32="","",S32*Q32/100%) -> 100.07396 | S32: 0.01 | U32: 1.24788 | V32: 1.24741 | W32: =IF(V32="","",IF(L32="Long",U32-V32,V32-U32)) -> 0.00047 | X32: =IF(W32="","",R32) -> 100.07396 | Y32: 1.24842 | Z32: =IF(Y32="","",IF(L32="Long",Y32-U32,U32-Y32)) -> 0.00054 | AA32: =IF(AB32="","",AB32*X32/1) -> 114.97859 | AB32: =IF(Z32="","",Z32*1/W32) -> 1.1489362 | AC32: 8 de Maio | AD32: 1.24842 | AE32: -6.68 | AF32: 0 | AG32: =-X32 -> -100.07396 | AH32: =IF(AG32="","",AG32+AF32+AE32) -> -106.75396 | AI32: =IF(AD32="","",IF(L32="Long",AD32-U32,U32-AD32)) -> 0.00054 | AJ32: =IF(AI32="","",AG32*S32/X32) -> -0.01 | AK32: =IF(AI32="","",(AG32+AF32+AE32)*S32/X32) -> -0.010667506 | AL32: =Q32+AH32 -> 9900.6421 | BH32: GBPCHF | BI32: =$BA$11 -> Minors
B33: FTMO challenge 1 | C33: 104 | D33: 19 | E33: 5ª F | F33: 9 de Maio | G33: Londres | H33: Majors | I33: GBPUSD | J33: ICT | K33: 1m | L33: Long | M33: L | Q33: =AL32 -> 9900.6421 | R33: =IF(Q33="","",S33*Q33/100%) -> 99.006421 | S33: 0.01 | U33: 1.24774 | V33: 1.24729 | W33: =IF(V33="","",IF(L33="Long",U33-V33,V33-U33)) -> 0.00045 | X33: =IF(W33="","",R33) -> 99.006421 | Y33: 1.24819 | Z33: =IF(Y33="","",IF(L33="Long",Y33-U33,U33-Y33)) -> 0.00045 | AA33: =IF(AB33="","",AB33*X33/1) -> 99.006421 | AB33: =IF(Z33="","",Z33*1/W33) -> 1 | AC33: 9 de Maio | AD33: 1.24748 | AE33: -6.96 | AF33: 0 | AG33: =-X33 -> -99.006421 | AH33: =IF(AG33="","",AG33+AF33+AE33) -> -105.96642 | AI33: =IF(AD33="","",IF(L33="Long",AD33-U33,U33-AD33)) -> -0.00026 | AJ33: =IF(AI33="","",AG33*S33/X33) -> -0.01 | AK33: =IF(AI33="","",(AG33+AF33+AE33)*S33/X33) -> -0.010702985 | AL33: =Q33+AH33 -> 9794.6757 | BH33: GBPJPY | BI33: =$BA$11 -> Minors
B34: FTMO challenge 1 | C34: 105 | D34: 20 | E34: 2ª F | F34: 13 de Maio | G34: Londres | H34: Majors | I34: GBPUSD | J34: ICT | K34: 5m | L34: Short | M34: L | Q34: =AL33 -> 9794.6757 | R34: =IF(Q34="","",S34*Q34/100%) -> 97.946757 | S34: 0.01 | U34: 1.25241 | V34: 1.25282 | W34: =IF(V34="","",IF(L34="Long",U34-V34,V34-U34)) -> 0.00041 | X34: =IF(W34="","",R34) -> 97.946757 | Y34: 1.252 | Z34: =IF(Y34="","",IF(L34="Long",Y34-U34,U34-Y34)) -> 0.00041 | AA34: =IF(AB34="","",AB34*X34/1) -> 97.946757 | AB34: =IF(Z34="","",Z34*1/W34) -> 1 | AC34: 13 de Maio | AD34: =V34 -> 1.25282 | AE34: -7.4 | AF34: 0 | AG34: =-X34 -> -97.946757 | AH34: =IF(AG34="","",AG34+AF34+AE34) -> -105.34676 | AI34: =IF(AD34="","",IF(L34="Long",AD34-U34,U34-AD34)) -> -0.00041 | AJ34: =IF(AI34="","",AG34*S34/X34) -> -0.01 | AK34: =IF(AI34="","",(AG34+AF34+AE34)*S34/X34) -> -0.010755513 | AL34: =Q34+AH34 -> 9689.329 | BH34: GBPNZD | BI34: =$BA$11 -> Minors
B35: FTMO challenge 1 | C35: 106 | D35: 20 | E35: 2ª F | F35: 13 de Maio | G35: NY | H35: Majors | I35: GBPUSD | J35: ICT | K35: 5m | L35: Short | M35: L | Q35: =AL34 -> 9689.329 | R35: =IF(Q35="","",S35*Q35/100%) -> 96.89329 | S35: 0.01 | U35: 1.25591 | V35: 1.25647 | W35: =IF(V35="","",IF(L35="Long",U35-V35,V35-U35)) -> 0.00056 | X35: =IF(W35="","",R35) -> 96.89329 | Y35: 1.25535 | Z35: =IF(Y35="","",IF(L35="Long",Y35-U35,U35-Y35)) -> 0.00056 | AA35: =IF(AB35="","",AB35*X35/1) -> 96.89329 | AB35: =IF(Z35="","",Z35*1/W35) -> 1 | AC35: 13 de Maio | AD35: =V35 -> 1.25647 | AE35: -5.61 | AF35: 0 | AG35: =-X35 -> -96.89329 | AH35: =IF(AG35="","",AG35+AF35+AE35) -> -102.50329 | AI35: =IF(AD35="","",IF(L35="Long",AD35-U35,U35-AD35)) -> -0.00056 | AJ35: =IF(AI35="","",AG35*S35/X35) -> -0.01 | AK35: =IF(AI35="","",(AG35+AF35+AE35)*S35/X35) -> -0.010578987 | AL35: =Q35+AH35 -> 9586.8257 | BH35: NZDCAD | BI35: =$BA$11 -> Minors
B36: FTMO challenge 1 | C36: 107 | D36: 21 | E36: 2ª F | F36: 20 de Maio | G36: NY | H36: Majors | I36: EURUSD | J36: ICT | K36: 1m | L36: Long | M36: W | Q36: =AL35 -> 9586.8257 | R36: =IF(Q36="","",S36*Q36/100%) -> 95.868257 | S36: 0.01 | U36: 1.08593 | V36: 1.08556 | W36: =IF(V36="","",IF(L36="Long",U36-V36,V36-U36)) -> 0.00037 | X36: =IF(W36="","",R36) -> 95.868257 | Y36: 1.08655 | Z36: =IF(Y36="","",IF(L36="Long",Y36-U36,U36-Y36)) -> 0.00062 | AA36: =IF(AB36="","",AB36*X36/1) -> 160.64411 | AB36: =IF(Z36="","",Z36*1/W36) -> 1.6756757 | AC36: 20 de Maio | AD36: =Y36 -> 1.08655 | AE36: -8.23 | AF36: 0 | AG36: =AA36 -> 160.64411 | AH36: =IF(AG36="","",AG36+AF36+AE36) -> 152.41411 | AI36: =IF(AD36="","",IF(L36="Long",AD36-U36,U36-AD36)) -> 0.00062 | AJ36: =IF(AI36="","",AG36*S36/X36) -> 0.016756757 | AK36: =IF(AI36="","",(AG36+AF36+AE36)*S36/X36) -> 0.015898287 | AL36: =Q36+AH36 -> 9739.2398 | BH36: NZDCHF | BI36: =$BA$11 -> Minors
B37: FTMO challenge 1 | C37: 108 | D37: 22 | E37: 2ª F | F37: 27 de Maio | G37: NY | H37: Majors | I37: EURUSD | J37: SSL | K37: 1m | L37: Long | M37: w | Q37: =AL36 -> 9739.2398 | R37: =IF(Q37="","",S37*Q37/100%) -> 97.392398 | S37: 0.01 | U37: 1.0847 | V37: 1.08432 | W37: =IF(V37="","",IF(L37="Long",U37-V37,V37-U37)) -> 0.00038 | X37: =IF(W37="","",R37) -> 97.392398 | Y37: 1.08564 | Z37: =IF(Y37="","",IF(L37="Long",Y37-U37,U37-Y37)) -> 0.00094 | AA37: =IF(AB37="","",AB37*X37/1) -> 240.91804 | AB37: =IF(Z37="","",Z37*1/W37) -> 2.4736842 | AC37: 27 de Maio | AD37: 1.08496 | AE37: -8.1 | AF37: 0 | AG37: 57 | AH37: =IF(AG37="","",AG37+AF37+AE37) -> 48.9 | AI37: =IF(AD37="","",IF(L37="Long",AD37-U37,U37-AD37)) -> 0.00026 | AJ37: =IF(AI37="","",AG37*S37/X37) -> 0.0058526129 | AK37: =IF(AI37="","",(AG37+AF37+AE37)*S37/X37) -> 0.0050209258 | AL37: =Q37+AH37 -> 9788.1398 | BH37: NZDJPY | BI37: =$BA$11 -> Minors
B38: FTMO challenge 1 | C38: 109 | D38: 22 | E38: 5ª F | F38: 30 de Maio | G38: Londres | H38: Majors | I38: AUDUSD | J38: BSL | K38: 1m | L38: Short | M38: W | Q38: =AL37 -> 9788.1398 | R38: =IF(Q38="","",S38*Q38/100%) -> 97.881398 | S38: 0.01 | U38: 0.66083 | V38: 0.66112 | W38: =IF(V38="","",IF(L38="Long",U38-V38,V38-U38)) -> 0.00029 | X38: =IF(W38="","",R38) -> 97.881398 | Y38: 0.66053 | Z38: =IF(Y38="","",IF(L38="Long",Y38-U38,U38-Y38)) -> 0.0003 | AA38: =IF(AB38="","",AB38*X38/1) -> 101.25662 | AB38: =IF(Z38="","",Z38*1/W38) -> 1.0344828 | AC38: 30 de Maio | AD38: =Y38 -> 0.66053 | AE38: -9.1 | AF38: 0 | AG38: =X38 -> 97.881398 | AH38: =IF(AG38="","",AG38+AF38+AE38) -> 88.781398 | AI38: =IF(AD38="","",IF(L38="Long",AD38-U38,U38-AD38)) -> 0.0003 | AJ38: =IF(AI38="","",AG38*S38/X38) -> 0.01 | AK38: =IF(AI38="","",(AG38+AF38+AE38)*S38/X38) -> 0.0090703034 | AL38: =Q38+AH38 -> 9876.9212 | BH38: NZDUSD | BI38: =$BA$11 -> Minors
B39: FTMO challenge 1 | C39: 110 | D39: 23 | E39: 2ª F | F39: 3 de Junho | G39: Londres | H39: Majors | I39: GBPUSD | J39: SSL | K39: 1m | L39: Long | M39: L | Q39: =AL38 -> 9876.9212 | R39: =IF(Q39="","",S39*Q39/100%) -> 98.769212 | S39: 0.01 | U39: 1.27367 | V39: 1.27325 | W39: =IF(V39="","",IF(L39="Long",U39-V39,V39-U39)) -> 0.00042 | X39: =IF(W39="","",R39) -> 98.769212 | Y39: 1.27409 | Z39: =IF(Y39="","",IF(L39="Long",Y39-U39,U39-Y39)) -> 0.00042 | AA39: =IF(AB39="","",AB39*X39/1) -> 98.769212 | AB39: =IF(Z39="","",Z39*1/W39) -> 1 | AC39: 3 de Junho | AD39: 1.27352 | AE39: -7.08 | AF39: 0 | AG39: -61.32 | AH39: =IF(AG39="","",AG39+AF39+AE39) -> -68.4 | AI39: =IF(AD39="","",IF(L39="Long",AD39-U39,U39-AD39)) -> -0.00015 | AJ39: =IF(AI39="","",AG39*S39/X39) -> -0.0062084124 | AK39: =IF(AI39="","",(AG39+AF39+AE39)*S39/X39) -> -0.006925235 | AL39: =Q39+AH39 -> 9808.5212 | BH39: USDSGD | BI39: =$BA$11 -> Minors
B40: FTMO challenge 1 | C40: 111 | D40: 23 | E40: 2ª F | F40: 3 de Junho | G40: Londres | H40: Majors | I40: USDCAD | J40: BSL | K40: 1m | L40: Short | M40: L | Q40: =AL39 -> 9808.5212 | R40: =IF(Q40="","",S40*Q40/100%) -> 98.085212 | S40: 0.01 | U40: 1.36523 | V40: 1.36571 | W40: =IF(V40="","",IF(L40="Long",U40-V40,V40-U40)) -> 0.00048 | X40: =IF(W40="","",R40) -> 98.085212 | Y40: 1.36463 | Z40: =IF(Y40="","",IF(L40="Long",Y40-U40,U40-Y40)) -> 0.0006 | AA40: =IF(AB40="","",AB40*X40/1) -> 122.60651 | AB40: =IF(Z40="","",Z40*1/W40) -> 1.25 | AC40: 3 de Junho | AD40: =V40 -> 1.36571 | AE40: -8.82 | AF40: 0 | AG40: =-X40 -> -98.085212 | AH40: =IF(AG40="","",AG40+AF40+AE40) -> -106.90521 | AI40: =IF(AD40="","",IF(L40="Long",AD40-U40,U40-AD40)) -> -0.00048 | AJ40: =IF(AI40="","",AG40*S40/X40) -> -0.01 | AK40: =IF(AI40="","",(AG40+AF40+AE40)*S40/X40) -> -0.010899218 | AL40: =Q40+AH40 -> 9701.616 | BH40: AUDSGD | BI40: =$BA$12 -> Exotics
B41: FTMO challenge 1 | C41: 112 | D41: 23 | E41: 2ª F | F41: 3 de Junho | G41: Londres | H41: Majors | I41: USDCAD | J41: BSL | K41: 1m | L41: Short | Q41: =AL40 -> 9701.616 | R41: =IF(Q41="","",S41*Q41/100%) -> 97.01616 | S41: 0.01 | U41: 1.36546 | V41: 1.366 | W41: =IF(V41="","",IF(L41="Long",U41-V41,V41-U41)) -> 0.00054 | X41: =IF(W41="","",R41) -> 97.01616 | Y41: 1.36463 | Z41: =IF(Y41="","",IF(L41="Long",Y41-U41,U41-Y41)) -> 0.00083 | AA41: =IF(AB41="","",AB41*X41/1) -> 149.11743 | AB41: =IF(Z41="","",Z41*1/W41) -> 1.537037 | AC41: 3 de Junho | AD41: =U41 -> 1.36546 | AE41: -7.9 | AF41: 0 | AG41: 0 | AH41: =IF(AG41="","",AG41+AF41+AE41) -> -7.9 | AI41: =IF(AD41="","",IF(L41="Long",AD41-U41,U41-AD41)) -> 0 | AJ41: =IF(AI41="","",AG41*S41/X41) -> 0 | AK41: =IF(AI41="","",(AG41+AF41+AE41)*S41/X41) -> -0.00081429733 | AL41: =Q41+AH41 -> 9693.716 | BH41: CHFSGD | BI41: =$BA$12 -> Exotics
B42: FTMO challenge 1 | C42: 113 | D42: 23 | E42: 3ª F | F42: 4 de Junho | G42: Londres | H42: Majors | I42: AUDUSD | J42: SSL | K42: 1m | L42: Long | M42: L | Q42: =AL41 -> 9693.716 | R42: =IF(Q42="","",S42*Q42/100%) -> 96.93716 | S42: 0.01 | U42: 0.66637 | V42: 0.66602 | W42: =IF(V42="","",IF(L42="Long",U42-V42,V42-U42)) -> 0.00035 | X42: =IF(W42="","",R42) -> 96.93716 | Y42: 0.66707 | Z42: =IF(Y42="","",IF(L42="Long",Y42-U42,U42-Y42)) -> 0.0007 | AA42: =IF(AB42="","",AB42*X42/1) -> 193.87432 | AB42: =IF(Z42="","",Z42*1/W42) -> 2 | AC42: 4 de Junho | AD42: =V42 -> 0.66602 | AE42: -9.01 | AF42: 0 | AG42: =-X42 -> -96.93716 | AH42: =IF(AG42="","",AG42+AF42+AE42) -> -105.94716 | AI42: =IF(AD42="","",IF(L42="Long",AD42-U42,U42-AD42)) -> -0.00035 | AJ42: =IF(AI42="","",AG42*S42/X42) -> -0.01 | AK42: =IF(AI42="","",(AG42+AF42+AE42)*S42/X42) -> -0.010929468 | AL42: =Q42+AH42 -> 9587.7688 | BH42: EURDKK | BI42: =$BA$12 -> Exotics
B43: FTMO challenge 1 | C43: 114 | D43: 23 | E43: 5ª F | F43: 6 de Junho | G43: NY | H43: Majors | I43: USDCAD | J43: BSL | K43: 3m | L43: Short | M43: L | Q43: =AL42 -> 9587.7688 | R43: =IF(Q43="","",S43*Q43/100%) -> 95.877688 | S43: 0.01 | U43: 1.36952 | V43: 1.36976 | W43: =IF(V43="","",IF(L43="Long",U43-V43,V43-U43)) -> 0.00024 | X43: =IF(W43="","",R43) -> 95.877688 | Y43: 1.36906 | Z43: =IF(Y43="","",IF(L43="Long",Y43-U43,U43-Y43)) -> 0.00046 | AA43: =IF(AB43="","",AB43*X43/1) -> 183.76557 | AB43: =IF(Z43="","",Z43*1/W43) -> 1.9166667 | AC43: 6 de Junho | AD43: =V43 -> 1.36976 | AE43: -8.62 | AF43: 0 | AG43: =-X43 -> -95.877688 | AH43: =IF(AG43="","",AG43+AF43+AE43) -> -104.49769 | AI43: =IF(AD43="","",IF(L43="Long",AD43-U43,U43-AD43)) -> -0.00024 | AJ43: =IF(AI43="","",AG43*S43/X43) -> -0.01 | AK43: =IF(AI43="","",(AG43+AF43+AE43)*S43/X43) -> -0.010899062 | AL43: =Q43+AH43 -> 9483.2711 | BH43: EURHKD | BI43: =$BA$12 -> Exotics
B44: FTMO challenge 1 | C44: 115 | D44: 23 | E44: 5ª F | F44: 6 de Junho | G44: NY | H44: Majors | I44: GBPUSD | J44: SSL | K44: 1m | L44: Long | M44: W | Q44: =AL43 -> 9483.2711 | R44: =IF(Q44="","",S44*Q44/100%) -> 94.832711 | S44: 0.01 | U44: 1.2772 | V44: 1.27663 | W44: =IF(V44="","",IF(L44="Long",U44-V44,V44-U44)) -> 0.00057 | X44: =IF(W44="","",R44) -> 94.832711 | Y44: 1.27834 | Z44: =IF(Y44="","",IF(L44="Long",Y44-U44,U44-Y44)) -> 0.00114 | AA44: =IF(AB44="","",AB44*X44/1) -> 189.66542 | AB44: =IF(Z44="","",Z44*1/W44) -> 2 | AC44: 6 de Junho | AD44: =Y44 -> 1.27834 | AE44: -5.1 | AF44: 0 | AG44: =AA44 -> 189.66542 | AH44: =IF(AG44="","",AG44+AF44+AE44) -> 184.56542 | AI44: =IF(AD44="","",IF(L44="Long",AD44-U44,U44-AD44)) -> 0.00114 | AJ44: =IF(AI44="","",AG44*S44/X44) -> 0.02 | AK44: =IF(AI44="","",(AG44+AF44+AE44)*S44/X44) -> 0.019462211 | AL44: =Q44+AH44 -> 9667.8365 | BH44: EURNOK | BI44: =$BA$12 -> Exotics
B45: FTMO challenge 1 | C45: 116 | D45: 23 | E45: 6ª F | F45: 7 de Junho | G45: Londres | H45: Majors | I45: GBPUSD | J45: BSL | K45: 1m | L45: Short | M45: L | Q45: =AL44 -> 9667.8365 | R45: =IF(Q45="","",S45*Q45/100%) -> 96.678365 | S45: 0.01 | U45: 1.27983 | V45: 1.28009 | W45: =IF(V45="","",IF(L45="Long",U45-V45,V45-U45)) -> 0.00026 | X45: =IF(W45="","",R45) -> 96.678365 | Y45: 1.2792 | Z45: =IF(Y45="","",IF(L45="Long",Y45-U45,U45-Y45)) -> 0.00063 | AA45: =IF(AB45="","",AB45*X45/1) -> 234.25912 | AB45: =IF(Z45="","",Z45*1/W45) -> 2.4230769 | AC45: 7 de Junho | AD45: =V45 -> 1.28009 | AE45: -5.9 | AF45: 0 | AG45: =-X45 -> -96.678365 | AH45: =IF(AG45="","",AG45+AF45+AE45) -> -102.57837 | AI45: =IF(AD45="","",IF(L45="Long",AD45-U45,U45-AD45)) -> -0.00026 | AJ45: =IF(AI45="","",AG45*S45/X45) -> -0.01 | AK45: =IF(AI45="","",(AG45+AF45+AE45)*S45/X45) -> -0.010610271 | AL45: =Q45+AH45 -> 9565.2582 | BH45: EURPLN | BI45: =$BA$12 -> Exotics
B46: Fusion demo | C46: 117 | D46: 24 | E46: 3ª F | F46: 12 de Junho | G46: Londres | H46: Majors | I46: GBPUSD | J46: BSL | K46: 1m | L46: Short | M46: W | Q46: =AL45 -> 9565.2582 | R46: =IF(Q46="","",S46*Q46/100%) -> 95.652582 | S46: 0.01 | U46: 1.27472 | V46: 1.27504 | W46: =IF(V46="","",IF(L46="Long",U46-V46,V46-U46)) -> 0.00032 | X46: =IF(W46="","",R46) -> 95.652582 | Y46: 1.27408 | Z46: =IF(Y46="","",IF(L46="Long",Y46-U46,U46-Y46)) -> 0.00064 | AA46: =IF(AB46="","",AB46*X46/1) -> 191.30516 | AB46: =IF(Z46="","",Z46*1/W46) -> 2 | AC46: 12 de Junho | AD46: =Y46 -> 1.27408 | AE46: -12.92 | AF46: 0 | AG46: =AA46 -> 191.30516 | AH46: =IF(AG46="","",AG46+AF46+AE46) -> 178.38516 | AI46: =IF(AD46="","",IF(L46="Long",AD46-U46,U46-AD46)) -> 0.00064 | AJ46: =IF(AI46="","",AG46*S46/X46) -> 0.02 | AK46: =IF(AI46="","",(AG46+AF46+AE46)*S46/X46) -> 0.018649278 | AL46: =Q46+AH46 -> 9743.6433 | BH46: EURSEK | BI46: =$BA$12 -> Exotics
B47: Fusion demo | C47: 118 | D47: 24 | E47: 5ª F | F47: 13 de Junho | G47: Londres | H47: Majors | I47: GBPUSD | J47: BSL | K47: 1m | L47: Short | M47: L | Q47: =AL46 -> 9743.6433 | R47: =IF(Q47="","",S47*Q47/100%) -> 97.436433 | S47: 0.01 | U47: 1.27883 | V47: 1.27918 | W47: =IF(V47="","",IF(L47="Long",U47-V47,V47-U47)) -> 0.00035 | X47: =IF(W47="","",R47) -> 97.436433 | Y47: 1.27831 | Z47: =IF(Y47="","",IF(L47="Long",Y47-U47,U47-Y47)) -> 0.00052 | AA47: =IF(AB47="","",AB47*X47/1) -> 144.7627 | AB47: =IF(Z47="","",Z47*1/W47) -> 1.4857143 | AC47: 13 de Junho | AD47: =V47 -> 1.27918 | AE47: -12.1 | AF47: 0 | AG47: =-X47 -> -97.436433 | AH47: =IF(AG47="","",AG47+AF47+AE47) -> -109.53643 | AI47: =IF(AD47="","",IF(L47="Long",AD47-U47,U47-AD47)) -> -0.00035 | AJ47: =IF(AI47="","",AG47*S47/X47) -> -0.01 | AK47: =IF(AI47="","",(AG47+AF47+AE47)*S47/X47) -> -0.011241835 | AL47: =Q47+AH47 -> 9634.1069 | BH47: EURSGD | BI47: =$BA$12 -> Exotics
B48: Fusion demo | C48: 119 | D48: 24 | E48: 6ª F | F48: 14 de Junho | G48: Londres | H48: Majors | I48: GBPUSD | J48: SSL | K48: 3m | L48: Long | Q48: =AL47 -> 9634.1069 | R48: =IF(Q48="","",S48*Q48/100%) -> 96.341069 | S48: 0.01 | U48: 1.27283 | V48: 1.27218 | W48: =IF(V48="","",IF(L48="Long",U48-V48,V48-U48)) -> 0.00065 | X48: =IF(W48="","",R48) -> 96.341069 | Y48: 1.27383 | Z48: =IF(Y48="","",IF(L48="Long",Y48-U48,U48-Y48)) -> 0.001 | AA48: =IF(AB48="","",AB48*X48/1) -> 148.21703 | AB48: =IF(Z48="","",Z48*1/W48) -> 1.5384615 | AC48: 14 de Junho | AD48: 1.27284 | AE48: -6.48 | AF48: 0 | AG48: 5 | AH48: =IF(AG48="","",AG48+AF48+AE48) -> -1.48 | AI48: =IF(AD48="","",IF(L48="Long",AD48-U48,U48-AD48)) -> 1e-05 | AJ48: =IF(AI48="","",AG48*S48/X48) -> 0.00051898947 | AK48: =IF(AI48="","",(AG48+AF48+AE48)*S48/X48) -> -0.00015362088 | AL48: =Q48+AH48 -> 9632.6269 | BH48: EURTRY | BI48: =$BA$12 -> Exotics
B49: Fusion demo | C49: 120 | D49: 24 | E49: 6ª F | F49: 14 de Junho | G49: NY | H49: Majors | I49: AUDUSD | J49: SSL | K49: 3m | L49: Long | M49: w | Q49: =AL48 -> 9632.6269 | R49: =IF(Q49="","",S49*Q49/100%) -> 96.326269 | S49: 0.01 | U49: 0.66127 | V49: 0.66096 | W49: =IF(V49="","",IF(L49="Long",U49-V49,V49-U49)) -> 0.00031 | X49: =IF(W49="","",R49) -> 96.326269 | Y49: 0.66174 | Z49: =IF(Y49="","",IF(L49="Long",Y49-U49,U49-Y49)) -> 0.00047 | AA49: =IF(AB49="","",AB49*X49/1) -> 146.04305 | AB49: =IF(Z49="","",Z49*1/W49) -> 1.516129 | AC49: 14 de Junho | AD49: =Y49 -> 0.66174 | AE49: -12.2 | AF49: 0 | AG49: =AA49 -> 146.04305 | AH49: =IF(AG49="","",AG49+AF49+AE49) -> 133.84305 | AI49: =IF(AD49="","",IF(L49="Long",AD49-U49,U49-AD49)) -> 0.00047 | AJ49: =IF(AI49="","",AG49*S49/X49) -> 0.01516129 | AK49: =IF(AI49="","",(AG49+AF49+AE49)*S49/X49) -> 0.013894761 | AL49: =Q49+AH49 -> 9766.47 | BH49: EURZAR | BI49: =$BA$12 -> Exotics
B50: Fusion demo | C50: 121 | D50: 25 | E50: 2ª F | F50: 17 de Junho | G50: Londres | H50: Majors | I50: AUDUSD | J50: SSL | K50: 1m | L50: Long | M50: L | Q50: =AL49 -> 9766.47 | R50: =IF(Q50="","",S50*Q50/100%) -> 97.6647 | S50: 0.01 | U50: 0.65945 | V50: 0.6592 | W50: =IF(V50="","",IF(L50="Long",U50-V50,V50-U50)) -> 0.00025 | X50: =IF(W50="","",R50) -> 97.6647 | Y50: 0.65998 | Z50: =IF(Y50="","",IF(L50="Long",Y50-U50,U50-Y50)) -> 0.00053 | AA50: =IF(AB50="","",AB50*X50/1) -> 207.04916 | AB50: =IF(Z50="","",Z50*1/W50) -> 2.12 | AC50: 17 de Junho | AD50: =V50 -> 0.6592 | AE50: -16.8 | AF50: 0 | AG50: =-X50 -> -97.6647 | AH50: =IF(AG50="","",AG50+AF50+AE50) -> -114.4647 | AI50: =IF(AD50="","",IF(L50="Long",AD50-U50,U50-AD50)) -> -0.00025 | AJ50: =IF(AI50="","",AG50*S50/X50) -> -0.01 | AK50: =IF(AI50="","",(AG50+AF50+AE50)*S50/X50) -> -0.011720171 | AL50: =Q50+AH50 -> 9652.0053 | BH50: GBPDKK | BI50: =$BA$12 -> Exotics
B51: Fusion demo | C51: 122 | D51: 25 | E51: 2ª F | F51: 17 de Junho | G51: NY | H51: Majors | I51: GBPUSD | J51: SSL | K51: 1m | L51: Long | M51: W | Q51: =AL50 -> 9652.0053 | R51: =IF(Q51="","",S51*Q51/100%) -> 96.520053 | S51: 0.01 | U51: 1.26643 | V51: 1.26606 | W51: =IF(V51="","",IF(L51="Long",U51-V51,V51-U51)) -> 0.00037 | X51: =IF(W51="","",R51) -> 96.520053 | Y51: 1.26703 | Z51: =IF(Y51="","",IF(L51="Long",Y51-U51,U51-Y51)) -> 0.0006 | AA51: =IF(AB51="","",AB51*X51/1) -> 156.519 | AB51: =IF(Z51="","",Z51*1/W51) -> 1.6216216 | AC51: 17 de Junho | AD51: =Y51 -> 1.26703 | AE51: -11.86 | AF51: 0 | AG51: =AA51 -> 156.519 | AH51: =IF(AG51="","",AG51+AF51+AE51) -> 144.659 | AI51: =IF(AD51="","",IF(L51="Long",AD51-U51,U51-AD51)) -> 0.0006 | AJ51: =IF(AI51="","",AG51*S51/X51) -> 0.016216216 | AK51: =IF(AI51="","",(AG51+AF51+AE51)*S51/X51) -> 0.014987456 | AL51: =Q51+AH51 -> 9796.6643 | BH51: GBPNOK | BI51: =$BA$12 -> Exotics
B52: Fusion demo | C52: 123 | D52: 25 | E52: 3ª F | F52: 18 de Junho | G52: NY | H52: Indices | I52: UK100 | J52: BSL | K52: 1m | L52: Short | M52: W | Q52: =AL51 -> 9796.6643 | R52: =IF(Q52="","",S52*Q52/100%) -> 97.966643 | S52: 0.01 | U52: 19942.5 | V52: 19961.3 | W52: =IF(V52="","",IF(L52="Long",U52-V52,V52-U52)) -> 18.8 | X52: =IF(W52="","",R52) -> 97.966643 | Y52: 19921.9 | Z52: =IF(Y52="","",IF(L52="Long",Y52-U52,U52-Y52)) -> 20.6 | AA52: =IF(AB52="","",AB52*X52/1) -> 107.34643 | AB52: =IF(Z52="","",Z52*1/W52) -> 1.0957447 | AC52: 18 de Junho | AD52: =Y52 -> 19921.9 | AE52: 0 | AF52: 0 | AG52: =AA52 -> 107.34643 | AH52: =IF(AG52="","",AG52+AF52+AE52) -> 107.34643 | AI52: =IF(AD52="","",IF(L52="Long",AD52-U52,U52-AD52)) -> 20.6 | AJ52: =IF(AI52="","",AG52*S52/X52) -> 0.010957447 | AK52: =IF(AI52="","",(AG52+AF52+AE52)*S52/X52) -> 0.010957447 | AL52: =Q52+AH52 -> 9904.0107 | BH52: GBPSEK | BI52: =$BA$12 -> Exotics
B53: Fusion demo | C53: 124 | D53: 25 | E53: 4ª F | F53: 19 de Junho | G53: Londres | H53: Majors | I53: GBPUSD | J53: BSL | K53: 1m | L53: Short | M53: L | Q53: =AL52 -> 9904.0107 | R53: =IF(Q53="","",S53*Q53/100%) -> 99.040107 | S53: 0.01 | U53: 1.27257 | V53: 1.27314 | W53: =IF(V53="","",IF(L53="Long",U53-V53,V53-U53)) -> 0.00057 | X53: =IF(W53="","",R53) -> 99.040107 | Y53: 1.27073 | Z53: =IF(Y53="","",IF(L53="Long",Y53-U53,U53-Y53)) -> 0.00184 | AA53: =IF(AB53="","",AB53*X53/1) -> 319.70842 | AB53: =IF(Z53="","",Z53*1/W53) -> 3.2280702 | AC53: 19 de Junho | AD53: =V53 -> 1.27314 | AE53: -7.2 | AF53: 0 | AG53: =-X53 -> -99.040107 | AH53: =IF(AG53="","",AG53+AF53+AE53) -> -106.24011 | AI53: =IF(AD53="","",IF(L53="Long",AD53-U53,U53-AD53)) -> -0.00057 | AJ53: =IF(AI53="","",AG53*S53/X53) -> -0.01 | AK53: =IF(AI53="","",(AG53+AF53+AE53)*S53/X53) -> -0.010726978 | AL53: =Q53+AH53 -> 9797.7706 | BH53: GBPSGD | BI53: =$BA$12 -> Exotics
B54: Fusion demo | C54: 125 | D54: 25 | E54: 4ª F | F54: 19 de Junho | G54: Londres | H54: Majors | I54: GBPUSD | J54: BSL | K54: 5m | L54: Short | M54: L | Q54: =AL53 -> 9797.7706 | R54: =IF(Q54="","",S54*Q54/100%) -> 97.977706 | S54: 0.01 | U54: 1.27236 | V54: 1.27334 | W54: =IF(V54="","",IF(L54="Long",U54-V54,V54-U54)) -> 0.00098 | X54: =IF(W54="","",R54) -> 97.977706 | Y54: 1.27031 | Z54: =IF(Y54="","",IF(L54="Long",Y54-U54,U54-Y54)) -> 0.00205 | AA54: =IF(AB54="","",AB54*X54/1) -> 204.95336 | AB54: =IF(Z54="","",Z54*1/W54) -> 2.0918367 | AC54: 19 de Junho | AD54: 1.27288 | AE54: -4.3 | AF54: 0 | AG54: -51 | AH54: =IF(AG54="","",AG54+AF54+AE54) -> -55.3 | AI54: =IF(AD54="","",IF(L54="Long",AD54-U54,U54-AD54)) -> -0.00052 | AJ54: =IF(AI54="","",AG54*S54/X54) -> -0.0052052658 | AK54: =IF(AI54="","",(AG54+AF54+AE54)*S54/X54) -> -0.0056441411 | AL54: =Q54+AH54 -> 9742.4706 | BH54: GBPTRY | BI54: =$BA$12 -> Exotics
B55: Fusion demo | C55: 126 | D55: 25 | E55: 4ª F | F55: 19 de Junho | G55: NY | H55: Majors | I55: USDCAD | J55: SSL | K55: 1m | L55: Long | M55: L | Q55: =AL54 -> 9742.4706 | R55: =IF(Q55="","",S55*Q55/100%) -> 97.424706 | S55: 0.01 | U55: 1.37105 | V55: 1.37085 | W55: =IF(V55="","",IF(L55="Long",U55-V55,V55-U55)) -> 0.0002 | X55: =IF(W55="","",R55) -> 97.424706 | Y55: 1.37151 | Z55: =IF(Y55="","",IF(L55="Long",Y55-U55,U55-Y55)) -> 0.00046 | AA55: =IF(AB55="","",AB55*X55/1) -> 224.07682 | AB55: =IF(Z55="","",Z55*1/W55) -> 2.3 | AC55: 19 de Junho | AD55: =V55 -> 1.37085 | AE55: -30.26 | AF55: 0 | AG55: =-X55 -> -97.424706 | AH55: =IF(AG55="","",AG55+AF55+AE55) -> -127.68471 | AI55: =IF(AD55="","",IF(L55="Long",AD55-U55,U55-AD55)) -> -0.0002 | AJ55: =IF(AI55="","",AG55*S55/X55) -> -0.01 | AK55: =IF(AI55="","",(AG55+AF55+AE55)*S55/X55) -> -0.013105988 | AL55: =Q55+AH55 -> 9614.7859 | BH55: NOKJPY | BI55: =$BA$12 -> Exotics
B56: Fusion demo | C56: 127 | D56: 25 | E56: 4ª F | F56: 19 de Junho | G56: NY | H56: Indices | I56: UK100 | J56: BSL | K56: 1m | L56: Short | M56: L | Q56: =AL55 -> 9614.7859 | R56: =IF(Q56="","",S56*Q56/100%) -> 96.147859 | S56: 0.01 | U56: 19981.6 | V56: 19985.1 | W56: =IF(V56="","",IF(L56="Long",U56-V56,V56-U56)) -> 3.5 | X56: =IF(W56="","",R56) -> 96.147859 | Y56: 19969.9 | Z56: =IF(Y56="","",IF(L56="Long",Y56-U56,U56-Y56)) -> 11.7 | AA56: =IF(AB56="","",AB56*X56/1) -> 321.40856 | AB56: =IF(Z56="","",Z56*1/W56) -> 3.3428571 | AC56: 19 de Junho | AD56: =V56 -> 19985.1 | AE56: 0 | AF56: 0 | AG56: =-X56 -> -96.147859 | AH56: =IF(AG56="","",AG56+AF56+AE56) -> -96.147859 | AI56: =IF(AD56="","",IF(L56="Long",AD56-U56,U56-AD56)) -> -3.5 | AJ56: =IF(AI56="","",AG56*S56/X56) -> -0.01 | AK56: =IF(AI56="","",(AG56+AF56+AE56)*S56/X56) -> -0.01 | AL56: =Q56+AH56 -> 9518.638 | BH56: NOKSEK | BI56: =$BA$12 -> Exotics
B57: Fusion demo | C57: 128 | D57: 25 | E57: 5ª F | F57: 20 de Junho | G57: Londres | H57: Majors | I57: EURUSD | J57: SSL | K57: 3m | L57: Long | M57: L | Q57: =AL56 -> 9518.638 | R57: =IF(Q57="","",S57*Q57/100%) -> 95.18638 | S57: 0.01 | U57: 1.07324 | V57: 1.07295 | W57: =IF(V57="","",IF(L57="Long",U57-V57,V57-U57)) -> 0.00029 | X57: =IF(W57="","",R57) -> 95.18638 | Y57: 1.07371 | Z57: =IF(Y57="","",IF(L57="Long",Y57-U57,U57-Y57)) -> 0.00047 | AA57: =IF(AB57="","",AB57*X57/1) -> 154.26758 | AB57: =IF(Z57="","",Z57*1/W57) -> 1.6206897 | AC57: 20 de Junho | AD57: =V57 -> 1.07295 | AE57: -0.04 | AF57: 0 | AG57: =-X57 -> -95.18638 | AH57: =IF(AG57="","",AG57+AF57+AE57) -> -95.22638 | AI57: =IF(AD57="","",IF(L57="Long",AD57-U57,U57-AD57)) -> -0.00029 | AJ57: =IF(AI57="","",AG57*S57/X57) -> -0.01 | AK57: =IF(AI57="","",(AG57+AF57+AE57)*S57/X57) -> -0.010004202 | AL57: =Q57+AH57 -> 9423.4116 | BH57: SEKJPY | BI57: =$BA$12 -> Exotics
B58: FTMO challenge 1 | C58: 129 | D58: 26 | E58: 2ª F | F58: 24 de Junho | G58: Londres | H58: Majors | I58: GBPUSD | J58: BSL | K58: 1m | L58: Short | M58: L | Q58: =AL57 -> 9423.4116 | R58: =IF(Q58="","",S58*Q58/100%) -> 94.234116 | S58: 0.01 | U58: 1.26497 | V58: 1.26523 | W58: =IF(V58="","",IF(L58="Long",U58-V58,V58-U58)) -> 0.00026 | X58: =IF(W58="","",R58) -> 94.234116 | Y58: 1.26445 | Z58: =IF(Y58="","",IF(L58="Long",Y58-U58,U58-Y58)) -> 0.00052 | AA58: =IF(AB58="","",AB58*X58/1) -> 188.46823 | AB58: =IF(Z58="","",Z58*1/W58) -> 2 | AC58: 24 de Junho | AD58: =V58 -> 1.26523 | AE58: -6.62 | AF58: 0 | AG58: =-X58 -> -94.234116 | AH58: =IF(AG58="","",AG58+AF58+AE58) -> -100.85412 | AI58: =IF(AD58="","",IF(L58="Long",AD58-U58,U58-AD58)) -> -0.00026 | AJ58: =IF(AI58="","",AG58*S58/X58) -> -0.01 | AK58: =IF(AI58="","",(AG58+AF58+AE58)*S58/X58) -> -0.010702506 | AL58: =Q58+AH58 -> 9322.5575 | BH58: USDCNH | BI58: =$BA$12 -> Exotics
B59: Fusion demo | C59: 130 | D59: 26 | E59: 2ª F | F59: 24 de Junho | G59: Londres | H59: Indices | I59: UK100 | J59: BSL | K59: 1m | L59: Short | M59: W | Q59: =AL58 -> 9322.5575 | R59: =IF(Q59="","",S59*Q59/100%) -> 93.225575 | S59: 0.01 | U59: 19767.6 | V59: 19775.8 | W59: =IF(V59="","",IF(L59="Long",U59-V59,V59-U59)) -> 8.2 | X59: =IF(W59="","",R59) -> 93.225575 | Y59: 19747.8 | Z59: =IF(Y59="","",IF(L59="Long",Y59-U59,U59-Y59)) -> 19.8 | AA59: =IF(AB59="","",AB59*X59/1) -> 225.10566 | AB59: =IF(Z59="","",Z59*1/W59) -> 2.4146341 | AC59: 24 de Junho | AD59: =Y59 -> 19747.8 | AE59: 0 | AF59: 0 | AG59: =AA59 -> 225.10566 | AH59: =IF(AG59="","",AG59+AF59+AE59) -> 225.10566 | AI59: =IF(AD59="","",IF(L59="Long",AD59-U59,U59-AD59)) -> 19.8 | AJ59: =IF(AI59="","",AG59*S59/X59) -> 0.024146341 | AK59: =IF(AI59="","",(AG59+AF59+AE59)*S59/X59) -> 0.024146341 | AL59: =Q59+AH59 -> 9547.6632 | BH59: USDCZK | BI59: =$BA$12 -> Exotics
B60: Fusion demo | C60: 131 | D60: 26 | E60: 2ª F | F60: 24 de Junho | G60: NY | H60: Majors | I60: GBPUSD | J60: BSL | K60: 1m | L60: Short | Q60: =AL59 -> 9547.6632 | R60: =IF(Q60="","",S60*Q60/100%) -> 95.476632 | S60: 0.01 | U60: 1.26908 | V60: 1.2699 | W60: =IF(V60="","",IF(L60="Long",U60-V60,V60-U60)) -> 0.00082 | X60: =IF(W60="","",R60) -> 95.476632 | Y60: 1.2675 | Z60: =IF(Y60="","",IF(L60="Long",Y60-U60,U60-Y60)) -> 0.00158 | AA60: =IF(AB60="","",AB60*X60/1) -> 183.96717 | AB60: =IF(Z60="","",Z60*1/W60) -> 1.9268293 | AC60: 24 de Junho | AD60: 1.26876 | AE60: -2.48 | AF60: 0 | AG60: 13 | AH60: =IF(AG60="","",AG60+AF60+AE60) -> 10.52 | AI60: =IF(AD60="","",IF(L60="Long",AD60-U60,U60-AD60)) -> 0.00032 | AJ60: =IF(AI60="","",AG60*S60/X60) -> 0.0013615897 | AK60: =IF(AI60="","",(AG60+AF60+AE60)*S60/X60) -> 0.0011018403 | AL60: =Q60+AH60 -> 9558.1832 | BH60: USDDKK | BI60: =$BA$12 -> Exotics
B61: FTMO challenge 1 | C61: 132 | D61: 26 | E61: 3ª F | F61: 25 de Junho | G61: Londres | H61: Majors | I61: EURUSD | J61: SSL | K61: 2m | L61: Long | M61: W | Q61: =AL60 -> 9558.1832 | R61: =IF(Q61="","",S61*Q61/100%) -> 95.581832 | S61: 0.01 | U61: 1.07267 | V61: 1.07218 | W61: =IF(V61="","",IF(L61="Long",U61-V61,V61-U61)) -> 0.00049 | X61: =IF(W61="","",R61) -> 95.581832 | Y61: 1.07346 | Z61: =IF(Y61="","",IF(L61="Long",Y61-U61,U61-Y61)) -> 0.00079 | AA61: =IF(AB61="","",AB61*X61/1) -> 154.10132 | AB61: =IF(Z61="","",Z61*1/W61) -> 1.6122449 | AC61: 25 de Junho | AD61: 1.07305 | AE61: -3.28 | AF61: 0 | AG61: =AA61 -> 154.10132 | AH61: =IF(AG61="","",AG61+AF61+AE61) -> 150.82132 | AI61: =IF(AD61="","",IF(L61="Long",AD61-U61,U61-AD61)) -> 0.00038 | AJ61: =IF(AI61="","",AG61*S61/X61) -> 0.016122449 | AK61: =IF(AI61="","",(AG61+AF61+AE61)*S61/X61) -> 0.015779288 | AL61: =Q61+AH61 -> 9709.0045 | BH61: USDHKD | BI61: =$BA$12 -> Exotics
B62: Fusion demo | C62: 133 | D62: 26 | E62: 4ª F | F62: 26 de Junho | G62: Londres | H62: Indices | I62: UK100 | J62: BSL | K62: 2m | L62: Short | M62: L | Q62: =AL61 -> 9709.0045 | R62: =IF(Q62="","",S62*Q62/100%) -> 97.090045 | S62: 0.01 | U62: 19803.4 | V62: 19811.4 | W62: =IF(V62="","",IF(L62="Long",U62-V62,V62-U62)) -> 8 | X62: =IF(W62="","",R62) -> 97.090045 | Y62: 19780.4 | Z62: =IF(Y62="","",IF(L62="Long",Y62-U62,U62-Y62)) -> 23 | AA62: =IF(AB62="","",AB62*X62/1) -> 279.13388 | AB62: =IF(Z62="","",Z62*1/W62) -> 2.875 | AC62: 26 de Junho | AD62: =V62 -> 19811.4 | AE62: 0 | AF62: 0 | AG62: =-X62 -> -97.090045 | AH62: =IF(AG62="","",AG62+AF62+AE62) -> -97.090045 | AI62: =IF(AD62="","",IF(L62="Long",AD62-U62,U62-AD62)) -> -8 | AJ62: =IF(AI62="","",AG62*S62/X62) -> -0.01 | AK62: =IF(AI62="","",(AG62+AF62+AE62)*S62/X62) -> -0.01 | AL62: =Q62+AH62 -> 9611.9145 | BH62: USDHUF | BI62: =$BA$12 -> Exotics
B63: FTMO challenge 1 | C63: 134 | D63: 26 | E63: 4ª F | F63: 26 de Junho | G63: NY | H63: Majors | I63: USDCAD | J63: BSL | K63: 2m | L63: Short | M63: W | Q63: =AL62 -> 9611.9145 | R63: =IF(Q63="","",S63*Q63/100%) -> 96.119145 | S63: 0.01 | U63: 1.36898 | V63: 1.36949 | W63: =IF(V63="","",IF(L63="Long",U63-V63,V63-U63)) -> 0.00051 | X63: =IF(W63="","",R63) -> 96.119145 | Y63: 1.3684 | Z63: =IF(Y63="","",IF(L63="Long",Y63-U63,U63-Y63)) -> 0.00058 | AA63: =IF(AB63="","",AB63*X63/1) -> 109.31197 | AB63: =IF(Z63="","",Z63*1/W63) -> 1.1372549 | AC63: 26 de Junho | AD63: =Y63 -> 1.3684 | AE63: -4.12 | AF63: 0 | AG63: =AA63 -> 109.31197 | AH63: =IF(AG63="","",AG63+AF63+AE63) -> 105.19197 | AI63: =IF(AD63="","",IF(L63="Long",AD63-U63,U63-AD63)) -> 0.00058 | AJ63: =IF(AI63="","",AG63*S63/X63) -> 0.011372549 | AK63: =IF(AI63="","",(AG63+AF63+AE63)*S63/X63) -> 0.010943914 | AL63: =Q63+AH63 -> 9717.1064 | BH63: USDMXN | BI63: =$BA$12 -> Exotics
B64: FTMO challenge 1 | C64: 135 | D64: 26 | E64: 5ª F | F64: 27 de Junho | G64: Londres | H64: Majors | I64: EURUSD | J64: BSL | K64: 4m | L64: Short | M64: W | Q64: =AL63 -> 9717.1064 | R64: =IF(Q64="","",S64*Q64/100%) -> 97.171064 | S64: 0.01 | U64: 1.06951 | V64: 1.06991 | W64: =IF(V64="","",IF(L64="Long",U64-V64,V64-U64)) -> 0.0004 | X64: =IF(W64="","",R64) -> 97.171064 | Y64: 1.06871 | Z64: =IF(Y64="","",IF(L64="Long",Y64-U64,U64-Y64)) -> 0.0008 | AA64: =IF(AB64="","",AB64*X64/1) -> 194.34213 | AB64: =IF(Z64="","",Z64*1/W64) -> 2 | AC64: 27 de Junho | AD64: =Y64 -> 1.06871 | AE64: -3.7 | AF64: 0 | AG64: =AA64 -> 194.34213 | AH64: =IF(AG64="","",AG64+AF64+AE64) -> 190.64213 | AI64: =IF(AD64="","",IF(L64="Long",AD64-U64,U64-AD64)) -> 0.0008 | AJ64: =IF(AI64="","",AG64*S64/X64) -> 0.02 | AK64: =IF(AI64="","",(AG64+AF64+AE64)*S64/X64) -> 0.019619228 | AL64: =Q64+AH64 -> 9907.7486 | BH64: USDNOK | BI64: =$BA$12 -> Exotics
B65: FTMO challenge 1 | C65: 136 | D65: 27 | E65: 2ª F | F65: 1 de Julho | G65: Londres | H65: Majors | I65: EURUSD | J65: BSL | K65: 15m | L65: Short | Q65: =AL64 -> 9907.7486 | R65: =IF(Q65="","",S65*Q65/100%) -> 99.077486 | S65: 0.01 | U65: 1.07649 | V65: 1.07734 | W65: =IF(V65="","",IF(L65="Long",U65-V65,V65-U65)) -> 0.00085 | X65: =IF(W65="","",R65) -> 99.077486 | Y65: 1.07477 | Z65: =IF(Y65="","",IF(L65="Long",Y65-U65,U65-Y65)) -> 0.00172 | AA65: =IF(AB65="","",AB65*X65/1) -> 200.48621 | AB65: =IF(Z65="","",Z65*1/W65) -> 2.0235294 | AC65: 1 de Julho | AD65: 1.0762 | AE65: -1.78 | AF65: 0 | AG65: 26 | AH65: =IF(AG65="","",AG65+AF65+AE65) -> 24.22 | AI65: =IF(AD65="","",IF(L65="Long",AD65-U65,U65-AD65)) -> 0.00029 | AJ65: =IF(AI65="","",AG65*S65/X65) -> 0.0026242087 | AK65: =IF(AI65="","",(AG65+AF65+AE65)*S65/X65) -> 0.0024445513 | AL65: =Q65+AH65 -> 9931.9686 | BH65: USDPLN | BI65: =$BA$12 -> Exotics
B66: Fusion demo | C66: 137 | D66: 27 | E66: 3ª F | F66: 2 de Julho | G66: NY | H66: Indices | I66: UK100 | J66: BSL | K66: 1m | L66: Short | M66: W | Q66: =AL65 -> 9931.9686 | R66: =IF(Q66="","",S66*Q66/100%) -> 99.319686 | S66: 0.01 | U66: 19855.7 | V66: 19885.2 | W66: =IF(V66="","",IF(L66="Long",U66-V66,V66-U66)) -> 29.5 | X66: =IF(W66="","",R66) -> 99.319686 | Y66: 19803.8 | Z66: =IF(Y66="","",IF(L66="Long",Y66-U66,U66-Y66)) -> 51.9 | AA66: =IF(AB66="","",AB66*X66/1) -> 174.73531 | AB66: =IF(Z66="","",Z66*1/W66) -> 1.759322 | AC66: 2 de Julho | AD66: =Y66 -> 19803.8 | AE66: 0 | AF66: 0 | AG66: =AA66 -> 174.73531 | AH66: =IF(AG66="","",AG66+AF66+AE66) -> 174.73531 | AI66: =IF(AD66="","",IF(L66="Long",AD66-U66,U66-AD66)) -> 51.9 | AJ66: =IF(AI66="","",AG66*S66/X66) -> 0.01759322 | AK66: =IF(AI66="","",(AG66+AF66+AE66)*S66/X66) -> 0.01759322 | AL66: =Q66+AH66 -> 10106.704 | BH66: USDRUB | BI66: =$BA$12 -> Exotics
B67: FTMO challenge 1 | C67: 138 | D67: 27 | E67: 4ª F | F67: 3 de Julho | G67: Londres | H67: Majors | I67: EURUSD | J67: BSL | K67: 4m | L67: Short | M67: W | Q67: =AL66 -> 10106.704 | R67: =IF(Q67="","",S67*Q67/100%) -> 101.06704 | S67: 0.01 | U67: 1.07578 | V67: 1.0764 | W67: =IF(V67="","",IF(L67="Long",U67-V67,V67-U67)) -> 0.00062 | X67: =IF(W67="","",R67) -> 101.06704 | Y67: 1.07454 | Z67: =IF(Y67="","",IF(L67="Long",Y67-U67,U67-Y67)) -> 0.00124 | AA67: =IF(AB67="","",AB67*X67/1) -> 202.13408 | AB67: =IF(Z67="","",Z67*1/W67) -> 2 | AC67: 3 de Julho | AD67: 1.07545 | AE67: -2.48 | AF67: 0 | AG67: 50 | AH67: =IF(AG67="","",AG67+AF67+AE67) -> 47.52 | AI67: =IF(AD67="","",IF(L67="Long",AD67-U67,U67-AD67)) -> 0.00033 | AJ67: =IF(AI67="","",AG67*S67/X67) -> 0.0049472113 | AK67: =IF(AI67="","",(AG67+AF67+AE67)*S67/X67) -> 0.0047018297 | AL67: =Q67+AH67 -> 10154.224 | BH67: USDSEK | BI67: =$BA$12 -> Exotics
B68: FTMO challenge 1 | C68: 139 | D68: 27 | E68: 4ª F | F68: 3 de Julho | G68: Londres | H68: Majors | I68: EURUSD | J68: BSL | K68: 4m | L68: Short | M68: W | Q68: =AL67 -> 10154.224 | R68: =IF(Q68="","",S68*Q68/100%) -> 101.54224 | S68: 0.01 | U68: 1.07601 | V68: 1.0764 | W68: =IF(V68="","",IF(L68="Long",U68-V68,V68-U68)) -> 0.00039 | X68: =IF(W68="","",R68) -> 101.54224 | Y68: 1.07454 | Z68: =IF(Y68="","",IF(L68="Long",Y68-U68,U68-Y68)) -> 0.00147 | AA68: =IF(AB68="","",AB68*X68/1) -> 382.73613 | AB68: =IF(Z68="","",Z68*1/W68) -> 3.7692308 | AC68: 3 de Julho | AD68: 1.07545 | AE68: -4.04 | AF68: 0 | AG68: 150 | AH68: =IF(AG68="","",AG68+AF68+AE68) -> 145.96 | AI68: =IF(AD68="","",IF(L68="Long",AD68-U68,U68-AD68)) -> 0.00056 | AJ68: =IF(AI68="","",AG68*S68/X68) -> 0.014772178 | AK68: =IF(AI68="","",(AG68+AF68+AE68)*S68/X68) -> 0.014374314 | AL68: =Q68+AH68 -> 10300.184 | BH68: USDTHB | BI68: =$BA$12 -> Exotics
B69: FTMO challenge 1 | C69: 140 | D69: 27 | E69: 5ª F | F69: 4 de Julho | G69: Londres | H69: Majors | I69: USDCAD | J69: SSL | K69: 1m | L69: Long | M69: L | Q69: =AL68 -> 10300.184 | R69: =IF(Q69="","",S69*Q69/100%) -> 103.00184 | S69: 0.01 | U69: 1.36233 | V69: 1.36193 | W69: =IF(V69="","",IF(L69="Long",U69-V69,V69-U69)) -> 0.0004 | X69: =IF(W69="","",R69) -> 103.00184 | Y69: 1.36344 | Z69: =IF(Y69="","",IF(L69="Long",Y69-U69,U69-Y69)) -> 0.00111 | AA69: =IF(AB69="","",AB69*X69/1) -> 285.8301 | AB69: =IF(Z69="","",Z69*1/W69) -> 2.775 | AC69: 4 de Julho | AD69: =V69 -> 1.36193 | AE69: -5.14 | AF69: 0 | AG69: =-X69 -> -103.00184 | AH69: =IF(AG69="","",AG69+AF69+AE69) -> -108.14184 | AI69: =IF(AD69="","",IF(L69="Long",AD69-U69,U69-AD69)) -> -0.0004 | AJ69: =IF(AI69="","",AG69*S69/X69) -> -0.01 | AK69: =IF(AI69="","",(AG69+AF69+AE69)*S69/X69) -> -0.01049902 | AL69: =Q69+AH69 -> 10192.042 | BH69: USDTRY | BI69: =$BA$12 -> Exotics
B70: FTMO challenge 1 | C70: 141 | D70: 29 | E70: 2ª F | F70: 15 de Julho | G70: NY | H70: Majors | I70: GBPUSD | J70: SSL | K70: 2m | L70: Long | M70: L | Q70: =AL69 -> 10192.042 | R70: =IF(Q70="","",S70*Q70/100%) -> 101.92042 | S70: 0.01 | U70: 1.29791 | V70: 1.29734 | W70: =IF(V70="","",IF(L70="Long",U70-V70,V70-U70)) -> 0.00057 | X70: =IF(W70="","",R70) -> 101.92042 | Y70: 1.29905 | Z70: =IF(Y70="","",IF(L70="Long",Y70-U70,U70-Y70)) -> 0.00114 | AA70: =IF(AB70="","",AB70*X70/1) -> 203.84084 | AB70: =IF(Z70="","",Z70*1/W70) -> 2 | AC70: 15 de Julho | AD70: =V70 -> 1.29734 | AE70: -5.42 | AF70: 0 | AG70: =-X70 -> -101.92042 | AH70: =IF(AG70="","",AG70+AF70+AE70) -> -107.34042 | AI70: =IF(AD70="","",IF(L70="Long",AD70-U70,U70-AD70)) -> -0.00057 | AJ70: =IF(AI70="","",AG70*S70/X70) -> -0.01 | AK70: =IF(AI70="","",(AG70+AF70+AE70)*S70/X70) -> -0.010531787 | AL70: =Q70+AH70 -> 10084.702 | BH70: USDZAR | BI70: =$BA$12 -> Exotics
B71: FTMO challenge 1 | C71: 142 | D71: 29 | E71: 4ª F | F71: 17 de Julho | G71: Londres | H71: Majors | I71: EURUSD | J71: BSL | K71: 1m | L71: Short | M71: L | Q71: =AL70 -> 10084.702 | R71: =IF(Q71="","",S71*Q71/100%) -> 100.84702 | S71: 0.01 | U71: 1.09392 | V71: 1.09434 | W71: =IF(V71="","",IF(L71="Long",U71-V71,V71-U71)) -> 0.00042 | X71: =IF(W71="","",R71) -> 100.84702 | Y71: 1.09265 | Z71: =IF(Y71="","",IF(L71="Long",Y71-U71,U71-Y71)) -> 0.00127 | AA71: =IF(AB71="","",AB71*X71/1) -> 304.94217 | AB71: =IF(Z71="","",Z71*1/W71) -> 3.0238095 | AC71: 17 de Julho | AD71: =V71 -> 1.09434 | AE71: -7.1 | AF71: 0 | AG71: =-X71 -> -100.84702 | AH71: =IF(AG71="","",AG71+AF71+AE71) -> -107.94702 | AI71: =IF(AD71="","",IF(L71="Long",AD71-U71,U71-AD71)) -> -0.00042 | AJ71: =IF(AI71="","",AG71*S71/X71) -> -0.01 | AK71: =IF(AI71="","",(AG71+AF71+AE71)*S71/X71) -> -0.010704037 | AL71: =Q71+AH71 -> 9976.7546 | BH71: XAGEUR | BI71: =$BA$14 -> Futures
B72: FTMO challenge 1 | C72: 143 | D72: 29 | E72: 5ª F | F72: 18 de Junho | G72: Londres | H72: Majors | I72: EURUSD | J72: SSL | K72: 3m | L72: Long | M72: L | Q72: =AL71 -> 9976.7546 | R72: =IF(Q72="","",S72*Q72/100%) -> 99.767546 | S72: 0.01 | U72: 1.09341 | V72: 1.09299 | W72: =IF(V72="","",IF(L72="Long",U72-V72,V72-U72)) -> 0.00042 | X72: =IF(W72="","",R72) -> 99.767546 | Y72: 1.09429 | Z72: =IF(Y72="","",IF(L72="Long",Y72-U72,U72-Y72)) -> 0.00088 | AA72: =IF(AB72="","",AB72*X72/1) -> 209.03676 | AB72: =IF(Z72="","",Z72*1/W72) -> 2.0952381 | AC72: 18 de Julho | AD72: =V72 -> 1.09299 | AE72: -7.36 | AF72: 0 | AG72: =-X72 -> -99.767546 | AH72: =IF(AG72="","",AG72+AF72+AE72) -> -107.12755 | AI72: =IF(AD72="","",IF(L72="Long",AD72-U72,U72-AD72)) -> -0.00042 | AJ72: =IF(AI72="","",AG72*S72/X72) -> -0.01 | AK72: =IF(AI72="","",(AG72+AF72+AE72)*S72/X72) -> -0.010737715 | AL72: =Q72+AH72 -> 9869.627 | BH72: XAGUSD | BI72: =$BA$14 -> Futures
B73: FTMO challenge 1 | C73: 144 | D73: 29 | E73: 5ª F | F73: 18 de Junho | G73: NY | H73: Majors | I73: GBPUSD | J73: FVG | K73: 1m | L73: Long | M73: L | Q73: =AL72 -> 9869.627 | R73: =IF(Q73="","",S73*Q73/100%) -> 98.69627 | S73: 0.01 | U73: 1.29809 | V73: 1.29768 | W73: =IF(V73="","",IF(L73="Long",U73-V73,V73-U73)) -> 0.00041 | X73: =IF(W73="","",R73) -> 98.69627 | Y73: 1.29957 | Z73: =IF(Y73="","",IF(L73="Long",Y73-U73,U73-Y73)) -> 0.00148 | AA73: =IF(AB73="","",AB73*X73/1) -> 356.26946 | AB73: =IF(Z73="","",Z73*1/W73) -> 3.6097561 | AC73: 18 de Julho | AD73: =V73 -> 1.29768 | AE73: -3.68 | AF73: 0 | AG73: =-X73 -> -98.69627 | AH73: =IF(AG73="","",AG73+AF73+AE73) -> -102.37627 | AI73: =IF(AD73="","",IF(L73="Long",AD73-U73,U73-AD73)) -> -0.00041 | AJ73: =IF(AI73="","",AG73*S73/X73) -> -0.01 | AK73: =IF(AI73="","",(AG73+AF73+AE73)*S73/X73) -> -0.010372861 | AL73: =Q73+AH73 -> 9767.2508 | BH73: XNGUSD | BI73: =$BA$14 -> Futures
B74: FTMO challenge 1 | C74: 145 | D74: 30 | E74: 2ª F | F74: 22 de Julho | G74: Londres | H74: Majors | I74: EURUSD | J74: SSL | K74: 1m | L74: Long | M74: L | Q74: =AL73 -> 9767.2508 | R74: =IF(Q74="","",S74*Q74/100%) -> 97.672508 | S74: 0.01 | U74: 1.08873 | V74: 1.08834 | W74: =IF(V74="","",IF(L74="Long",U74-V74,V74-U74)) -> 0.00039 | X74: =IF(W74="","",R74) -> 97.672508 | Y74: 1.08917 | Z74: =IF(Y74="","",IF(L74="Long",Y74-U74,U74-Y74)) -> 0.00044 | AA74: =IF(AB74="","",AB74*X74/1) -> 110.19462 | AB74: =IF(Z74="","",Z74*1/W74) -> 1.1282051 | AC74: 22 de Julho | AD74: =V74 -> 1.08834 | AE74: -7.78 | AF74: 0 | AG74: =-X74 -> -97.672508 | AH74: =IF(AG74="","",AG74+AF74+AE74) -> -105.45251 | AI74: =IF(AD74="","",IF(L74="Long",AD74-U74,U74-AD74)) -> -0.00039 | AJ74: =IF(AI74="","",AG74*S74/X74) -> -0.01 | AK74: =IF(AI74="","",(AG74+AF74+AE74)*S74/X74) -> -0.010796539 | AL74: =Q74+AH74 -> 9661.7983 | BH74: XTIUSD | BI74: =$BA$14 -> Futures
B75: FTMO challenge 1 | C75: 146 | D75: 30 | E75: 2ª F | F75: 22 de Julho | G75: Londres | H75: Majors | I75: EURUSD | J75: SSL | K75: 1m | L75: Long | M75: L | Q75: =AL74 -> 9661.7983 | R75: =IF(Q75="","",S75*Q75/100%) -> 96.617983 | S75: 0.01 | U75: 1.0885 | V75: 1.0881 | W75: =IF(V75="","",IF(L75="Long",U75-V75,V75-U75)) -> 0.0004 | X75: =IF(W75="","",R75) -> 96.617983 | Y75: 1.0893 | Z75: =IF(Y75="","",IF(L75="Long",Y75-U75,U75-Y75)) -> 0.0008 | AA75: =IF(AB75="","",AB75*X75/1) -> 193.23597 | AB75: =IF(Z75="","",Z75*1/W75) -> 2 | AC75: 22 de Julho | AD75: =V75 -> 1.0881 | AE75: -7.5 | AF75: 0 | AG75: =-X75 -> -96.617983 | AH75: =IF(AG75="","",AG75+AF75+AE75) -> -104.11798 | AI75: =IF(AD75="","",IF(L75="Long",AD75-U75,U75-AD75)) -> -0.0004 | AJ75: =IF(AI75="","",AG75*S75/X75) -> -0.01 | AK75: =IF(AI75="","",(AG75+AF75+AE75)*S75/X75) -> -0.010776253 | AL75: =Q75+AH75 -> 9557.6803 | BH75: XBRUSD | BI75: =$BA$14 -> Futures
B76: FTMO challenge 1 | C76: 147 | D76: 30 | E76: 2ª F | F76: 22 de Julho | G76: Londres | H76: Majors | I76: EURUSD | J76: SSL | K76: 3m | L76: Long | M76: W | Q76: =AL75 -> 9557.6803 | R76: =IF(Q76="","",S76*Q76/100%) -> 95.576803 | S76: 0.01 | U76: 1.08857 | V76: 1.08803 | W76: =IF(V76="","",IF(L76="Long",U76-V76,V76-U76)) -> 0.00054 | X76: =IF(W76="","",R76) -> 95.576803 | Y76: 1.08965 | Z76: =IF(Y76="","",IF(L76="Long",Y76-U76,U76-Y76)) -> 0.00108 | AA76: =IF(AB76="","",AB76*X76/1) -> 191.15361 | AB76: =IF(Z76="","",Z76*1/W76) -> 2 | AC76: 22 de Julho | AD76: 1.08908 | AE76: -5.34 | AF76: 0 | AG76: =AA76 -> 191.15361 | AH76: =IF(AG76="","",AG76+AF76+AE76) -> 185.81361 | AI76: =IF(AD76="","",IF(L76="Long",AD76-U76,U76-AD76)) -> 0.00051 | AJ76: =IF(AI76="","",AG76*S76/X76) -> 0.02 | AK76: =IF(AI76="","",(AG76+AF76+AE76)*S76/X76) -> 0.019441287 | AL76: =Q76+AH76 -> 9743.4939 | BH76: XPTUSD | BI76: =$BA$14 -> Futures
B77: FTMO challenge 1 | C77: 148 | D77: 30 | E77: 2ª F | F77: 22 de Julho | G77: NY | H77: Majors | I77: GBPUSD | J77: BSL | K77: 4m | L77: Short | M77: W | Q77: =AL76 -> 9743.4939 | R77: =IF(Q77="","",S77*Q77/100%) -> 97.434939 | S77: 0.01 | U77: 1.2935 | V77: 1.29425 | W77: =IF(V77="","",IF(L77="Long",U77-V77,V77-U77)) -> 0.00075 | X77: =IF(W77="","",R77) -> 97.434939 | Y77: 1.29218 | Z77: =IF(Y77="","",IF(L77="Long",Y77-U77,U77-Y77)) -> 0.00132 | AA77: =IF(AB77="","",AB77*X77/1) -> 171.48549 | AB77: =IF(Z77="","",Z77*1/W77) -> 1.76 | AC77: 22 de Julho | AD77: =Y77 -> 1.29218 | AE77: -4 | AF77: 0 | AG77: =AA77 -> 171.48549 | AH77: =IF(AG77="","",AG77+AF77+AE77) -> 167.48549 | AI77: =IF(AD77="","",IF(L77="Long",AD77-U77,U77-AD77)) -> 0.00132 | AJ77: =IF(AI77="","",AG77*S77/X77) -> 0.0176 | AK77: =IF(AI77="","",(AG77+AF77+AE77)*S77/X77) -> 0.01718947 | AL77: =Q77+AH77 -> 9910.9794 | BH77: XPDUSD | BI77: =$BA$14 -> Futures
B78: FTMO challenge 1 | C78: 149 | D78: 30 | E78: 3ª F | F78: 23 de Julho | G78: Londres | H78: Majors | I78: GBPUSD | J78: SSL | K78: 5m | L78: Long | M78: L | Q78: =AL77 -> 9910.9794 | R78: =IF(Q78="","",S78*Q78/100%) -> 99.109794 | S78: 0.01 | U78: 1.29201 | V78: 1.29138 | W78: =IF(V78="","",IF(L78="Long",U78-V78,V78-U78)) -> 0.00063 | X78: =IF(W78="","",R78) -> 99.109794 | Y78: 1.29327 | Z78: =IF(Y78="","",IF(L78="Long",Y78-U78,U78-Y78)) -> 0.00126 | AA78: =IF(AB78="","",AB78*X78/1) -> 198.21959 | AB78: =IF(Z78="","",Z78*1/W78) -> 2 | AC78: 23 de Julho | AD78: =V78 -> 1.29138 | AE78: -4.78 | AF78: 0 | AG78: =-X78 -> -99.109794 | AH78: =IF(AG78="","",AG78+AF78+AE78) -> -103.88979 | AI78: =IF(AD78="","",IF(L78="Long",AD78-U78,U78-AD78)) -> -0.00063 | AJ78: =IF(AI78="","",AG78*S78/X78) -> -0.01 | AK78: =IF(AI78="","",(AG78+AF78+AE78)*S78/X78) -> -0.010482293 | AL78: =Q78+AH78 -> 9807.0896 | BH78: XAUEUR | BI78: =$BA$14 -> Futures
B79: FTMO challenge 1 | C79: 150 | D79: 30 | E79: 3ª F | F79: 23 de Julho | G79: Londres | H79: Majors | I79: EURUSD | J79: SSL | K79: 1m | L79: Long | M79: L | Q79: =AL78 -> 9807.0896 | R79: =IF(Q79="","",S79*Q79/100%) -> 98.070896 | S79: 0.01 | U79: 1.08757 | V79: 1.08706 | W79: =IF(V79="","",IF(L79="Long",U79-V79,V79-U79)) -> 0.00051 | X79: =IF(W79="","",R79) -> 98.070896 | Y79: 1.08887 | Z79: =IF(Y79="","",IF(L79="Long",Y79-U79,U79-Y79)) -> 0.0013 | AA79: =IF(AB79="","",AB79*X79/1) -> 249.98464 | AB79: =IF(Z79="","",Z79*1/W79) -> 2.5490196 | AC79: 23 de Julho | AD79: =V79 -> 1.08706 | AE79: -5.96 | AF79: 0 | AG79: =-X79 -> -98.070896 | AH79: =IF(AG79="","",AG79+AF79+AE79) -> -104.0309 | AI79: =IF(AD79="","",IF(L79="Long",AD79-U79,U79-AD79)) -> -0.00051 | AJ79: =IF(AI79="","",AG79*S79/X79) -> -0.01 | AK79: =IF(AI79="","",(AG79+AF79+AE79)*S79/X79) -> -0.010607724 | AL79: =Q79+AH79 -> 9703.0587 | BH79: XAUUSD | BI79: =$BA$14 -> Futures
B80: FTMO challenge 1 | C80: 151 | D80: 30 | E80: 4ª F | F80: 24 de Julho | G80: Londres | H80: Majors | I80: EURUSD | J80: SSL | K80: 3m | L80: Long | M80: W | Q80: =AL79 -> 9703.0587 | R80: =IF(Q80="","",S80*Q80/100%) -> 97.030587 | S80: 0.01 | U80: 1.08345 | V80: 1.08274 | W80: =IF(V80="","",IF(L80="Long",U80-V80,V80-U80)) -> 0.00071 | X80: =IF(W80="","",R80) -> 97.030587 | Y80: 1.085 | Z80: =IF(Y80="","",IF(L80="Long",Y80-U80,U80-Y80)) -> 0.00155 | AA80: =IF(AB80="","",AB80*X80/1) -> 211.82734 | AB80: =IF(Z80="","",Z80*1/W80) -> 2.1830986 | AC80: 24 de Julho | AD80: =Y80 -> 1.085 | AE80: -4.01 | AF80: 0 | AG80: =AA80 -> 211.82734 | AH80: =IF(AG80="","",AG80+AF80+AE80) -> 207.81734 | AI80: =IF(AD80="","",IF(L80="Long",AD80-U80,U80-AD80)) -> 0.00155 | AJ80: =IF(AI80="","",AG80*S80/X80) -> 0.021830986 | AK80: =IF(AI80="","",(AG80+AF80+AE80)*S80/X80) -> 0.021417714 | AL80: =Q80+AH80 -> 9910.876 | BH80: XAUAUD | BI80: =$BA$14 -> Futures
B81: FTMO challenge 1 | C81: 152 | D81: 30 | E81: 5ª F | F81: 25 de Julho | G81: Londres | H81: Majors | I81: GBPUSD | J81: SSL | K81: 2m | L81: Long | M81: L | Q81: =AL80 -> 9910.876 | R81: =IF(Q81="","",S81*Q81/100%) -> 99.10876 | S81: 0.01 | U81: 1.28836 | V81: 1.28791 | W81: =IF(V81="","",IF(L81="Long",U81-V81,V81-U81)) -> 0.00045 | X81: =IF(W81="","",R81) -> 99.10876 | Y81: 1.28956 | Z81: =IF(Y81="","",IF(L81="Long",Y81-U81,U81-Y81)) -> 0.0012 | AA81: =IF(AB81="","",AB81*X81/1) -> 264.29003 | AB81: =IF(Z81="","",Z81*1/W81) -> 2.6666667 | AC81: 25 de Julho | AD81: =V81 -> 1.28791 | AE81: -6.48 | AF81: 0 | AG81: =-X81 -> -99.10876 | AH81: =IF(AG81="","",AG81+AF81+AE81) -> -105.58876 | AI81: =IF(AD81="","",IF(L81="Long",AD81-U81,U81-AD81)) -> -0.00045 | AJ81: =IF(AI81="","",AG81*S81/X81) -> -0.01 | AK81: =IF(AI81="","",(AG81+AF81+AE81)*S81/X81) -> -0.010653827 | AL81: =Q81+AH81 -> 9805.2873 | BH81: SUGAR | BI81: =$BA$14 -> Futures
B82: FTMO challenge 1 | C82: 153 | D82: 30 | E82: 5ª F | F82: 25 de Julho | G82: Londres | H82: Majors | I82: EURUSD | J82: SSL | K82: 1m | L82: Long | M82: W | Q82: =AL81 -> 9805.2873 | R82: =IF(Q82="","",S82*Q82/100%) -> 98.052873 | S82: 0.01 | U82: 1.08321 | V82: 1.08278 | W82: =IF(V82="","",IF(L82="Long",U82-V82,V82-U82)) -> 0.00043 | X82: =IF(W82="","",R82) -> 98.052873 | Y82: 1.08398 | Z82: =IF(Y82="","",IF(L82="Long",Y82-U82,U82-Y82)) -> 0.00077 | AA82: =IF(AB82="","",AB82*X82/1) -> 175.58305 | AB82: =IF(Z82="","",Z82*1/W82) -> 1.7906977 | AC82: 25 de Julho | AD82: =Y82 -> 1.08398 | AE82: -6.56 | AF82: 0 | AG82: =AA82 -> 175.58305 | AH82: =IF(AG82="","",AG82+AF82+AE82) -> 169.02305 | AI82: =IF(AD82="","",IF(L82="Long",AD82-U82,U82-AD82)) -> 0.00077 | AJ82: =IF(AI82="","",AG82*S82/X82) -> 0.017906977 | AK82: =IF(AI82="","",(AG82+AF82+AE82)*S82/X82) -> 0.01723795 | AL82: =Q82+AH82 -> 9974.3103 | BH82: DE30 | BI82: indices
B83: FTMO challenge 1 | C83: 154 | D83: 30 | E83: 6ª F | F83: 26 de Julho | G83: Londres | H83: Majors | I83: GBPUSD | J83: OB | K83: 2m | L83: Short | M83: L | Q83: =AL82 -> 9974.3103 | R83: =IF(Q83="","",S83*Q83/100%) -> 99.743103 | S83: 0.01 | U83: 1.28642 | V83: 1.28704 | W83: =IF(V83="","",IF(L83="Long",U83-V83,V83-U83)) -> 0.00062 | X83: =IF(W83="","",R83) -> 99.743103 | Y83: 1.28456 | Z83: =IF(Y83="","",IF(L83="Long",Y83-U83,U83-Y83)) -> 0.00186 | AA83: =IF(AB83="","",AB83*X83/1) -> 299.22931 | AB83: =IF(Z83="","",Z83*1/W83) -> 3 | AC83: 26 de Julhp | AD83: =V83 -> 1.28704 | AE83: -4.98 | AF83: 0 | AG83: =-X83 -> -99.743103 | AH83: =IF(AG83="","",AG83+AF83+AE83) -> -104.7231 | AI83: =IF(AD83="","",IF(L83="Long",AD83-U83,U83-AD83)) -> -0.00062 | AJ83: =IF(AI83="","",AG83*S83/X83) -> -0.01 | AK83: =IF(AI83="","",(AG83+AF83+AE83)*S83/X83) -> -0.010499283 | AL83: =Q83+AH83 -> 9869.5872 | BH83: Nasdaq | BI83: Futures
B84: FTMO challenge 1 | C84: 155 | D84: 30 | E84: 6ª F | F84: 26 de Julho | G84: Londres | H84: Majors | I84: GBPUSD | J84: OB | K84: 2m | L84: Short | M84: L | Q84: =AL83 -> 9869.5872 | R84: =IF(Q84="","",S84*Q84/100%) -> 98.695872 | S84: 0.01 | U84: 1.2865 | V84: 1.28694 | W84: =IF(V84="","",IF(L84="Long",U84-V84,V84-U84)) -> 0.00044 | X84: =IF(W84="","",R84) -> 98.695872 | Y84: 1.28517 | Z84: =IF(Y84="","",IF(L84="Long",Y84-U84,U84-Y84)) -> 0.00133 | AA84: =IF(AB84="","",AB84*X84/1) -> 298.3307 | AB84: =IF(Z84="","",Z84*1/W84) -> 3.0227273 | AC84: 26 de Julho | AD84: =V84 -> 1.28694 | AE84: -6.78 | AF84: 0 | AG84: =-X84 -> -98.695872 | AH84: =IF(AG84="","",AG84+AF84+AE84) -> -105.47587 | AI84: =IF(AD84="","",IF(L84="Long",AD84-U84,U84-AD84)) -> -0.00044 | AJ84: =IF(AI84="","",AG84*S84/X84) -> -0.01 | AK84: =IF(AI84="","",(AG84+AF84+AE84)*S84/X84) -> -0.010686959 | AL84: =Q84+AH84 -> 9764.1113
B85: FTMO challenge 1 | C85: 156 | D85: 31 | E85: 2ª F | F85: 29 de Julho | G85: NY | H85: Majors | I85: GBPUSD | J85: FVG | K85: 1m | L85: Long | M85: W | Q85: =AL84 -> 9764.1113 | R85: =IF(Q85="","",S85*Q85/100%) -> 97.641113 | S85: 0.01 | U85: 1.2828 | V85: 1.28232 | W85: =IF(V85="","",IF(L85="Long",U85-V85,V85-U85)) -> 0.00048 | X85: =IF(W85="","",R85) -> 97.641113 | Y85: 1.28358 | Z85: =IF(Y85="","",IF(L85="Long",Y85-U85,U85-Y85)) -> 0.00078 | AA85: =IF(AB85="","",AB85*X85/1) -> 158.66681 | AB85: =IF(Z85="","",Z85*1/W85) -> 1.625 | AC85: 29 de Julho | AD85: =Y85 -> 1.28358 | AE85: -6.54 | AF85: 0 | AG85: =AA85 -> 158.66681 | AH85: =IF(AG85="","",AG85+AF85+AE85) -> 152.12681 | AI85: =IF(AD85="","",IF(L85="Long",AD85-U85,U85-AD85)) -> 0.00078 | AJ85: =IF(AI85="","",AG85*S85/X85) -> 0.01625 | AK85: =IF(AI85="","",(AG85+AF85+AE85)*S85/X85) -> 0.0155802 | AL85: =Q85+AH85 -> 9916.2382
B86: FTMO challenge 1 | C86: 157 | D86: 31 | E86: 3ª F | F86: 30 de Julho | G86: NY | H86: Majors | I86: EURUSD | J86: SSL | K86: 2m | L86: Long | M86: L | Q86: =AL85 -> 9916.2382 | R86: =IF(Q86="","",S86*Q86/100%) -> 99.162382 | S86: 0.01 | U86: 1.08097 | V86: 1.0801 | W86: =IF(V86="","",IF(L86="Long",U86-V86,V86-U86)) -> 0.00087 | X86: =IF(W86="","",R86) -> 99.162382 | Y86: 1.08271 | Z86: =IF(Y86="","",IF(L86="Long",Y86-U86,U86-Y86)) -> 0.00174 | AA86: =IF(AB86="","",AB86*X86/1) -> 198.32476 | AB86: =IF(Z86="","",Z86*1/W86) -> 2 | AC86: 30 de Julho | AD86: =V86 -> 1.0801 | AE86: -3.16 | AF86: 0 | AG86: =-X86 -> -99.162382 | AH86: =IF(AG86="","",AG86+AF86+AE86) -> -102.32238 | AI86: =IF(AD86="","",IF(L86="Long",AD86-U86,U86-AD86)) -> -0.00087 | AJ86: =IF(AI86="","",AG86*S86/X86) -> -0.01 | AK86: =IF(AI86="","",(AG86+AF86+AE86)*S86/X86) -> -0.010318669 | AL86: =Q86+AH86 -> 9813.9158
B87: FTMO challenge 1 | C87: 158 | D87: 31 | E87: 4ª F | F87: 31 de Julho | G87: NY | H87: Majors | I87: EURUSD | J87: BSL | K87: 2m | L87: Short | M87: L | Q87: =AL86 -> 9813.9158 | R87: =IF(Q87="","",S87*Q87/100%) -> 98.139158 | S87: 0.01 | U87: 1.08311 | V87: 1.08364 | W87: =IF(V87="","",IF(L87="Long",U87-V87,V87-U87)) -> 0.00053 | X87: =IF(W87="","",R87) -> 98.139158 | Y87: 1.08204 | Z87: =IF(Y87="","",IF(L87="Long",Y87-U87,U87-Y87)) -> 0.00107 | AA87: =IF(AB87="","",AB87*X87/1) -> 198.13 | AB87: =IF(Z87="","",Z87*1/W87) -> 2.0188679 | AC87: 31 de Julho | AD87: =V87 -> 1.08364 | AE87: -7.56 | AF87: 0 | AG87: =-X87 -> -98.139158 | AH87: =IF(AG87="","",AG87+AF87+AE87) -> -105.69916 | AI87: =IF(AD87="","",IF(L87="Long",AD87-U87,U87-AD87)) -> -0.00053 | AJ87: =IF(AI87="","",AG87*S87/X87) -> -0.01 | AK87: =IF(AI87="","",(AG87+AF87+AE87)*S87/X87) -> -0.010770335 | AL87: =Q87+AH87 -> 9708.2166
B88: FTMO challenge 1 | C88: 159 | D88: 31 | E88: 5ª F | F88: 1 de Agosto | G88: Londres | H88: Majors | I88: GBPUSD | J88: SSL | K88: 1m | L88: Long | M88: L | Q88: =AL87 -> 9708.2166 | R88: =IF(Q88="","",S88*Q88/100%) -> 97.082166 | S88: 0.01 | U88: 1.27967 | V88: 1.27877 | W88: =IF(V88="","",IF(L88="Long",U88-V88,V88-U88)) -> 0.0009 | X88: =IF(W88="","",R88) -> 97.082166 | Y88: 1.282 | Z88: =IF(Y88="","",IF(L88="Long",Y88-U88,U88-Y88)) -> 0.00233 | AA88: =IF(AB88="","",AB88*X88/1) -> 251.33494 | AB88: =IF(Z88="","",Z88*1/W88) -> 2.5888889 | AC88: 1 de Agosto | AD88: =V88 -> 1.27877 | AE88: -3.11 | AF88: 0 | AG88: =-X88 -> -97.082166 | AH88: =IF(AG88="","",AG88+AF88+AE88) -> -100.19217 | AI88: =IF(AD88="","",IF(L88="Long",AD88-U88,U88-AD88)) -> -0.0009 | AJ88: =IF(AI88="","",AG88*S88/X88) -> -0.01 | AK88: =IF(AI88="","",(AG88+AF88+AE88)*S88/X88) -> -0.010320347 | AL88: =Q88+AH88 -> 9608.0245
B89: FTMO challenge 1 | C89: 160 | D89: 31 | E89: 6ª F | F89: 2 de Agosto | G89: Londres | H89: Majors | I89: EURUSD | J89: BSL | K89: 1m | L89: Short | M89: L | Q89: =AL88 -> 9608.0245 | R89: =IF(Q89="","",S89*Q89/100%) -> 96.080245 | S89: 0.01 | U89: 1.08055 | V89: 1.08108 | W89: =IF(V89="","",IF(L89="Long",U89-V89,V89-U89)) -> 0.00053 | X89: =IF(W89="","",R89) -> 96.080245 | Y89: 1.07952 | Z89: =IF(Y89="","",IF(L89="Long",Y89-U89,U89-Y89)) -> 0.00103 | AA89: =IF(AB89="","",AB89*X89/1) -> 186.72198 | AB89: =IF(Z89="","",Z89*1/W89) -> 1.9433962 | AC89: 2 de Agosto | AD89: =V89 -> 1.08108 | AE89: -5.3 | AF89: 0 | AG89: =-X89 -> -96.080245 | AH89: =IF(AG89="","",AG89+AF89+AE89) -> -101.38024 | AI89: =IF(AD89="","",IF(L89="Long",AD89-U89,U89-AD89)) -> -0.00053 | AJ89: =IF(AI89="","",AG89*S89/X89) -> -0.01 | AK89: =IF(AI89="","",(AG89+AF89+AE89)*S89/X89) -> -0.010551622 | AL89: =Q89+AH89 -> 9506.6442
B90: FTMO challenge 1 | C90: 161 | D90: 31 | E90: 6ª F | F90: 2 de Agosto | G90: NY | H90: Majors | I90: EURUSD | J90: BSL | K90: 1m | L90: Short | M90: L | Q90: =AL89 -> 9506.6442 | R90: =IF(Q90="","",S90*Q90/100%) -> 95.066442 | S90: 0.01 | U90: 1.08205 | V90: 1.08255 | W90: =IF(V90="","",IF(L90="Long",U90-V90,V90-U90)) -> 0.0005 | X90: =IF(W90="","",R90) -> 95.066442 | Y90: 1.07952 | Z90: =IF(Y90="","",IF(L90="Long",Y90-U90,U90-Y90)) -> 0.00253 | AA90: =IF(AB90="","",AB90*X90/1) -> 481.0362 | AB90: =IF(Z90="","",Z90*1/W90) -> 5.06 | AC90: 2 de Agosto | AD90: =V90 -> 1.08255 | AE90: -5.94 | AF90: 0 | AG90: =-X90 -> -95.066442 | AH90: =IF(AG90="","",AG90+AF90+AE90) -> -101.00644 | AI90: =IF(AD90="","",IF(L90="Long",AD90-U90,U90-AD90)) -> -0.0005 | AJ90: =IF(AI90="","",AG90*S90/X90) -> -0.01 | AK90: =IF(AI90="","",(AG90+AF90+AE90)*S90/X90) -> -0.010624826 | AL90: =Q90+AH90 -> 9405.6378
B91: FTMO challenge 1 | C91: 162 | D91: 32 | E91: 2ª F | F91: 5 de Agosto | G91: NY | H91: Futures | I91: Nasdaq | J91: SSL | K91: 1m | L91: Long | Q91: =AL90 -> 9405.6378 | R91: =IF(Q91="","",S91*Q91/100%) -> 94.056378 | S91: 0.01 | U91: 17393.85 | V91: 17307.93 | W91: =IF(V91="","",IF(L91="Long",U91-V91,V91-U91)) -> 85.92 | X91: =IF(W91="","",R91) -> 94.056378 | Y91: 17714.9 | Z91: =IF(Y91="","",IF(L91="Long",Y91-U91,U91-Y91)) -> 321.05 | AA91: =IF(AB91="","",AB91*X91/1) -> 351.45251 | AB91: =IF(Z91="","",Z91*1/W91) -> 3.7366155 | AC91: 5 de Agosto | AD91: 17358.45 | AE91: 0 | AF91: 0 | AG91: -30 | AH91: =IF(AG91="","",AG91+AF91+AE91) -> -30 | AI91: =IF(AD91="","",IF(L91="Long",AD91-U91,U91-AD91)) -> -35.4 | AJ91: =IF(AI91="","",AG91*S91/X91) -> -0.0031895764 | AK91: =IF(AI91="","",(AG91+AF91+AE91)*S91/X91) -> -0.0031895764 | AL91: =Q91+AH91 -> 9375.6378
Q92: =AL91 -> 9375.6378 | R92: =IF(Q92="","",S92*Q92/100%) -> 93.756378 | S92: 0.01 | W92: =IF(V92="","",IF(L92="Long",U92-V92,V92-U92)) | X92: =IF(W92="","",R92) | Z92: =IF(Y92="","",IF(L92="Long",Y92-U92,U92-Y92)) | AA92: =IF(AB92="","",AB92*X92/1) | AB92: =IF(Z92="","",Z92*1/W92) | AF92: 0 | AH92: =IF(AG92="","",AG92+AF92+AE92) | AI92: =IF(AD92="","",IF(L92="Long",AD92-U92,U92-AD92)) | AJ92: =IF(AI92="","",AG92*S92/X92) | AK92: =IF(AI92="","",(AG92+AF92+AE92)*S92/X92) | AL92: =Q92+AH92 -> #VALUE!
Q93: =AL92 -> #VALUE! | R93: =IF(Q93="","",S93*Q93/100%) -> #VALUE! | S93: 0.01 | W93: =IF(V93="","",IF(L93="Long",U93-V93,V93-U93)) | X93: =IF(W93="","",R93) | Z93: =IF(Y93="","",IF(L93="Long",Y93-U93,U93-Y93)) | AA93: =IF(AB93="","",AB93*X93/1) | AB93: =IF(Z93="","",Z93*1/W93) | AF93: 0 | AH93: =IF(AG93="","",AG93+AF93+AE93) | AI93: =IF(AD93="","",IF(L93="Long",AD93-U93,U93-AD93)) | AJ93: =IF(AI93="","",AG93*S93/X93) | AK93: =IF(AI93="","",(AG93+AF93+AE93)*S93/X93) | AL93: =Q93+AH93 -> #VALUE!
Q94: =AL93 -> #VALUE! | R94: =IF(Q94="","",S94*Q94/100%) -> #VALUE! | S94: 0.01 | W94: =IF(V94="","",IF(L94="Long",U94-V94,V94-U94)) | X94: =IF(W94="","",R94) | Z94: =IF(Y94="","",IF(L94="Long",Y94-U94,U94-Y94)) | AA94: =IF(AB94="","",AB94*X94/1) | AB94: =IF(Z94="","",Z94*1/W94) | AF94: 0 | AH94: =IF(AG94="","",AG94+AF94+AE94) | AI94: =IF(AD94="","",IF(L94="Long",AD94-U94,U94-AD94)) | AJ94: =IF(AI94="","",AG94*S94/X94) | AK94: =IF(AI94="","",(AG94+AF94+AE94)*S94/X94) | AL94: =Q94+AH94 -> #VALUE!
Q95: =AL94 -> #VALUE! | R95: =IF(Q95="","",S95*Q95/100%) -> #VALUE! | S95: 0.01 | W95: =IF(V95="","",IF(L95="Long",U95-V95,V95-U95)) | X95: =IF(W95="","",R95) | Z95: =IF(Y95="","",IF(L95="Long",Y95-U95,U95-Y95)) | AA95: =IF(AB95="","",AB95*X95/1) | AB95: =IF(Z95="","",Z95*1/W95) | AF95: 0 | AH95: =IF(AG95="","",AG95+AF95+AE95) | AI95: =IF(AD95="","",IF(L95="Long",AD95-U95,U95-AD95)) | AJ95: =IF(AI95="","",AG95*S95/X95) | AK95: =IF(AI95="","",(AG95+AF95+AE95)*S95/X95) | AL95: =Q95+AH95 -> #VALUE!
Q96: =AL95 -> #VALUE! | R96: =IF(Q96="","",S96*Q96/100%) -> #VALUE! | S96: 0.01 | W96: =IF(V96="","",IF(L96="Long",U96-V96,V96-U96)) | X96: =IF(W96="","",R96) | Z96: =IF(Y96="","",IF(L96="Long",Y96-U96,U96-Y96)) | AA96: =IF(AB96="","",AB96*X96/1) | AB96: =IF(Z96="","",Z96*1/W96) | AF96: 0 | AH96: =IF(AG96="","",AG96+AF96+AE96) | AI96: =IF(AD96="","",IF(L96="Long",AD96-U96,U96-AD96)) | AJ96: =IF(AI96="","",AG96*S96/X96) | AK96: =IF(AI96="","",(AG96+AF96+AE96)*S96/X96) | AL96: =Q96+AH96 -> #VALUE!
Q97: =AL96 -> #VALUE! | R97: =IF(Q97="","",S97*Q97/100%) -> #VALUE! | S97: 0.01 | W97: =IF(V97="","",IF(L97="Long",U97-V97,V97-U97)) | X97: =IF(W97="","",R97) | Z97: =IF(Y97="","",IF(L97="Long",Y97-U97,U97-Y97)) | AA97: =IF(AB97="","",AB97*X97/1) | AB97: =IF(Z97="","",Z97*1/W97) | AF97: 0 | AH97: =IF(AG97="","",AG97+AF97+AE97) | AI97: =IF(AD97="","",IF(L97="Long",AD97-U97,U97-AD97)) | AJ97: =IF(AI97="","",AG97*S97/X97) | AK97: =IF(AI97="","",(AG97+AF97+AE97)*S97/X97) | AL97: =Q97+AH97 -> #VALUE!
Q98: =AL97 -> #VALUE! | R98: =IF(Q98="","",S98*Q98/100%) -> #VALUE! | S98: 0.01 | W98: =IF(V98="","",IF(L98="Long",U98-V98,V98-U98)) | X98: =IF(W98="","",R98) | Z98: =IF(Y98="","",IF(L98="Long",Y98-U98,U98-Y98)) | AA98: =IF(AB98="","",AB98*X98/1) | AB98: =IF(Z98="","",Z98*1/W98) | AF98: 0 | AH98: =IF(AG98="","",AG98+AF98+AE98) | AI98: =IF(AD98="","",IF(L98="Long",AD98-U98,U98-AD98)) | AJ98: =IF(AI98="","",AG98*S98/X98) | AK98: =IF(AI98="","",(AG98+AF98+AE98)*S98/X98) | AL98: =Q98+AH98 -> #VALUE!
Q99: =AL98 -> #VALUE! | R99: =IF(Q99="","",S99*Q99/100%) -> #VALUE! | S99: 0.01 | W99: =IF(V99="","",IF(L99="Long",U99-V99,V99-U99)) | X99: =IF(W99="","",R99) | Z99: =IF(Y99="","",IF(L99="Long",Y99-U99,U99-Y99)) | AA99: =IF(AB99="","",AB99*X99/1) | AB99: =IF(Z99="","",Z99*1/W99) | AF99: 0 | AH99: =IF(AG99="","",AG99+AF99+AE99) | AI99: =IF(AD99="","",IF(L99="Long",AD99-U99,U99-AD99)) | AJ99: =IF(AI99="","",AG99*S99/X99) | AK99: =IF(AI99="","",(AG99+AF99+AE99)*S99/X99) | AL99: =Q99+AH99 -> #VALUE!
Q100: =AL99 -> #VALUE! | R100: =IF(Q100="","",S100*Q100/100%) -> #VALUE! | S100: 0.01 | W100: =IF(V100="","",IF(L100="Long",U100-V100,V100-U100)) | X100: =IF(W100="","",R100) | Z100: =IF(Y100="","",IF(L100="Long",Y100-U100,U100-Y100)) | AA100: =IF(AB100="","",AB100*X100/1) | AB100: =IF(Z100="","",Z100*1/W100) | AF100: 0 | AH100: =IF(AG100="","",AG100+AF100+AE100) | AI100: =IF(AD100="","",IF(L100="Long",AD100-U100,U100-AD100)) | AJ100: =IF(AI100="","",AG100*S100/X100) | AK100: =IF(AI100="","",(AG100+AF100+AE100)*S100/X100) | AL100: =Q100+AH100 -> #VALUE!
Q101: =AL100 -> #VALUE! | R101: =IF(Q101="","",S101*Q101/100%) -> #VALUE! | S101: 0.01 | W101: =IF(V101="","",IF(L101="Long",U101-V101,V101-U101)) | X101: =IF(W101="","",R101) | Z101: =IF(Y101="","",IF(L101="Long",Y101-U101,U101-Y101)) | AA101: =IF(AB101="","",AB101*X101/1) | AB101: =IF(Z101="","",Z101*1/W101) | AF101: 0 | AH101: =IF(AG101="","",AG101+AF101+AE101) | AI101: =IF(AD101="","",IF(L101="Long",AD101-U101,U101-AD101)) | AJ101: =IF(AI101="","",AG101*S101/X101) | AK101: =IF(AI101="","",(AG101+AF101+AE101)*S101/X101) | AL101: =Q101+AH101 -> #VALUE!
R102: =IF(Q102="","",S102*Q102/100%) | W102: =IF(V102="","",IF(L102="Long",U102-V102,V102-U102)) | X102: =IF(W102="","",R102) | Z102: =IF(Y102="","",IF(L102="Long",Y102-U102,U102-Y102)) | AA102: =IF(AB102="","",AB102*X102/1) | AB102: =IF(Z102="","",Z102*1/W102) | AH102: =IF(AG102="","",AG102+AF102+AE102) | AI102: =IF(AD102="","",IF(L102="Long",AD102-U102,U102-AD102)) | AJ102: =IF(AI102="","",AG102*S102/X102) | AK102: =IF(AI102="","",(AG102+AF102+AE102)*S102/X102)
...

Sheet Statistics
A3: Nº Entradas/Dia semana | B3: 2ª Feira | C3: 3ª Feira | D3: 4ª Feira | E3: 5ª Feira | F3: 6ª Feira
B4: =COUNTIF('Registo de operações'!$E$11:$E$1001,'Registo de operações'!AS10) -> 22 | C4: =COUNTIF('Registo de operações'!$E$11:$E$211,'Registo de operações'!AS11) -> 15 | D4: =COUNTIF('Registo de operações'!$E$11:$E$211,'Registo de operações'!AS12) -> 17 | E4: =COUNTIF('Registo de operações'!$E$11:$E$211,'Registo de operações'!AS13) -> 18 | F4: =COUNTIF('Registo de operações'!$E$11:$E$211,'Registo de operações'!AS14) -> 9
A5: Acerto: | B5: =COUNTIFS('Registo de operações'!$E$11:$E$1001,'Registo de operações'!$AS$10,'Registo de operações'!$M$11:$M$1001,'Registo de operações'!$AW$10) -> 8 | C5: =COUNTIFS('Registo de operações'!$E$11:$E$1001,'Registo de operações'!$AS$11,'Registo de operações'!$M$11:$M$1001,'Registo de operações'!$AW$10) -> 9 | D5: =COUNTIFS('Registo de operações'!$E$11:$E$1001,'Registo de operações'!$AS$12,'Registo de operações'!$M$11:$M$1001,'Registo de operações'!$AW$10) -> 4 | E5: =COUNTIFS('Registo de operações'!$E$11:$E$1001,'Registo de operações'!$AS$13,'Registo de operações'!$M$11:$M$1001,'Registo de operações'!$AW$10) -> 5 | F5: =COUNTIFS('Registo de operações'!$E$11:$E$1001,'Registo de operações'!$AS$14,'Registo de operações'!$M$11:$M$1001,'Registo de operações'!$AW$10) -> 1
A6: Perda: | B6: =COUNTIFS('Registo de operações'!$E$11:$E$1001,'Registo de operações'!$AS$10,'Registo de operações'!$M$11:$M$1001,'Registo de operações'!$AW$11) -> 10 | C6: =COUNTIFS('Registo de operações'!$E$11:$E$1001,'Registo de operações'!$AS$11,'Registo de operações'!$M$11:$M$1001,'Registo de operações'!$AW$11) -> 6 | D6: =COUNTIFS('Registo de operações'!$E$11:$E$1001,'Registo de operações'!$AS$12,'Registo de operações'!$M$11:$M$1001,'Registo de operações'!$AW$11) -> 12 | E6: =COUNTIFS('Registo de operações'!$E$11:$E$1001,'Registo de operações'!$AS$13,'Registo de operações'!$M$11:$M$1001,'Registo de operações'!$AW$11) -> 12 | F6: =COUNTIFS('Registo de operações'!$E$11:$E$1001,'Registo de operações'!$AS$14,'Registo de operações'!$M$11:$M$1001,'Registo de operações'!$AW$11) -> 7
A7: Taxa de Acerto: | B7: =B5/B4 -> 0.36363636 | C7: =C5/C4 -> 0.6 | D7: =D5/D4 -> 0.23529412 | E7: =E5/E4 -> 0.27777778 | F7: =F5/F4 -> 0.11111111
A8: Manhã
A9: Tarde
A12: Marcos Temporais | B12: 3 Minutos | C12: 5 Minutos | D12: 15 Minutos | E12: 30 Minutos | F12: 1 Hora | G12: 2 Horas | H12: 4 Horas | I12: 8 Horas | J12: 1 Dia | K12: 1 Semana
B13: =COUNTIF('Registo de operações'!$K$11:$K$211,'Registo de operações'!AV19) -> 7 | C13: =COUNTIF('Registo de operações'!$K$11:$K$211,'Registo de operações'!$AV$18) -> 5 | D13: =COUNTIF('Registo de operações'!$K$11:$K$211,'Registo de operações'!$AV$17) -> 1 | E13: =COUNTIF('Registo de operações'!$K$11:$K$211,'Registo de operações'!$AV$16) -> 1 | F13: =COUNTIF('Registo de operações'!$K$11:$K$211,'Registo de operações'!$AV$15) -> 0 | G13: =COUNTIF('Registo de operações'!$K$11:$K$211,'Registo de operações'!$AV$14) -> 0 | H13: =COUNTIF('Registo de operações'!$K$11:$K$211,'Registo de operações'!$AV$13) -> 0 | I13: =COUNTIF('Registo de operações'!$K$11:$K$211,'Registo de operações'!$AV$12) -> 0 | J13: =COUNTIF('Registo de operações'!$K$11:$K$211,'Registo de operações'!$AV$10) -> 0 | K13: =COUNTIF('Registo de operações'!$K$11:$K$211,'Registo de operações'!$AV$20) -> 0
A14: Acerto: | B14: =COUNTIFS('Registo de operações'!$K$11:$K$1001,'Registo de operações'!$AV$19,'Registo de operações'!$M$11:$M$1001,'Registo de operações'!$AW$10) -> 3 | C14: =COUNTIFS('Registo de operações'!$K$11:$K$1001,'Registo de operações'!$AV$18,'Registo de operações'!$M$11:$M$1001,'Registo de operações'!$AW$10) -> 1 | D14: =COUNTIFS('Registo de operações'!$K$11:$K$1001,'Registo de operações'!$AV$17,'Registo de operações'!$M$11:$M$1001,'Registo de operações'!$AW$10) -> 0 | E14: =COUNTIFS('Registo de operações'!$K$11:$K$1001,'Registo de operações'!$AV$16,'Registo de operações'!$M$11:$M$1001,'Registo de operações'!$AW$10) -> 0 | F14: =COUNTIFS('Registo de operações'!$K$11:$K$1001,'Registo de operações'!$AV$15,'Registo de operações'!$M$11:$M$1001,'Registo de operações'!$AW$10) -> 0 | G14: =COUNTIFS('Registo de operações'!$K$11:$K$1001,'Registo de operações'!$AV$14,'Registo de operações'!$M$11:$M$1001,'Registo de operações'!$AW$10) -> 0 | H14: =COUNTIFS('Registo de operações'!$K$11:$K$1001,'Registo de operações'!$AV$13,'Registo de operações'!$M$11:$M$1001,'Registo de operações'!$AW$10) -> 0 | I14: =COUNTIFS('Registo de operações'!$K$11:$K$1001,'Registo de operações'!$AV$12,'Registo de operações'!$M$11:$M$1001,'Registo de operações'!$AW$10) -> 0 | J14: =COUNTIFS('Registo de operações'!$K$11:$K$1001,'Registo de operações'!$AV$10,'Registo de operações'!$M$11:$M$1001,'Registo de operações'!$AW$10) -> 0 | K14: =COUNTIFS('Registo de operações'!$K$11:$K$1001,'Registo de operações'!$AV$20,'Registo de operações'!$M$11:$M$1001,'Registo de operações'!$AW$10) -> 0
A15: Perda: | B15: =COUNTIFS('Registo de operações'!$K$11:$K$1001,'Registo de operações'!$AV$19,'Registo de operações'!$M$11:$M$1001,'Registo de operações'!$AW$11) -> 3 | C15: =COUNTIFS('Registo de operações'!$K$11:$K$1001,'Registo de operações'!$AV$18,'Registo de operações'!$M$11:$M$1001,'Registo de operações'!$AW$11) -> 4 | D15: =COUNTIFS('Registo de operações'!$K$11:$K$1001,'Registo de operações'!$AV$17,'Registo de operações'!$M$11:$M$1001,'Registo de operações'!$AW$11) -> 0 | E15: =COUNTIFS('Registo de operações'!$K$11:$K$1001,'Registo de operações'!$AV$16,'Registo de operações'!$M$11:$M$1001,'Registo de operações'!$AW$11) -> 1 | F15: =COUNTIFS('Registo de operações'!$K$11:$K$1001,'Registo de operações'!$AV$15,'Registo de operações'!$M$11:$M$1001,'Registo de operações'!$AW$11) -> 0 | G15: =COUNTIFS('Registo de operações'!$K$11:$K$1001,'Registo de operações'!$AV$14,'Registo de operações'!$M$11:$M$1001,'Registo de operações'!$AW$11) -> 0 | H15: =COUNTIFS('Registo de operações'!$K$11:$K$1001,'Registo de operações'!$AV$13,'Registo de operações'!$M$11:$M$1001,'Registo de operações'!$AW$11) -> 0 | I15: =COUNTIFS('Registo de operações'!$K$11:$K$1001,'Registo de operações'!$AV$12,'Registo de operações'!$M$11:$M$1001,'Registo de operações'!$AW$11) -> 0 | J15: =COUNTIFS('Registo de operações'!$K$11:$K$1001,'Registo de operações'!$AV$10,'Registo de operações'!$M$11:$M$1001,'Registo de operações'!$AW$11) -> 0 | K15: =COUNTIFS('Registo de operações'!$K$11:$K$1001,'Registo de operações'!$AV$20,'Registo de operações'!$M$11:$M$1001,'Registo de operações'!$AW$11) -> 0
A16: Taxa de Acerto: | B16: =B14/B13 -> 0.42857143 | C16: =C14/C13 -> 0.2 | D16: =D14/D13 -> 0 | E16: =E14/E13 -> 0 | F16: =F14/F13 -> #DIV/0! | G16: =G14/G13 -> #DIV/0! | H16: =H14/H13 -> #DIV/0! | I16: =I14/I13 -> #DIV/0! | ... K16: =K14/K13 -> #DIV/0!
A17: Estratégia
A18: Breakout
A19: Bandeira
A20: Retest
A22: Entradas por estratégia | B22: BreakOut | C22: Bandeira | D22: Retest | E22: Total
B23: =COUNTIF('Registo de operações'!$J$11:$J$1001,'Registo de operações'!AU11) -> 25 | C23: =COUNTIF('Registo de operações'!$J$11:$J$1001,'Registo de operações'!AU12) -> 2 | D23: =COUNTIF('Registo de operações'!$J$11:$J$1001,'Registo de operações'!AU10) -> 26 | E23: =SUM(B23:D23) -> 53
A24: Acerto: | B24: =COUNTIFS('Registo de operações'!$J$11:$J$1001,'Registo de operações'!$AU$11,'Registo de operações'!$M$11:$M$1001,'Registo de operações'!AW10) -> 8 | C24: =COUNTIFS('Registo de operações'!$J$11:$J$1001,'Registo de operações'!$AU$12,'Registo de operações'!$M$11:$M$1001,'Registo de operações'!AW10) -> 1 | D24: =COUNTIFS('Registo de operações'!$J$11:$J$1001,'Registo de operações'!$AU$10,'Registo de operações'!$M$11:$M$1001,'Registo de operações'!AW10) -> 10
A25: Perda: | B25: =COUNTIFS('Registo de operações'!$J$11:$J$1001,'Registo de operações'!$AU$11,'Registo de operações'!$M$11:$M$1001,'Registo de operações'!AW11) -> 15 | C25: =COUNTIFS('Registo de operações'!$J$11:$J$1001,'Registo de operações'!$AU$12,'Registo de operações'!$M$11:$M$1001,'Registo de operações'!AW11) -> 1 | D25: =COUNTIFS('Registo de operações'!$J$11:$J$1001,'Registo de operações'!$AU$10,'Registo de operações'!$M$11:$M$1001,'Registo de operações'!AW11) -> 13
A26: Taxa de Acerto estratégia: | B26: =B24/B23 -> 0.32 | C26: =C24/C23 -> 0.5 | D26: =D24/D23 -> 0.38461538

Sheet Evolução de Conta

Sheet Pontuação
H1: Majors | I1: Minors | J1: Exotics | K1: Breakout | M1: Retest
B2: =SUM(B5:B204) -> 0.43638742 | C2: =SUM(C5:C204) -> -0.43733417 | D2: =SUM(D5:D204) -> 4242.6641 | E2: =SUM(E5:E204) -> -4302.8764 | G2: W | H2: =COUNTIFS(#REF!,"Majors",$L$11:$L$210,"W") -> #REF! | I2: =COUNTIFS(#REF!,"Minors",$L$11:$L$210,"W") -> #REF! | J2: =COUNTIFS(#REF!,"Exotics",$L$11:$L$210,"W") -> #REF! | K2: 6 | L2: =K2*100%/#REF! -> #REF! | M2: 11 | N2: =M2*100%/$C$5 -> -1100
B3: =AVERAGE(B5:B204) -> 0.014546247 | C3: =AVERAGE(C5:C204) -> -0.0089251872 | D3: =AVERAGE(D5:D204) -> 141.42214 | E3: =AVERAGE(E5:E204) -> -87.813803 | G3: L | H3: =H4-H2 -> #REF! | I3: =I4-I2 -> #REF! | J3: =J4-J2 -> #REF! | K3: 7 | L3: =K3*100%/#REF! -> #REF! | M3: 14 | N3: =M3*100%/$C$5 -> -1400
A4: Nº T | B4: Ganhos % | C4: Perdas % | D4: Ganhos € | E4: Perdas € | G4: Total | H4: =COUNTIF(#REF!,"MAJORS") -> #REF! | I4: =COUNTIF(#REF!,"minors") -> #REF! | J4: =COUNTIF(#REF!,"Exotics") -> #REF! | K4: =SUM(K2:K3) -> 13 | L4: =SUM(L2:L3) -> #REF! | M4: =SUM(M2:M3) -> 25 | N4: =SUM(N2:N3) -> -2500
A5: ='Registo de operações'!C11 -> 77 | B5: =IF('Registo de operações'!AJ11>0,'Registo de operações'!AJ11,"") | C5: =IF('Registo de operações'!AJ11<0,'Registo de operações'!AJ11,"") -> -0.01 | D5: =IF('Registo de operações'!AG11>0,'Registo de operações'!AG11,"") | E5: =IF('Registo de operações'!AG11<0,'Registo de operações'!AG11,"") -> -100
A6: ='Registo de operações'!C12 -> 78 | B6: =IF('Registo de operações'!AJ12>0,'Registo de operações'!AJ12,"") | C6: =IF('Registo de operações'!AJ12<0,'Registo de operações'!AJ12,"") -> -0.01 | D6: =IF('Registo de operações'!AG12>0,'Registo de operações'!AG12,"") | E6: =IF('Registo de operações'!AG12<0,'Registo de operações'!AG12,"") -> -98.987
A7: ='Registo de operações'!C13 -> 79 | B7: =IF('Registo de operações'!AJ13>0,'Registo de operações'!AJ13,"") | C7: =IF('Registo de operações'!AJ13<0,'Registo de operações'!AJ13,"") -> -0.01 | D7: =IF('Registo de operações'!AG13>0,'Registo de operações'!AG13,"") | E7: =IF('Registo de operações'!AG13<0,'Registo de operações'!AG13,"") -> -97.85733
A8: ='Registo de operações'!C14 -> 80 | B8: =IF('Registo de operações'!AJ14>0,'Registo de operações'!AJ14,"") | C8: =IF('Registo de operações'!AJ14<0,'Registo de operações'!AJ14,"") -> -0.01 | D8: =IF('Registo de operações'!AG14>0,'Registo de operações'!AG14,"") | E8: =IF('Registo de operações'!AG14<0,'Registo de operações'!AG14,"") -> -96.692357
A9: ='Registo de operações'!C15 -> 81 | B9: =IF('Registo de operações'!AJ15>0,'Registo de operações'!AJ15,"") -> 0.024285714 | C9: =IF('Registo de operações'!AJ15<0,'Registo de operações'!AJ15,"") | D9: =IF('Registo de operações'!AG15>0,'Registo de operações'!AG15,"") -> 231.93788 | E9: =IF('Registo de operações'!AG15<0,'Registo de operações'!AG15,"")
A10: ='Registo de operações'!C16 -> 82 | B10: =IF('Registo de operações'!AJ16>0,'Registo de operações'!AJ16,"") -> 0.029 | C10: =IF('Registo de operações'!AJ16<0,'Registo de operações'!AJ16,"") | D10: =IF('Registo de operações'!AG16>0,'Registo de operações'!AG16,"") -> 283.29262 | E10: =IF('Registo de operações'!AG16<0,'Registo de operações'!AG16,"")
A11: ='Registo de operações'!C17 -> 83 | B11: =IF('Registo de operações'!AJ17>0,'Registo de operações'!AJ17,"") -> 0.016228039 | C11: =IF('Registo de operações'!AJ17<0,'Registo de operações'!AJ17,"") | D11: =IF('Registo de operações'!AG17>0,'Registo de operações'!AG17,"") -> 163 | E11: =IF('Registo de operações'!AG17<0,'Registo de operações'!AG17,"")
A12: ='Registo de operações'!C18 -> 84 | B12: =IF('Registo de operações'!AJ18>0,'Registo de operações'!AJ18,"") | C12: =IF('Registo de operações'!AJ18<0,'Registo de operações'!AJ18,"") -> -0.01 | D12: =IF('Registo de operações'!AG18>0,'Registo de operações'!AG18,"") | E12: =IF('Registo de operações'!AG18<0,'Registo de operações'!AG18,"") -> -102.00014
A13: ='Registo de operações'!C19 -> 85 | B13: =IF('Registo de operações'!AJ19>0,'Registo de operações'!AJ19,"") -> 0.006953396 | C13: =IF('Registo de operações'!AJ19<0,'Registo de operações'!AJ19,"") | D13: =IF('Registo de operações'!AG19>0,'Registo de operações'!AG19,"") -> 70.16 | E13: =IF('Registo de operações'!AG19<0,'Registo de operações'!AG19,"")
A14: ='Registo de operações'!C20 -> 86 | B14: =IF('Registo de operações'!AJ20>0,'Registo de operações'!AJ20,"") | C14: =IF('Registo de operações'!AJ20<0,'Registo de operações'!AJ20,"") -> -0.0019882413 | D14: =IF('Registo de operações'!AG20>0,'Registo de operações'!AG20,"") | E14: =IF('Registo de operações'!AG20<0,'Registo de operações'!AG20,"") -> -20.18
A15: ='Registo de operações'!C21 -> 87 | B15: =IF('Registo de operações'!AJ21>0,'Registo de operações'!AJ21,"") | C15: =IF('Registo de operações'!AJ21<0,'Registo de operações'!AJ21,"") | D15: =IF('Registo de operações'!AG21>0,'Registo de operações'!AG21,"") | E15: =IF('Registo de operações'!AG21<0,'Registo de operações'!AG21,"")
A16: ='Registo de operações'!C22 -> 88 | B16: =IF('Registo de operações'!AJ22>0,'Registo de operações'!AJ22,"") | C16: =IF('Registo de operações'!AJ22<0,'Registo de operações'!AJ22,"") -> -0.0052185516 | D16: =IF('Registo de operações'!AG22>0,'Registo de operações'!AG22,"") | E16: =IF('Registo de operações'!AG22<0,'Registo de operações'!AG22,"") -> -52.79
... A203: ='Registo de operações'!C209 -> 0 | B203: =IF('Registo de operações'!AJ209>0,'Registo de operações'!AJ209,"") | C203: =IF('Registo de operações'!AJ209<0,'Registo de operações'!AJ209,"") | D203: =IF('Registo de operações'!AG209>0,'Registo de operações'!AG209,"") | E203: =IF('Registo de operações'!AG209<0,'Registo de operações'!AG209,"")
A204: ='Registo de operações'!C211 -> 0 | B204: =IF('Registo de operações'!AJ211>0,'Registo de operações'!AJ211,"") | C204: =IF('Registo de operações'!AJ211<0,'Registo de operações'!AJ211,"") | D204: =IF('Registo de operações'!AG211>0,'Registo de operações'!AG211,"") | E204: =IF('Registo de operações'!AG211<0,'Registo de operações'!AG211,"")
